Workbook

Sheet Como usar
A1: Planilha de cruzamento — o arquivo-mestre da pauta
A2: Jornalismo Investigativo na Prática · material bônus · alinhada aos roteiros das aulas e aos insertos de tela · setembro de 2026
A4: Como ler as cores
A5: Cabeçalho azul | B5: Você preenche.
A6: Cabeçalho cinza (auto) | B6: Fórmula automática. Não digite nessas colunas.
A7: Linha em itálico | B7: Exemplo fictício. Exclua as linhas inteiras (botão direito > Excluir) antes de usar na sua pauta. Na aba Ética da pauta, apague só o texto em itálico.
A8: Vermelho ou laranja | B8: Alerta automático. Cada alerta é uma pergunta, não uma conclusão (aula 4.6).
A9: CNPJ em vermelho | B9: O CNPJ não tem 14 caracteres. Tire pontos, barra e traço.
A11: As abas, na ordem do curso
A12: Aba | B12: Para que serve | C12: Aulas e insertos | D12: Colunas, na ordem | E12: Pronta até a linha
A13: Bombas | B13: As bombas que chegaram e qual delas vira a pauta do curso. | C13: 1.1 | D13: bomba, quem mandou, documento verificável?, interesse público? | E13: 51
A14: Linha do tempo | B14: Os fatos em ordem de data, cada um com documento e fonte. É o arquivo-mestre. | C14: 1.3, 4.1, OSINT 6.3, 7.2 | D14: data, fato, documento, fonte | E14: 501
A15: Ética da pauta | B15: Interesse público em duas linhas, conflito de interesse e quem não será exposto. | C15: 1.4 | D15: uma linha por item: interesse público, conflito de interesse, quem não será exposto | E15: 4
A16: Fontes | B16: As fontes possíveis, com a matriz de credibilidade e a ordem de abordagem. Só código ou descrição, nunca o nome. | C16: 2.1, 2.2 | D16: fonte, tipo, acesso, interesse, histórico, corroboração, ordem de abordagem | E16: 51
A17: Log | B17: De onde veio cada dado e quando: documentos, bases, pedidos, arquivos, respostas, hashes. | C17: 2.3, 3.2, 3.5, 4.6, OSINT 6.1, 6.6 e 6.7, 6.2 a 6.4 | D17: origem, data e hora, ferramenta, arquivo, código ou protocolo, hash | E17: 501
A18: Risco | B18: A matriz de risco da pauta, com a prioridade de cada risco. | C18: 2.4 | D18: risco, probabilidade, impacto, medida | E18: 51
A19: Documentos | B19: Os documentos de que a pauta precisa, quem tem e se já estão publicados. | C19: 3.1 | D19: documento, quem tem, já está publicado?, onde | E19: 101
A20: Prazos LAI | B20: O calendário de cada pedido: prazo do órgão, recurso e reclamação. | C20: 3.2 a 3.5 | D20: protocolo, órgão, esfera, pedido, data do pedido e as datas seguintes | E20: 101
A21: Pagamentos | B21: Empenhos e pagamentos, com o cruzamento do inserto 4.6. | C21: 4.2, 4.6 | D21: CNPJ do credor, nome, valor, data, fonte | E21: 2001
A22: Contratos | B22: Contratos, com data de abertura da empresa, sanção e aditivos. | C22: 4.2, 4.6 | D22: CNPJ do fornecedor, órgão, objeto, valor, modalidade, data do contrato, data de abertura (fórmula), vigência | E22: 1001
A23: Sancoes | B23: CEIS, CNEP, CEPIM e outros cadastros. “Não consta” também é resultado. | C23: 4.2 | D23: CNPJ, tipo de sanção, abrangência, período (início e fim) | E23: 301
A24: Empresas | B24: Uma linha por CNPJ, com o sinal e o resumo do que as outras abas encontraram. | C24: 4.3, 4.6 | D24: CNPJ, razão social, data de abertura, CNAE, capital social, endereço, sinal | E24: 501
... A30: Perfis | B30: Os perfis oficiais da pauta e a regra de observação. | C30: OSINT 6.5, 6.7 | D30: nome, rede, link, data de criação, cópia arquivada | E30: 201
A31: Listas | B31: Opções das listas suspensas e a frase de cada fase processual. | C31: — | D31: — | E31: —
A33: Regras de uso
A34: 1 | B34: O cabeçalho fica na linha 1 e os dados começam na linha 2. Por isso as fórmulas mostradas nas aulas, como =PROCX(A2;...), funcionam do jeito que aparecem na tela.
A35: 2 | B35: O CNPJ é a chave. Fica sempre na coluna A de Pagamentos, Contratos, Sancoes, Empresas, Socios e Eleitoral, como texto, com 14 caracteres, sem pontos, barra ou traço. Texto guarda o zero à esquerda e aceita o CNPJ com letras (aula 4.3). Copiou com pontos? Limpe numa coluna ao lado com =SUBSTITUIR(SUBSTITUIR(SUBSTITUIR(A2;".";"");"/";"");"-";"") (aula 4.6) e cole o resultado como valor.
A36: 3 | B36: Pessoa se cruza pelo nome mais os dígitos visíveis do CPF. Nunca só pelo nome (aula 4.6).
A37: 4 | B37: Todo dado entra com fonte. No Log, dê a cada registro um ID (L001, L002...) e cite esse ID na coluna Fonte das outras abas. É o que responde à pergunta “como você sabe disso?”.
A38: 5 | B38: Vínculo não é culpa. Cada alerta vira uma pergunta para os documentos e para as pessoas envolvidas (aula 4.6).
A39: 6 | B39: Fonte humana entra só por código (F1, F2) ou por descrição. Nunca o nome verdadeiro (aula 2.2).
A40: 7 | B40: Na tela, tarje CPF, endereço, telefone e o nome de sócio pessoa física, de servidor sem cargo de chefia e de cidadão comum, salvo quando forem o centro de um fato já publicado.
A41: 8 | B41: As aulas mostram PROCX. Esta planilha usa ÍNDICE e CORRESP, que dão o mesmo resultado e funcionam em qualquer Excel, no LibreOffice e no Google Planilhas. A tabela abaixo mostra a equivalência.
A42: 9 | B42: As abas Socios e Sancoes não têm acento para que as fórmulas das aulas funcionem como mostradas.
A43: 10 | B43: A aba Prazos LAI conta dias corridos a partir da data de hoje do computador. Depois da 1ª instância, segue os degraus do governo federal; em estados e municípios, confira a norma local (aula 3.3).
A44: 11 | B44: As fórmulas vão até a linha indicada na tabela das abas. Para mais linhas, copie a última linha da aba para baixo.
A45: 12 | B45: OSINT 6.1 a 6.7 são as aulas do módulo de fontes abertas, que substitui a aula 4.7.
... A47: 14 | B47: Os exemplos contam uma história fictícia de ponta a ponta, em Cidade Exemplo: siga os CNPJs da Alimentos Modelo e da Gráfica Exemplo pelas abas para ver os cruzamentos. Nomes, CNPJs, CPFs, protocolos, processos e links não existem.
A49: As fórmulas das aulas nesta planilha
A50: Na aula | B50: Nesta planilha | C50: Onde
A51: =PROCX(A2;Sancoes!A:A;Sancoes!B:B;"não consta") | B51: =SEERRO(ÍNDICE(Sancoes!B:B;CORRESP(A2;Sancoes!A:A;0));"não consta") | C51: Contratos, coluna J; Pagamentos, coluna K
A52: =PROCV(A2;Sancoes!A:C;2;FALSO) | B52: Funciona como está: o tipo de sanção fica na coluna B de Sancoes. | C52: Numa coluna nova de Contratos ou Pagamentos
A53: =CONT.SE(Socios!B:B;Pessoas!A2) | B53: Funciona como está. A coluna K de Pessoas faz o mesmo com nome e CPF, que é mais seguro. | C53: Pessoas
A54: =PROCX(A2;Empresas!A:A;Empresas!C:C) | B54: =ÍNDICE(Empresas!C:C;CORRESP(A2;Empresas!A:A;0)) | C54: Contratos, coluna G
A55: =SE(F2-G2<180;"ABERTA MENOS DE 6 MESES ANTES";"") | B55: Igual, com um aviso a mais quando o contrato é anterior à abertura. | C55: Contratos, coluna I
A56: =PROCX(A2;Empresas!A:A;Empresas!D:D;"não consta") | B56: =SEERRO(ÍNDICE(Empresas!D:D;CORRESP(A2;Empresas!A:A;0));"não consta") | C56: Pagamentos, coluna J
A57: =PROCX(A2;Eleitoral!A:A;Eleitoral!B:B;"não consta") | B57: =SEERRO(ÍNDICE(Eleitoral!B:B;CORRESP(A2;Eleitoral!A:A;0));"não consta") | C57: Pagamentos, coluna L
A58: Tabela dinâmica de pagamentos por favorecido e por ano | B58: Inserir > Tabela dinâmica sobre a aba Pagamentos: linhas, Nome; colunas, Ano; valores, soma de Valor. | C58: Pagamentos, colunas B, C e O

Sheet Bombas
A1: Bomba | B1: Quem mandou | C1: Documento verificável? | D1: Interesse público? | E1: Escolhida para o curso? | F1: Observações
A2: Print: o secretário de saúde superfatura remédio | B2: Grupo de WhatsApp, sem autor | C2: Não | D2: Sim | E2: Não | F2: EXEMPLO — fica na gaveta até aparecer um documento
A3: Áudio: o prefeito tem apartamento em Miami | B3: “O primo de alguém” | C3: Não | D3: Depende de onde veio o dinheiro | E3: Não | F3: EXEMPLO — curiosidade até prova em contrário
A4: Empresa aberta cinco meses antes ganha contrato de merenda sem licitação em Cidade Exemplo | B4: Servidor da secretaria (F1) | C4: Sim: extrato do contrato no PNCP | D4: Sim: dinheiro da merenda escolar | E4: Sim | F4: EXEMPLO — PAUTA DO CURSO

Sheet Linha do tempo
A1: Data | B1: Fato | C1: Documento | D1: Fonte | E1: Link | F1: Quem (pessoa ou empresa) | G1: Tipo | H1: Fato, indício ou versão? | I1: Registro no Log (auto) | J1: Observações
A2: 45550 | B2: Fulano de Tal doa R$ 20 mil à campanha de Sicrano Candidato a vereador | C2: Prestação de contas da campanha de 2024 | D2: L006 | F2: Fulano de Tal; Sicrano Candidato | G2: Campanha ou eleição | H2: Fato | I2: =IF(D2="","",IFERROR(IF(INDEX(Log!$I:$I,MATCH(D2,Log!$G:$G,0))&""="",INDEX(Log!$A:$A,MATCH(D2,Log!$G:$G,0))&"",INDEX(Log!$I:$I,MATCH(D2,Log!$G:$G,0))&""),IF(AND(LEN(D2)=4,LEFT(D2,1)="L",ISNUMBER(VALUE(MID(D2,2,3)))),"ID não encontrado no Log",""))) -> Bens, doadores e fornecedores de campanha de Sicrano Candidato (2024 e 2026) | J2: EXEMPLO — exclua esta linha
A3: 45555 | B3: Gráfica Exemplo recebe R$ 15 mil da campanha de Sicrano Candidato por santinhos e adesivos | C3: Prestação de contas da campanha de 2024 | D3: L006 | F3: Gráfica Exemplo Ltda; Sicrano Candidato | G3: Campanha ou eleição | H3: Fato | I3: =IF(D3="","",IFERROR(IF(INDEX(Log!$I:$I,MATCH(D3,Log!$G:$G,0))&""="",INDEX(Log!$A:$A,MATCH(D3,Log!$G:$G,0))&"",INDEX(Log!$I:$I,MATCH(D3,Log!$G:$G,0))&""),IF(AND(LEN(D3)=4,LEFT(D3,1)="L",ISNUMBER(VALUE(MID(D3,2,3)))),"ID não encontrado no Log",""))) -> Bens, doadores e fornecedores de campanha de Sicrano Candidato (2024 e 2026) | J3: EXEMPLO — exclua esta linha
A4: 45672 | B4: Fulano de Tal é nomeado assessor parlamentar no gabinete de Sicrano Candidato | C4: Ato de nomeação no diário oficial da Câmara | D4: L002 | F4: Fulano de Tal | G4: Nomeação ou exoneração | H4: Fato | I4: =IF(D4="","",IFERROR(IF(INDEX(Log!$I:$I,MATCH(D4,Log!$G:$G,0))&""="",INDEX(Log!$A:$A,MATCH(D4,Log!$G:$G,0))&"",INDEX(Log!$I:$I,MATCH(D4,Log!$G:$G,0))&""),IF(AND(LEN(D4)=4,LEFT(D4,1)="L",ISNUMBER(VALUE(MID(D4,2,3)))),"ID não encontrado no Log",""))) -> Ato de nomeação de Fulano de Tal (15/01/2025) | J4: EXEMPLO — exclua esta linha
A5: 45719 | B5: A Câmara contrata a Gráfica Exemplo por pregão, por R$ 95 mil | C5: Extrato do contrato 008/2025 | D5: L003 | F5: Gráfica Exemplo Ltda | G5: Contrato ou aditivo | H5: Fato | I5: =IF(D5="","",IFERROR(IF(INDEX(Log!$I:$I,MATCH(D5,Log!$G:$G,0))&""="",INDEX(Log!$A:$A,MATCH(D5,Log!$G:$G,0))&"",INDEX(Log!$I:$I,MATCH(D5,Log!$G:$G,0))&""),IF(AND(LEN(D5)=4,LEFT(D5,1)="L",ISNUMBER(VALUE(MID(D5,2,3)))),"ID não encontrado no Log",""))) -> Extratos dos contratos 045/2025 (dispensa) e 008/2025 (pregão) | J5: EXEMPLO — exclua esta linha
A6: 45726 | B6: Alimentos Modelo Ltda é aberta, com Fulano de Tal como sócio-administrador | C6: Cadastro CNPJ e quadro de sócios | D6: L001 | F6: Alimentos Modelo Ltda | G6: Empresa | H6: Fato | I6: =IF(D6="","",IFERROR(IF(INDEX(Log!$I:$I,MATCH(D6,Log!$G:$G,0))&""="",INDEX(Log!$A:$A,MATCH(D6,Log!$G:$G,0))&"",INDEX(Log!$I:$I,MATCH(D6,Log!$G:$G,0))&""),IF(AND(LEN(D6)=4,LEFT(D6,1)="L",ISNUMBER(VALUE(MID(D6,2,3)))),"ID não encontrado no Log",""))) -> Cadastro CNPJ e quadro de sócios da Alimentos Modelo, da Construtora Exemplo e da Gráfica Exemplo | J6: EXEMPLO — exclua esta linha
A7: 45839 | B7: Segundo fonte em off (F1), a contratação foi acertada antes do processo | C7: Nenhum ainda | D7: L011 | F7: Alimentos Modelo Ltda | G7: Contrato ou aditivo | H7: Versão | I7: =IF(D7="","",IFERROR(IF(INDEX(Log!$I:$I,MATCH(D7,Log!$G:$G,0))&""="",INDEX(Log!$A:$A,MATCH(D7,Log!$G:$G,0))&"",INDEX(Log!$I:$I,MATCH(D7,Log!$G:$G,0))&""),IF(AND(LEN(D7)=4,LEFT(D7,1)="L",ISNUMBER(VALUE(MID(D7,2,3)))),"ID não encontrado no Log",""))) -> Conversa em off com F1 sobre a contratação da merenda | J7: EXEMPLO — sem documento, é lenda: não vai ao ar sem confirmação independente
A8: 45889 | B8: Secretaria de Educação contrata a Alimentos Modelo por dispensa, por R$ 480 mil | C8: Extrato do contrato 045/2025 | D8: L003 | F8: Alimentos Modelo Ltda | G8: Contrato ou aditivo | H8: Fato | I8: =IF(D8="","",IFERROR(IF(INDEX(Log!$I:$I,MATCH(D8,Log!$G:$G,0))&""="",INDEX(Log!$A:$A,MATCH(D8,Log!$G:$G,0))&"",INDEX(Log!$I:$I,MATCH(D8,Log!$G:$G,0))&""),IF(AND(LEN(D8)=4,LEFT(D8,1)="L",ISNUMBER(VALUE(MID(D8,2,3)))),"ID não encontrado no Log",""))) -> Extratos dos contratos 045/2025 (dispensa) e 008/2025 (pregão) | J8: EXEMPLO — exclua esta linha
A9: 45930 | B9: Primeiro pagamento à Alimentos Modelo: R$ 120 mil | C9: Ordem bancária 2025OB000456 | D9: L004 | F9: Alimentos Modelo Ltda | G9: Pagamento | H9: Fato | I9: =IF(D9="","",IFERROR(IF(INDEX(Log!$I:$I,MATCH(D9,Log!$G:$G,0))&""="",INDEX(Log!$A:$A,MATCH(D9,Log!$G:$G,0))&"",INDEX(Log!$I:$I,MATCH(D9,Log!$G:$G,0))&""),IF(AND(LEN(D9)=4,LEFT(D9,1)="L",ISNUMBER(VALUE(MID(D9,2,3)))),"ID não encontrado no Log",""))) -> Empenhos e pagamentos a fornecedores, de 2023 a 2025 | J9: EXEMPLO — exclua esta linha
A10: 46154 | B10: Justiça recebe ação de improbidade sobre a contratação | C10: Decisão de recebimento da ação | D10: L007 | F10: Alimentos Modelo Ltda | G10: Processo judicial | H10: Fato | I10: =IF(D10="","",IFERROR(IF(INDEX(Log!$I:$I,MATCH(D10,Log!$G:$G,0))&""="",INDEX(Log!$A:$A,MATCH(D10,Log!$G:$G,0))&"",INDEX(Log!$I:$I,MATCH(D10,Log!$G:$G,0))&""),IF(AND(LEN(D10)=4,LEFT(D10,1)="L",ISNUMBER(VALUE(MID(D10,2,3)))),"ID não encontrado no Log",""))) -> Decisão que recebeu a ação de improbidade | J10: EXEMPLO — exclua esta linha
A11: 46289 | B11: Pedido de posicionamento enviado à empresa, ao gabinete do vereador e à Câmara | C11: E-mail com as perguntas e o prazo | D11: L012 | F11: Alimentos Modelo Ltda; Sicrano Candidato | G11: Pedido de posicionamento | H11: Fato | I11: =IF(D11="","",IFERROR(IF(INDEX(Log!$I:$I,MATCH(D11,Log!$G:$G,0))&""="",INDEX(Log!$A:$A,MATCH(D11,Log!$G:$G,0))&"",INDEX(Log!$I:$I,MATCH(D11,Log!$G:$G,0))&""),IF(AND(LEN(D11)=4,LEFT(D11,1)="L",ISNUMBER(VALUE(MID(D11,2,3)))),"ID não encontrado no Log",""))) -> Perguntas enviadas com prazo até 29/09/2026, às 18h | J11: EXEMPLO — exclua esta linha
I12: =IF(D12="","",IFERROR(IF(INDEX(Log!$I:$I,MATCH(D12,Log!$G:$G,0))&""="",INDEX(Log!$A:$A,MATCH(D12,Log!$G:$G,0))&"",INDEX(Log!$I:$I,MATCH(D12,Log!$G:$G,0))&""),IF(AND(LEN(D12)=4,LEFT(D12,1)="L",ISNUMBER(VALUE(MID(D12,2,3)))),"ID não encontrado no Log","")))
I13: =IF(D13="","",IFERROR(IF(INDEX(Log!$I:$I,MATCH(D13,Log!$G:$G,0))&""="",INDEX(Log!$A:$A,MATCH(D13,Log!$G:$G,0))&"",INDEX(Log!$I:$I,MATCH(D13,Log!$G:$G,0))&""),IF(AND(LEN(D13)=4,LEFT(D13,1)="L",ISNUMBER(VALUE(MID(D13,2,3)))),"ID não encontrado no Log","")))
I14: =IF(D14="","",IFERROR(IF(INDEX(Log!$I:$I,MATCH(D14,Log!$G:$G,0))&""="",INDEX(Log!$A:$A,MATCH(D14,Log!$G:$G,0))&"",INDEX(Log!$I:$I,MATCH(D14,Log!$G:$G,0))&""),IF(AND(LEN(D14)=4,LEFT(D14,1)="L",ISNUMBER(VALUE(MID(D14,2,3)))),"ID não encontrado no Log","")))
I15: =IF(D15="","",IFERROR(IF(INDEX(Log!$I:$I,MATCH(D15,Log!$G:$G,0))&""="",INDEX(Log!$A:$A,MATCH(D15,Log!$G:$G,0))&"",INDEX(Log!$I:$I,MATCH(D15,Log!$G:$G,0))&""),IF(AND(LEN(D15)=4,LEFT(D15,1)="L",ISNUMBER(VALUE(MID(D15,2,3)))),"ID não encontrado no Log","")))
I16: =IF(D16="","",IFERROR(IF(INDEX(Log!$I:$I,MATCH(D16,Log!$G:$G,0))&""="",INDEX(Log!$A:$A,MATCH(D16,Log!$G:$G,0))&"",INDEX(Log!$I:$I,MATCH(D16,Log!$G:$G,0))&""),IF(AND(LEN(D16)=4,LEFT(D16,1)="L",ISNUMBER(VALUE(MID(D16,2,3)))),"ID não encontrado no Log","")))
I17: =IF(D17="","",IFERROR(IF(INDEX(Log!$I:$I,MATCH(D17,Log!$G:$G,0))&""="",INDEX(Log!$A:$A,MATCH(D17,Log!$G:$G,0))&"",INDEX(Log!$I:$I,MATCH(D17,Log!$G:$G,0))&""),IF(AND(LEN(D17)=4,LEFT(D17,1)="L",ISNUMBER(VALUE(MID(D17,2,3)))),"ID não encontrado no Log","")))
I18: =IF(D18="","",IFERROR(IF(INDEX(Log!$I:$I,MATCH(D18,Log!$G:$G,0))&""="",INDEX(Log!$A:$A,MATCH(D18,Log!$G:$G,0))&"",INDEX(Log!$I:$I,MATCH(D18,Log!$G:$G,0))&""),IF(AND(LEN(D18)=4,LEFT(D18,1)="L",ISNUMBER(VALUE(MID(D18,2,3)))),"ID não encontrado no Log","")))
I19: =IF(D19="","",IFERROR(IF(INDEX(Log!$I:$I,MATCH(D19,Log!$G:$G,0))&""="",INDEX(Log!$A:$A,MATCH(D19,Log!$G:$G,0))&"",INDEX(Log!$I:$I,MATCH(D19,Log!$G:$G,0))&""),IF(AND(LEN(D19)=4,LEFT(D19,1)="L",ISNUMBER(VALUE(MID(D19,2,3)))),"ID não encontrado no Log","")))
I20: =IF(D20="","",IFERROR(IF(INDEX(Log!$I:$I,MATCH(D20,Log!$G:$G,0))&""="",INDEX(Log!$A:$A,MATCH(D20,Log!$G:$G,0))&"",INDEX(Log!$I:$I,MATCH(D20,Log!$G:$G,0))&""),IF(AND(LEN(D20)=4,LEFT(D20,1)="L",ISNUMBER(VALUE(MID(D20,2,3)))),"ID não encontrado no Log","")))
I21: =IF(D21="","",IFERROR(IF(INDEX(Log!$I:$I,MATCH(D21,Log!$G:$G,0))&""="",INDEX(Log!$A:$A,MATCH(D21,Log!$G:$G,0))&"",INDEX(Log!$I:$I,MATCH(D21,Log!$G:$G,0))&""),IF(AND(LEN(D21)=4,LEFT(D21,1)="L",ISNUMBER(VALUE(MID(D21,2,3)))),"ID não encontrado no Log","")))
I22: =IF(D22="","",IFERROR(IF(INDEX(Log!$I:$I,MATCH(D22,Log!$G:$G,0))&""="",INDEX(Log!$A:$A,MATCH(D22,Log!$G:$G,0))&"",INDEX(Log!$I:$I,MATCH(D22,Log!$G:$G,0))&""),IF(AND(LEN(D22)=4,LEFT(D22,1)="L",ISNUMBER(VALUE(MID(D22,2,3)))),"ID não encontrado no Log","")))
I23: =IF(D23="","",IFERROR(IF(INDEX(Log!$I:$I,MATCH(D23,Log!$G:$G,0))&""="",INDEX(Log!$A:$A,MATCH(D23,Log!$G:$G,0))&"",INDEX(Log!$I:$I,MATCH(D23,Log!$G:$G,0))&""),IF(AND(LEN(D23)=4,LEFT(D23,1)="L",ISNUMBER(VALUE(MID(D23,2,3)))),"ID não encontrado no Log","")))
... I501: =IF(D501="","",IFERROR(IF(INDEX(Log!$I:$I,MATCH(D501,Log!$G:$G,0))&""="",INDEX(Log!$A:$A,MATCH(D501,Log!$G:$G,0))&"",INDEX(Log!$I:$I,MATCH(D501,Log!$G:$G,0))&""),IF(AND(LEN(D501)=4,LEFT(D501,1)="L",ISNUMBER(VALUE(MID(D501,2,3)))),"ID não encontrado no Log","")))

Sheet Ética da pauta
A1: Item | B1: Em duas linhas | C1: Como vou lidar | D1: Observações
A2: Interesse público | B2: Dinheiro da merenda de Cidade Exemplo foi para uma empresa aberta cinco meses antes, contratada sem licitação. O mesmo caminho existe em qualquer prefeitura que compra por dispensa. | D2: EXEMPLO — apague o texto em itálico e escreva o seu
A3: Conflito de interesse | B3: Sem vínculo com a prefeitura, com a empresa ou com o vereador. | C3: Se surgir vínculo, declaro aqui ou passo a pauta adiante. | D3: EXEMPLO — apague o texto em itálico
A4: Quem não será exposto | B4: Sócia de fornecedora sem cargo público; merendeiras e alunos; servidores sem cargo de chefia. | C4: Aparecem só com tarja ou com autorização. | D4: EXEMPLO — apague o texto em itálico

Sheet Fontes
A1: Fonte | B1: Tipo | C1: Acesso | D1: Interesse | E1: Histórico | F1: Corroboração | G1: Ordem de abordagem | H1: Combinado | I1: Risco para a fonte | J1: Alerta (auto) | K1: Observações
A2: Merendeira de uma escola atendida | B2: Testemunha | C2: 3 | D2: 1 | F2: Cardápio e fotos das entregas | G2: 1 | H2: Off | I2: média | J2: =IF(A2="","",IF(AND(C2=3,D2=3,OR(F2="",F2=1,LOWER(F2&"")="não",LOWER(F2&"")="nenhuma")),"Muito acesso, muito interesse, sem corroboração: a mais perigosa (aula 2.1)","")) | K2: EXEMPLO — exclua esta linha
A3: Fornecedor concorrente que perdeu a disputa | B3: Gente do setor | C3: 2 | D3: 3 | E3: 1 | F3: Propostas da dispensa | G3: 2 | H3: Ainda não combinado | I3: baixa | J3: =IF(A3="","",IF(AND(C3=3,D3=3,OR(F3="",F3=1,LOWER(F3&"")="não",LOWER(F3&"")="nenhuma")),"Muito acesso, muito interesse, sem corroboração: a mais perigosa (aula 2.1)","")) | K3: EXEMPLO — exclua esta linha
A4: Vereador de oposição | B4: Adversário político | C4: 2 | D4: 3 | E4: 2 | G4: 3 | H4: On | I4: baixa | J4: =IF(A4="","",IF(AND(C4=3,D4=3,OR(F4="",F4=1,LOWER(F4&"")="não",LOWER(F4&"")="nenhuma")),"Muito acesso, muito interesse, sem corroboração: a mais perigosa (aula 2.1)","")) | K4: EXEMPLO — ouça e desconfie na mesma medida
A5: F1 — servidor de carreira do setor de compras | B5: De dentro do órgão | C5: 3 | D5: 3 | E5: 1 | G5: 4 | H5: Off | I5: alta | J5: =IF(A5="","",IF(AND(C5=3,D5=3,OR(F5="",F5=1,LOWER(F5&"")="não",LOWER(F5&"")="nenhuma")),"Muito acesso, muito interesse, sem corroboração: a mais perigosa (aula 2.1)","")) -> Muito acesso, muito interesse, sem corroboração: a mais perigosa (aula 2.1) | K5: EXEMPLO — protocolo da aula 2.2 antes do primeiro contato
A6: Sócio-administrador da Alimentos Modelo | B6: Alvo | C6: 3 | D6: 3 | F6: Contrato, pagamentos e cadastro CNPJ | G6: 5 | H6: On | I6: baixa | J6: =IF(A6="","",IF(AND(C6=3,D6=3,OR(F6="",F6=1,LOWER(F6&"")="não",LOWER(F6&"")="nenhuma")),"Muito acesso, muito interesse, sem corroboração: a mais perigosa (aula 2.1)","")) | K6: EXEMPLO — o centro fica por último, quando você já sabe o que perguntar
J7: =IF(A7="","",IF(AND(C7=3,D7=3,OR(F7="",F7=1,LOWER(F7&"")="não",LOWER(F7&"")="nenhuma")),"Muito acesso, muito interesse, sem corroboração: a mais perigosa (aula 2.1)",""))
J8: =IF(A8="","",IF(AND(C8=3,D8=3,OR(F8="",F8=1,LOWER(F8&"")="não",LOWER(F8&"")="nenhuma")),"Muito acesso, muito interesse, sem corroboração: a mais perigosa (aula 2.1)",""))
J9: =IF(A9="","",IF(AND(C9=3,D9=3,OR(F9="",F9=1,LOWER(F9&"")="não",LOWER(F9&"")="nenhuma")),"Muito acesso, muito interesse, sem corroboração: a mais perigosa (aula 2.1)",""))
J10: =IF(A10="","",IF(AND(C10=3,D10=3,OR(F10="",F10=1,LOWER(F10&"")="não",LOWER(F10&"")="nenhuma")),"Muito acesso, muito interesse, sem corroboração: a mais perigosa (aula 2.1)",""))
J11: =IF(A11="","",IF(AND(C11=3,D11=3,OR(F11="",F11=1,LOWER(F11&"")="não",LOWER(F11&"")="nenhuma")),"Muito acesso, muito interesse, sem corroboração: a mais perigosa (aula 2.1)",""))
J12: =IF(A12="","",IF(AND(C12=3,D12=3,OR(F12="",F12=1,LOWER(F12&"")="não",LOWER(F12&"")="nenhuma")),"Muito acesso, muito interesse, sem corroboração: a mais perigosa (aula 2.1)",""))
J13: =IF(A13="","",IF(AND(C13=3,D13=3,OR(F13="",F13=1,LOWER(F13&"")="não",LOWER(F13&"")="nenhuma")),"Muito acesso, muito interesse, sem corroboração: a mais perigosa (aula 2.1)",""))
J14: =IF(A14="","",IF(AND(C14=3,D14=3,OR(F14="",F14=1,LOWER(F14&"")="não",LOWER(F14&"")="nenhuma")),"Muito acesso, muito interesse, sem corroboração: a mais perigosa (aula 2.1)",""))
J15: =IF(A15="","",IF(AND(C15=3,D15=3,OR(F15="",F15=1,LOWER(F15&"")="não",LOWER(F15&"")="nenhuma")),"Muito acesso, muito interesse, sem corroboração: a mais perigosa (aula 2.1)",""))
J16: =IF(A16="","",IF(AND(C16=3,D16=3,OR(F16="",F16=1,LOWER(F16&"")="não",LOWER(F16&"")="nenhuma")),"Muito acesso, muito interesse, sem corroboração: a mais perigosa (aula 2.1)",""))
J17: =IF(A17="","",IF(AND(C17=3,D17=3,OR(F17="",F17=1,LOWER(F17&"")="não",LOWER(F17&"")="nenhuma")),"Muito acesso, muito interesse, sem corroboração: a mais perigosa (aula 2.1)",""))
J18: =IF(A18="","",IF(AND(C18=3,D18=3,OR(F18="",F18=1,LOWER(F18&"")="não",LOWER(F18&"")="nenhuma")),"Muito acesso, muito interesse, sem corroboração: a mais perigosa (aula 2.1)",""))
... J51: =IF(A51="","",IF(AND(C51=3,D51=3,OR(F51="",F51=1,LOWER(F51&"")="não",LOWER(F51&"")="nenhuma")),"Muito acesso, muito interesse, sem corroboração: a mais perigosa (aula 2.1)",""))

Sheet Log
A1: Origem | B1: Data e hora | C1: Ferramenta | D1: Arquivo | E1: Código ou protocolo | F1: Hash SHA-256 | G1: ID | H1: Tipo | I1: Descrição | J1: Cópia arquivada | K1: Citado na Linha do tempo (auto) | L1: Alertas (auto) | M1: Observações
A2: https://minhareceita.org | B2: 46266.425 | C2: Minha Receita | D2: cnpj-empresas-da-pauta.json | F2: aaa3e37cae511b0b47a83f21815efd0f8f6fb2b73bf42c43eaaccda59a7cb22d | G2: L001 | H2: Base de dados | I2: Cadastro CNPJ e quadro de sócios da Alimentos Modelo, da Construtora Exemplo e da Gráfica Exemplo | K2: =IF(G2="","",COUNTIF('Linha do tempo'!$D:$D,G2)) -> 1 | L2: =IF(AND(G2="",F2=""),"",TRIM(IF(AND(G2<>"",COUNTIF($G:$G,G2)>1),"ID repetido. ","")&IF(AND(F2<>"",LEN(TRIM(F2))<>64),"Hash deve ter 64 caracteres.",""))) | M2: EXEMPLO — exclua esta linha
A3: Diário oficial da Câmara de Cidade Exemplo | B3: 46266.479 | C3: Navegador | D3: nomeacao-2025-01-15.pdf | F3: bfd323af355e2847ce1eb8b7394cbca20bd538632a64786095e032b35f655862 | G3: L002 | H3: Documento público baixado | I3: Ato de nomeação de Fulano de Tal (15/01/2025) | K3: =IF(G3="","",COUNTIF('Linha do tempo'!$D:$D,G3)) -> 1 | L3: =IF(AND(G3="",F3=""),"",TRIM(IF(AND(G3<>"",COUNTIF($G:$G,G3)>1),"ID repetido. ","")&IF(AND(F3<>"",LEN(TRIM(F3))<>64),"Hash deve ter 64 caracteres.",""))) | M3: EXEMPLO — exclua esta linha
A4: https://pncp.gov.br | B4: 46267.403 | C4: Navegador | D4: contratos-045-2025-e-008-2025.pdf | F4: 7dfb629af7bdb7d70391564cd53257273e071918e2c46294c171073eabfc3e48 | G4: L003 | H4: Documento público baixado | I4: Extratos dos contratos 045/2025 (dispensa) e 008/2025 (pregão) | K4: =IF(G4="","",COUNTIF('Linha do tempo'!$D:$D,G4)) -> 2 | L4: =IF(AND(G4="",F4=""),"",TRIM(IF(AND(G4<>"",COUNTIF($G:$G,G4)>1),"ID repetido. ","")&IF(AND(F4<>"",LEN(TRIM(F4))<>64),"Hash deve ter 64 caracteres.",""))) | M4: EXEMPLO — exclua esta linha
A5: Portal da transparência de Cidade Exemplo | B5: 46267.42 | C5: Exportação em CSV | D5: pagamentos-2023-2025.csv | F5: 822c83d154a336001c9656b0da07d2d8695f9b315175af880fb62cd88809585c | G5: L004 | H5: Base de dados | I5: Empenhos e pagamentos a fornecedores, de 2023 a 2025 | K5: =IF(G5="","",COUNTIF('Linha do tempo'!$D:$D,G5)) -> 1 | L5: =IF(AND(G5="",F5=""),"",TRIM(IF(AND(G5<>"",COUNTIF($G:$G,G5)>1),"ID repetido. ","")&IF(AND(F5<>"",LEN(TRIM(F5))<>64),"Hash deve ter 64 caracteres.",""))) | M5: EXEMPLO — exclua esta linha
A6: https://portaldatransparencia.gov.br | B6: 46267.438 | C6: Consulta CEIS, CNEP e CEPIM | D6: sancoes-2026-09-02.pdf | F6: 68ac4fae8b3bece5b4b82d1815c02c213b602c2f93dd55b4874136724bfb5bf6 | G6: L005 | H6: Base de dados | I6: Construtora Exemplo no CEIS; Alimentos Modelo e Gráfica Exemplo: não consta | K6: =IF(G6="","",COUNTIF('Linha do tempo'!$D:$D,G6)) -> 0 | L6: =IF(AND(G6="",F6=""),"",TRIM(IF(AND(G6<>"",COUNTIF($G:$G,G6)>1),"ID repetido. ","")&IF(AND(F6<>"",LEN(TRIM(F6))<>64),"Hash deve ter 64 caracteres.",""))) | M6: EXEMPLO — exclua esta linha
A7: https://divulgacandcontas.tse.jus.br | B7: 46268.385 | C7: Navegador | D7: tse-sicrano-2024-2026.pdf | F7: 79a23d3eed159a1ef385b48a15099aad7823727f92ef85d1d2a5f58058c41de7 | G7: L006 | H7: Base de dados | I7: Bens, doadores e fornecedores de campanha de Sicrano Candidato (2024 e 2026) | K7: =IF(G7="","",COUNTIF('Linha do tempo'!$D:$D,G7)) -> 2 | L7: =IF(AND(G7="",F7=""),"",TRIM(IF(AND(G7<>"",COUNTIF($G:$G,G7)>1),"ID repetido. ","")&IF(AND(F7<>"",LEN(TRIM(F7))<>64),"Hash deve ter 64 caracteres.",""))) | M7: EXEMPLO — exclua esta linha
A8: Tribunal de Justiça — consulta processual | B8: 46268.597 | C8: Navegador | D8: decisao-recebimento.pdf | E8: 0000001-00.2026.8.99.0001 | F8: f27cd310c476f7a46c3647a5021e236d20c6905a39c134e8f17de1ad7c16f42c | G8: L007 | H8: Documento público baixado | I8: Decisão que recebeu a ação de improbidade | K8: =IF(G8="","",COUNTIF('Linha do tempo'!$D:$D,G8)) -> 1 | L8: =IF(AND(G8="",F8=""),"",TRIM(IF(AND(G8<>"",COUNTIF($G:$G,G8)>1),"ID repetido. ","")&IF(AND(F8<>"",LEN(TRIM(F8))<>64),"Hash deve ter 64 caracteres.",""))) | M8: EXEMPLO — exclua esta linha
A9: FNDE | B9: 46267.667 | C9: Sistema federal de pedidos | D9: pedido-fnde.pdf | E9: 99999.000001/2026-00 | G9: L008 | H9: Pedido LAI | I9: Repasses do PNAE a Cidade Exemplo em 2025, por mês | K9: =IF(G9="","",COUNTIF('Linha do tempo'!$D:$D,G9)) -> 0 | L9: =IF(AND(G9="",F9=""),"",TRIM(IF(AND(G9<>"",COUNTIF($G:$G,G9)>1),"ID repetido. ","")&IF(AND(F9<>"",LEN(TRIM(F9))<>64),"Hash deve ter 64 caracteres.",""))) | M9: EXEMPLO — exclua esta linha
A10: Prefeitura de Cidade Exemplo | B10: 46254.632 | C10: e-SIC municipal | D10: pedido-dispensa.pdf | E10: 99999.000002/2026-00 | G10: L009 | H10: Pedido LAI | I10: Processo completo da dispensa 045/2025 | K10: =IF(G10="","",COUNTIF('Linha do tempo'!$D:$D,G10)) -> 0 | L10: =IF(AND(G10="",F10=""),"",TRIM(IF(AND(G10<>"",COUNTIF($G:$G,G10)>1),"ID repetido. ","")&IF(AND(F10<>"",LEN(TRIM(F10))<>64),"Hash deve ter 64 caracteres.",""))) | M10: EXEMPLO — exclua esta linha
A11: Prefeitura de Cidade Exemplo | B11: 46283.74 | C11: e-SIC municipal | D11: resposta-dispensa.pdf | E11: 99999.000002/2026-00 | F11: 25ec1104eec583935e92060e29ffc342e6d78fe540d75ff4a6723cbdfa9b0e0a | G11: L010 | H11: Resposta de órgão | I11: Resposta parcial: faltou a pesquisa de preços | K11: =IF(G11="","",COUNTIF('Linha do tempo'!$D:$D,G11)) -> 0 | L11: =IF(AND(G11="",F11=""),"",TRIM(IF(AND(G11<>"",COUNTIF($G:$G,G11)>1),"ID repetido. ","")&IF(AND(F11<>"",LEN(TRIM(F11))<>64),"Hash deve ter 64 caracteres.",""))) | M11: EXEMPLO — exclua esta linha
A12: F1 | B12: 46270.792 | C12: Signal | G12: L011 | H12: Entrevista ou conversa | I12: Conversa em off com F1 sobre a contratação da merenda | K12: =IF(G12="","",COUNTIF('Linha do tempo'!$D:$D,G12)) -> 1 | L12: =IF(AND(G12="",F12=""),"",TRIM(IF(AND(G12<>"",COUNTIF($G:$G,G12)>1),"ID repetido. ","")&IF(AND(F12<>"",LEN(TRIM(F12))<>64),"Hash deve ter 64 caracteres.",""))) | M12: EXEMPLO — fonte humana só pelo código
A13: Alimentos Modelo; gabinete de Sicrano Candidato; Câmara Municipal | B13: 46289.417 | C13: E-mail da pauta | D13: posicionamento-2026-09-24.pdf | F13: 349f0c3a08e2f88754adfc42972c8b0dfe9100b90f5d175ae4a3d41b746a25bb | G13: L012 | H13: Pedido de posicionamento | I13: Perguntas enviadas com prazo até 29/09/2026, às 18h | K13: =IF(G13="","",COUNTIF('Linha do tempo'!$D:$D,G13)) -> 1 | L13: =IF(AND(G13="",F13=""),"",TRIM(IF(AND(G13<>"",COUNTIF($G:$G,G13)>1),"ID repetido. ","")&IF(AND(F13<>"",LEN(TRIM(F13))<>64),"Hash deve ter 64 caracteres.",""))) | M13: EXEMPLO — exclua esta linha
A14: https://pncp.gov.br | B14: 46269.389 | C14: Navegador | D14: contrato-012-2023.pdf | F14: c45b173470e3c72ba90a82e3e2766dfe9a7f273d6ff256b455743dd157c200fb | G14: L013 | H14: Documento público baixado | I14: Extrato do contrato 012/2023 (Construtora Exemplo) | K14: =IF(G14="","",COUNTIF('Linha do tempo'!$D:$D,G14)) -> 0 | L14: =IF(AND(G14="",F14=""),"",TRIM(IF(AND(G14<>"",COUNTIF($G:$G,G14)>1),"ID repetido. ","")&IF(AND(F14<>"",LEN(TRIM(F14))<>64),"Hash deve ter 64 caracteres.",""))) | M14: EXEMPLO — exclua esta linha
A15: Portal da transparência de Cidade Exemplo, página de despesas | B15: 46269.417 | C15: Wayback e SingleFile | D15: despesas-2025.html | F15: c4817b1a158db7615d452955cd88d428a3ab04b2372bed7fff52ce955aca48cc | G15: L014 | H15: Página arquivada | I15: Página de despesas de 2025, arquivada em dois lugares | J15: https://web.archive.org/web/20260904100000/https://transparencia.cidadeexemplo.gov.br/despesas | K15: =IF(G15="","",COUNTIF('Linha do tempo'!$D:$D,G15)) -> 0 | L15: =IF(AND(G15="",F15=""),"",TRIM(IF(AND(G15<>"",COUNTIF($G:$G,G15)>1),"ID repetido. ","")&IF(AND(F15<>"",LEN(TRIM(F15))<>64),"Hash deve ter 64 caracteres.",""))) | M15: EXEMPLO — exclua esta linha
A16: Tribunal de Contas do Estado — pesquisa de processos | B16: 46275.458 | C16: Navegador | D16: relatorio-tce.pdf | E16: TC-0000/2026 | F16: d485a210907cd3156822ca520351a39a2ba5b7dba1e5c6978e08464078e7a2e1 | G16: L015 | H16: Documento público baixado | I16: Relatório da área técnica na representação sobre a dispensa 045/2025 | K16: =IF(G16="","",COUNTIF('Linha do tempo'!$D:$D,G16)) -> 0 | L16: =IF(AND(G16="",F16=""),"",TRIM(IF(AND(G16<>"",COUNTIF($G:$G,G16)>1),"ID repetido. ","")&IF(AND(F16<>"",LEN(TRIM(F16))<>64),"Hash deve ter 64 caracteres.",""))) | M16: EXEMPLO — exclua esta linha
A17: Perfis de Sicrano Candidato e da prefeitura | B17: 46276.646 | C17: Wayback | D17: posts-merenda-2025.pdf | F17: 2395eb89c89c59080c916955d51587ae3c6a7fbf25ba075b369e9449b7d2b200 | G17: L016 | H17: Página arquivada | I17: Posts sobre a merenda publicados em 2025, arquivados | K17: =IF(G17="","",COUNTIF('Linha do tempo'!$D:$D,G17)) -> 0 | L17: =IF(AND(G17="",F17=""),"",TRIM(IF(AND(G17<>"",COUNTIF($G:$G,G17)>1),"ID repetido. ","")&IF(AND(F17<>"",LEN(TRIM(F17))<>64),"Hash deve ter 64 caracteres.",""))) | M17: EXEMPLO — exclua esta linha
K18: =IF(G18="","",COUNTIF('Linha do tempo'!$D:$D,G18)) | L18: =IF(AND(G18="",F18=""),"",TRIM(IF(AND(G18<>"",COUNTIF($G:$G,G18)>1),"ID repetido. ","")&IF(AND(F18<>"",LEN(TRIM(F18))<>64),"Hash deve ter 64 caracteres.","")))
K19: =IF(G19="","",COUNTIF('Linha do tempo'!$D:$D,G19)) | L19: =IF(AND(G19="",F19=""),"",TRIM(IF(AND(G19<>"",COUNTIF($G:$G,G19)>1),"ID repetido. ","")&IF(AND(F19<>"",LEN(TRIM(F19))<>64),"Hash deve ter 64 caracteres.","")))
K20: =IF(G20="","",COUNTIF('Linha do tempo'!$D:$D,G20)) | L20: =IF(AND(G20="",F20=""),"",TRIM(IF(AND(G20<>"",COUNTIF($G:$G,G20)>1),"ID repetido. ","")&IF(AND(F20<>"",LEN(TRIM(F20))<>64),"Hash deve ter 64 caracteres.","")))
K21: =IF(G21="","",COUNTIF('Linha do tempo'!$D:$D,G21)) | L21: =IF(AND(G21="",F21=""),"",TRIM(IF(AND(G21<>"",COUNTIF($G:$G,G21)>1),"ID repetido. ","")&IF(AND(F21<>"",LEN(TRIM(F21))<>64),"Hash deve ter 64 caracteres.","")))
K22: =IF(G22="","",COUNTIF('Linha do tempo'!$D:$D,G22)) | L22: =IF(AND(G22="",F22=""),"",TRIM(IF(AND(G22<>"",COUNTIF($G:$G,G22)>1),"ID repetido. ","")&IF(AND(F22<>"",LEN(TRIM(F22))<>64),"Hash deve ter 64 caracteres.","")))
K23: =IF(G23="","",COUNTIF('Linha do tempo'!$D:$D,G23)) | L23: =IF(AND(G23="",F23=""),"",TRIM(IF(AND(G23<>"",COUNTIF($G:$G,G23)>1),"ID repetido. ","")&IF(AND(F23<>"",LEN(TRIM(F23))<>64),"Hash deve ter 64 caracteres.","")))
K24: =IF(G24="","",COUNTIF('Linha do tempo'!$D:$D,G24)) | L24: =IF(AND(G24="",F24=""),"",TRIM(IF(AND(G24<>"",COUNTIF($G:$G,G24)>1),"ID repetido. ","")&IF(AND(F24<>"",LEN(TRIM(F24))<>64),"Hash deve ter 64 caracteres.","")))
K25: =IF(G25="","",COUNTIF('Linha do tempo'!$D:$D,G25)) | L25: =IF(AND(G25="",F25=""),"",TRIM(IF(AND(G25<>"",COUNTIF($G:$G,G25)>1),"ID repetido. ","")&IF(AND(F25<>"",LEN(TRIM(F25))<>64),"Hash deve ter 64 caracteres.","")))
K26: =IF(G26="","",COUNTIF('Linha do tempo'!$D:$D,G26)) | L26: =IF(AND(G26="",F26=""),"",TRIM(IF(AND(G26<>"",COUNTIF($G:$G,G26)>1),"ID repetido. ","")&IF(AND(F26<>"",LEN(TRIM(F26))<>64),"Hash deve ter 64 caracteres.","")))
K27: =IF(G27="","",COUNTIF('Linha do tempo'!$D:$D,G27)) | L27: =IF(AND(G27="",F27=""),"",TRIM(IF(AND(G27<>"",COUNTIF($G:$G,G27)>1),"ID repetido. ","")&IF(AND(F27<>"",LEN(TRIM(F27))<>64),"Hash deve ter 64 caracteres.","")))
K28: =IF(G28="","",COUNTIF('Linha do tempo'!$D:$D,G28)) | L28: =IF(AND(G28="",F28=""),"",TRIM(IF(AND(G28<>"",COUNTIF($G:$G,G28)>1),"ID repetido. ","")&IF(AND(F28<>"",LEN(TRIM(F28))<>64),"Hash deve ter 64 caracteres.","")))
K29: =IF(G29="","",COUNTIF('Linha do tempo'!$D:$D,G29)) | L29: =IF(AND(G29="",F29=""),"",TRIM(IF(AND(G29<>"",COUNTIF($G:$G,G29)>1),"ID repetido. ","")&IF(AND(F29<>"",LEN(TRIM(F29))<>64),"Hash deve ter 64 caracteres.","")))
... K501: =IF(G501="","",COUNTIF('Linha do tempo'!$D:$D,G501)) | L501: =IF(AND(G501="",F501=""),"",TRIM(IF(AND(G501<>"",COUNTIF($G:$G,G501)>1),"ID repetido. ","")&IF(AND(F501<>"",LEN(TRIM(F501))<>64),"Hash deve ter 64 caracteres.","")))

Sheet Risco
A1: Risco | B1: Probabilidade | C1: Impacto | D1: Medida | E1: Prioridade (auto) | F1: De quem é o risco | G1: Observações
A2: Ataque on-line de apoiadores do vereador | B2: alta | C2: médio | D2: Arquivar tudo, não responder, registrar ocorrência se virar ameaça | E2: =IF(OR(B2="",C2=""),"",IF(IFERROR(MATCH(B2,Listas!$N$2:$N$4,0)*MATCH(C2,Listas!$O$2:$O$4,0),0)=0,"escolha na lista",IF(MATCH(B2,Listas!$N$2:$N$4,0)*MATCH(C2,Listas!$O$2:$O$4,0)>=6,"ALTA — medida antes de seguir",IF(MATCH(B2,Listas!$N$2:$N$4,0)*MATCH(C2,Listas!$O$2:$O$4,0)>=3,"MÉDIA","baixa")))) -> ALTA — medida antes de seguir | F2: Você | G2: EXEMPLO — exclua esta linha
A3: Processo de um dos citados | B3: média | C3: alto | D3: Dossiê, pedido de posicionamento, redação na medida da prova (módulos 5 e 6) | E3: =IF(OR(B3="",C3=""),"",IF(IFERROR(MATCH(B3,Listas!$N$2:$N$4,0)*MATCH(C3,Listas!$O$2:$O$4,0),0)=0,"escolha na lista",IF(MATCH(B3,Listas!$N$2:$N$4,0)*MATCH(C3,Listas!$O$2:$O$4,0)>=6,"ALTA — medida antes de seguir",IF(MATCH(B3,Listas!$N$2:$N$4,0)*MATCH(C3,Listas!$O$2:$O$4,0)>=3,"MÉDIA","baixa")))) -> ALTA — medida antes de seguir | F3: Você | G3: EXEMPLO — exclua esta linha
A4: Visita ao endereço da empresa | B4: baixa | C4: alto | D4: Não ir sozinho, avisar o roteiro, não postar em tempo real; ou ficar com Street View e documentos | E4: =IF(OR(B4="",C4=""),"",IF(IFERROR(MATCH(B4,Listas!$N$2:$N$4,0)*MATCH(C4,Listas!$O$2:$O$4,0),0)=0,"escolha na lista",IF(MATCH(B4,Listas!$N$2:$N$4,0)*MATCH(C4,Listas!$O$2:$O$4,0)>=6,"ALTA — medida antes de seguir",IF(MATCH(B4,Listas!$N$2:$N$4,0)*MATCH(C4,Listas!$O$2:$O$4,0)>=3,"MÉDIA","baixa")))) -> MÉDIA | F4: Você | G4: EXEMPLO — exclua esta linha
A5: Exposição da fonte F1 | B5: média | C5: alto | D5: Protocolo da aula 2.2 | E5: =IF(OR(B5="",C5=""),"",IF(IFERROR(MATCH(B5,Listas!$N$2:$N$4,0)*MATCH(C5,Listas!$O$2:$O$4,0),0)=0,"escolha na lista",IF(MATCH(B5,Listas!$N$2:$N$4,0)*MATCH(C5,Listas!$O$2:$O$4,0)>=6,"ALTA — medida antes de seguir",IF(MATCH(B5,Listas!$N$2:$N$4,0)*MATCH(C5,Listas!$O$2:$O$4,0)>=3,"MÉDIA","baixa")))) -> ALTA — medida antes de seguir | F5: A fonte | G5: EXEMPLO — exclua esta linha
A6: Conta de e-mail ou de rede invadida | B6: média | C6: alto | D6: Verificação em duas etapas por aplicativo, hoje; gerenciador de senhas; disco criptografado | E6: =IF(OR(B6="",C6=""),"",IF(IFERROR(MATCH(B6,Listas!$N$2:$N$4,0)*MATCH(C6,Listas!$O$2:$O$4,0),0)=0,"escolha na lista",IF(MATCH(B6,Listas!$N$2:$N$4,0)*MATCH(C6,Listas!$O$2:$O$4,0)>=6,"ALTA — medida antes de seguir",IF(MATCH(B6,Listas!$N$2:$N$4,0)*MATCH(C6,Listas!$O$2:$O$4,0)>=3,"MÉDIA","baixa")))) -> ALTA — medida antes de seguir | F6: Você | G6: EXEMPLO — exclua esta linha
E7: =IF(OR(B7="",C7=""),"",IF(IFERROR(MATCH(B7,Listas!$N$2:$N$4,0)*MATCH(C7,Listas!$O$2:$O$4,0),0)=0,"escolha na lista",IF(MATCH(B7,Listas!$N$2:$N$4,0)*MATCH(C7,Listas!$O$2:$O$4,0)>=6,"ALTA — medida antes de seguir",IF(MATCH(B7,Listas!$N$2:$N$4,0)*MATCH(C7,Listas!$O$2:$O$4,0)>=3,"MÉDIA","baixa"))))
E8: =IF(OR(B8="",C8=""),"",IF(IFERROR(MATCH(B8,Listas!$N$2:$N$4,0)*MATCH(C8,Listas!$O$2:$O$4,0),0)=0,"escolha na lista",IF(MATCH(B8,Listas!$N$2:$N$4,0)*MATCH(C8,Listas!$O$2:$O$4,0)>=6,"ALTA — medida antes de seguir",IF(MATCH(B8,Listas!$N$2:$N$4,0)*MATCH(C8,Listas!$O$2:$O$4,0)>=3,"MÉDIA","baixa"))))
E9: =IF(OR(B9="",C9=""),"",IF(IFERROR(MATCH(B9,Listas!$N$2:$N$4,0)*MATCH(C9,Listas!$O$2:$O$4,0),0)=0,"escolha na lista",IF(MATCH(B9,Listas!$N$2:$N$4,0)*MATCH(C9,Listas!$O$2:$O$4,0)>=6,"ALTA — medida antes de seguir",IF(MATCH(B9,Listas!$N$2:$N$4,0)*MATCH(C9,Listas!$O$2:$O$4,0)>=3,"MÉDIA","baixa"))))
E10: =IF(OR(B10="",C10=""),"",IF(IFERROR(MATCH(B10,Listas!$N$2:$N$4,0)*MATCH(C10,Listas!$O$2:$O$4,0),0)=0,"escolha na lista",IF(MATCH(B10,Listas!$N$2:$N$4,0)*MATCH(C10,Listas!$O$2:$O$4,0)>=6,"ALTA — medida antes de seguir",IF(MATCH(B10,Listas!$N$2:$N$4,0)*MATCH(C10,Listas!$O$2:$O$4,0)>=3,"MÉDIA","baixa"))))
E11: =IF(OR(B11="",C11=""),"",IF(IFERROR(MATCH(B11,Listas!$N$2:$N$4,0)*MATCH(C11,Listas!$O$2:$O$4,0),0)=0,"escolha na lista",IF(MATCH(B11,Listas!$N$2:$N$4,0)*MATCH(C11,Listas!$O$2:$O$4,0)>=6,"ALTA — medida antes de seguir",IF(MATCH(B11,Listas!$N$2:$N$4,0)*MATCH(C11,Listas!$O$2:$O$4,0)>=3,"MÉDIA","baixa"))))
E12: =IF(OR(B12="",C12=""),"",IF(IFERROR(MATCH(B12,Listas!$N$2:$N$4,0)*MATCH(C12,Listas!$O$2:$O$4,0),0)=0,"escolha na lista",IF(MATCH(B12,Listas!$N$2:$N$4,0)*MATCH(C12,Listas!$O$2:$O$4,0)>=6,"ALTA — medida antes de seguir",IF(MATCH(B12,Listas!$N$2:$N$4,0)*MATCH(C12,Listas!$O$2:$O$4,0)>=3,"MÉDIA","baixa"))))
E13: =IF(OR(B13="",C13=""),"",IF(IFERROR(MATCH(B13,Listas!$N$2:$N$4,0)*MATCH(C13,Listas!$O$2:$O$4,0),0)=0,"escolha na lista",IF(MATCH(B13,Listas!$N$2:$N$4,0)*MATCH(C13,Listas!$O$2:$O$4,0)>=6,"ALTA — medida antes de seguir",IF(MATCH(B13,Listas!$N$2:$N$4,0)*MATCH(C13,Listas!$O$2:$O$4,0)>=3,"MÉDIA","baixa"))))
E14: =IF(OR(B14="",C14=""),"",IF(IFERROR(MATCH(B14,Listas!$N$2:$N$4,0)*MATCH(C14,Listas!$O$2:$O$4,0),0)=0,"escolha na lista",IF(MATCH(B14,Listas!$N$2:$N$4,0)*MATCH(C14,Listas!$O$2:$O$4,0)>=6,"ALTA — medida antes de seguir",IF(MATCH(B14,Listas!$N$2:$N$4,0)*MATCH(C14,Listas!$O$2:$O$4,0)>=3,"MÉDIA","baixa"))))
E15: =IF(OR(B15="",C15=""),"",IF(IFERROR(MATCH(B15,Listas!$N$2:$N$4,0)*MATCH(C15,Listas!$O$2:$O$4,0),0)=0,"escolha na lista",IF(MATCH(B15,Listas!$N$2:$N$4,0)*MATCH(C15,Listas!$O$2:$O$4,0)>=6,"ALTA — medida antes de seguir",IF(MATCH(B15,Listas!$N$2:$N$4,0)*MATCH(C15,Listas!$O$2:$O$4,0)>=3,"MÉDIA","baixa"))))
E16: =IF(OR(B16="",C16=""),"",IF(IFERROR(MATCH(B16,Listas!$N$2:$N$4,0)*MATCH(C16,Listas!$O$2:$O$4,0),0)=0,"escolha na lista",IF(MATCH(B16,Listas!$N$2:$N$4,0)*MATCH(C16,Listas!$O$2:$O$4,0)>=6,"ALTA — medida antes de seguir",IF(MATCH(B16,Listas!$N$2:$N$4,0)*MATCH(C16,Listas!$O$2:$O$4,0)>=3,"MÉDIA","baixa"))))
E17: =IF(OR(B17="",C17=""),"",IF(IFERROR(MATCH(B17,Listas!$N$2:$N$4,0)*MATCH(C17,Listas!$O$2:$O$4,0),0)=0,"escolha na lista",IF(MATCH(B17,Listas!$N$2:$N$4,0)*MATCH(C17,Listas!$O$2:$O$4,0)>=6,"ALTA — medida antes de seguir",IF(MATCH(B17,Listas!$N$2:$N$4,0)*MATCH(C17,Listas!$O$2:$O$4,0)>=3,"MÉDIA","baixa"))))
E18: =IF(OR(B18="",C18=""),"",IF(IFERROR(MATCH(B18,Listas!$N$2:$N$4,0)*MATCH(C18,Listas!$O$2:$O$4,0),0)=0,"escolha na lista",IF(MATCH(B18,Listas!$N$2:$N$4,0)*MATCH(C18,Listas!$O$2:$O$4,0)>=6,"ALTA — medida antes de seguir",IF(MATCH(B18,Listas!$N$2:$N$4,0)*MATCH(C18,Listas!$O$2:$O$4,0)>=3,"MÉDIA","baixa"))))
... E51: =IF(OR(B51="",C51=""),"",IF(IFERROR(MATCH(B51,Listas!$N$2:$N$4,0)*MATCH(C51,Listas!$O$2:$O$4,0),0)=0,"escolha na lista",IF(MATCH(B51,Listas!$N$2:$N$4,0)*MATCH(C51,Listas!$O$2:$O$4,0)>=6,"ALTA — medida antes de seguir",IF(MATCH(B51,Listas!$N$2:$N$4,0)*MATCH(C51,Listas!$O$2:$O$4,0)>=3,"MÉDIA","baixa"))))

Sheet Documentos
A1: Documento | B1: Quem tem | C1: Já está publicado? | D1: Onde | E1: Próximo passo (auto) | F1: Protocolo do pedido | G1: Observações
A2: Extrato do contrato 045/2025 | B2: Secretaria Municipal de Educação | C2: Sim | D2: PNCP | E2: =IF(C2="","",IF(C2="Sim","Baixe e registre no Log",IF(C2="Não","Peça pela LAI (aula 3.2) e anote em Prazos LAI",IF(C2="Em parte","Baixe o que está publicado e peça o resto pela LAI","Procure antes de pedir: pedir o que já está publicado é perder 20 dias")))) -> Baixe e registre no Log | G2: EXEMPLO — exclua esta linha
A3: Processo completo da dispensa 045/2025, com pesquisa de preços e parecer | B3: Secretaria Municipal de Educação | C3: Não | E3: =IF(C3="","",IF(C3="Sim","Baixe e registre no Log",IF(C3="Não","Peça pela LAI (aula 3.2) e anote em Prazos LAI",IF(C3="Em parte","Baixe o que está publicado e peça o resto pela LAI","Procure antes de pedir: pedir o que já está publicado é perder 20 dias")))) -> Peça pela LAI (aula 3.2) e anote em Prazos LAI | F3: 99999.000002/2026-00 | G3: EXEMPLO — exclua esta linha
A4: Notas fiscais e ordens bancárias dos pagamentos à Alimentos Modelo | B4: Prefeitura e Tribunal de Contas do Estado | C4: Em parte | D4: Portal da transparência municipal: só valores e datas | E4: =IF(C4="","",IF(C4="Sim","Baixe e registre no Log",IF(C4="Não","Peça pela LAI (aula 3.2) e anote em Prazos LAI",IF(C4="Em parte","Baixe o que está publicado e peça o resto pela LAI","Procure antes de pedir: pedir o que já está publicado é perder 20 dias")))) -> Baixe o que está publicado e peça o resto pela LAI | G4: EXEMPLO — exclua esta linha
A5: Repasses do PNAE a Cidade Exemplo em 2025, por mês | B5: FNDE | C5: Talvez | D5: Painel do FNDE? | E5: =IF(C5="","",IF(C5="Sim","Baixe e registre no Log",IF(C5="Não","Peça pela LAI (aula 3.2) e anote em Prazos LAI",IF(C5="Em parte","Baixe o que está publicado e peça o resto pela LAI","Procure antes de pedir: pedir o que já está publicado é perder 20 dias")))) -> Procure antes de pedir: pedir o que já está publicado é perder 20 dias | F5: 99999.000001/2026-00 | G5: EXEMPLO — exclua esta linha
A6: Decisão que recebeu a ação de improbidade | B6: Tribunal de Justiça | C6: Sim | D6: Consulta processual | E6: =IF(C6="","",IF(C6="Sim","Baixe e registre no Log",IF(C6="Não","Peça pela LAI (aula 3.2) e anote em Prazos LAI",IF(C6="Em parte","Baixe o que está publicado e peça o resto pela LAI","Procure antes de pedir: pedir o que já está publicado é perder 20 dias")))) -> Baixe e registre no Log | G6: EXEMPLO — exclua esta linha
E7: =IF(C7="","",IF(C7="Sim","Baixe e registre no Log",IF(C7="Não","Peça pela LAI (aula 3.2) e anote em Prazos LAI",IF(C7="Em parte","Baixe o que está publicado e peça o resto pela LAI","Procure antes de pedir: pedir o que já está publicado é perder 20 dias"))))
E8: =IF(C8="","",IF(C8="Sim","Baixe e registre no Log",IF(C8="Não","Peça pela LAI (aula 3.2) e anote em Prazos LAI",IF(C8="Em parte","Baixe o que está publicado e peça o resto pela LAI","Procure antes de pedir: pedir o que já está publicado é perder 20 dias"))))
E9: =IF(C9="","",IF(C9="Sim","Baixe e registre no Log",IF(C9="Não","Peça pela LAI (aula 3.2) e anote em Prazos LAI",IF(C9="Em parte","Baixe o que está publicado e peça o resto pela LAI","Procure antes de pedir: pedir o que já está publicado é perder 20 dias"))))
E10: =IF(C10="","",IF(C10="Sim","Baixe e registre no Log",IF(C10="Não","Peça pela LAI (aula 3.2) e anote em Prazos LAI",IF(C10="Em parte","Baixe o que está publicado e peça o resto pela LAI","Procure antes de pedir: pedir o que já está publicado é perder 20 dias"))))
E11: =IF(C11="","",IF(C11="Sim","Baixe e registre no Log",IF(C11="Não","Peça pela LAI (aula 3.2) e anote em Prazos LAI",IF(C11="Em parte","Baixe o que está publicado e peça o resto pela LAI","Procure antes de pedir: pedir o que já está publicado é perder 20 dias"))))
E12: =IF(C12="","",IF(C12="Sim","Baixe e registre no Log",IF(C12="Não","Peça pela LAI (aula 3.2) e anote em Prazos LAI",IF(C12="Em parte","Baixe o que está publicado e peça o resto pela LAI","Procure antes de pedir: pedir o que já está publicado é perder 20 dias"))))
E13: =IF(C13="","",IF(C13="Sim","Baixe e registre no Log",IF(C13="Não","Peça pela LAI (aula 3.2) e anote em Prazos LAI",IF(C13="Em parte","Baixe o que está publicado e peça o resto pela LAI","Procure antes de pedir: pedir o que já está publicado é perder 20 dias"))))
E14: =IF(C14="","",IF(C14="Sim","Baixe e registre no Log",IF(C14="Não","Peça pela LAI (aula 3.2) e anote em Prazos LAI",IF(C14="Em parte","Baixe o que está publicado e peça o resto pela LAI","Procure antes de pedir: pedir o que já está publicado é perder 20 dias"))))
E15: =IF(C15="","",IF(C15="Sim","Baixe e registre no Log",IF(C15="Não","Peça pela LAI (aula 3.2) e anote em Prazos LAI",IF(C15="Em parte","Baixe o que está publicado e peça o resto pela LAI","Procure antes de pedir: pedir o que já está publicado é perder 20 dias"))))
E16: =IF(C16="","",IF(C16="Sim","Baixe e registre no Log",IF(C16="Não","Peça pela LAI (aula 3.2) e anote em Prazos LAI",IF(C16="Em parte","Baixe o que está publicado e peça o resto pela LAI","Procure antes de pedir: pedir o que já está publicado é perder 20 dias"))))
E17: =IF(C17="","",IF(C17="Sim","Baixe e registre no Log",IF(C17="Não","Peça pela LAI (aula 3.2) e anote em Prazos LAI",IF(C17="Em parte","Baixe o que está publicado e peça o resto pela LAI","Procure antes de pedir: pedir o que já está publicado é perder 20 dias"))))
E18: =IF(C18="","",IF(C18="Sim","Baixe e registre no Log",IF(C18="Não","Peça pela LAI (aula 3.2) e anote em Prazos LAI",IF(C18="Em parte","Baixe o que está publicado e peça o resto pela LAI","Procure antes de pedir: pedir o que já está publicado é perder 20 dias"))))
... E101: =IF(C101="","",IF(C101="Sim","Baixe e registre no Log",IF(C101="Não","Peça pela LAI (aula 3.2) e anote em Prazos LAI",IF(C101="Em parte","Baixe o que está publicado e peça o resto pela LAI","Procure antes de pedir: pedir o que já está publicado é perder 20 dias"))))

Sheet Prazos LAI
A1: Protocolo | B1: Órgão | C1: Esfera | D1: O que foi pedido | E1: Data do pedido | F1: Prorrogado? | G1: Prazo de resposta (auto) | H1: Data da última resposta | I1: Resultado da última resposta | J1: Instância atual | K1: Data do último recurso ou reclamação | L1: Próxima data (auto) | M1: Dias até a próxima data (auto) | N1: Próxima ação (auto) | O1: Fonte (ID do Log) | P1: Observações
A2: 99999.000001/2026-00 | B2: FNDE | C2: Federal | D2: Repasses do PNAE a Cidade Exemplo em 2025, por mês | E2: 46267 | F2: Não | G2: =IF(E2="","",E2+IF(F2="Sim",30,20)) -> 46287 | J2: Pedido | L2: =IF(E2="","",IF(AND(K2<>"",OR(H2="",K2>=H2)),IF(J2="CMRI","",K2+5),IF(H2="",IF(TODAY()<=G2,G2,IF(TODAY()<E2+30,E2+30,E2+40)),IF(OR(I2="Negado",I2="Atendido em parte"),H2+10,"")))) -> 46297 | M2: =IF(L2="","",L2-TODAY()) -> 2 | N2: =IF(E2="","",IF(AND(K2<>"",OR(H2="",K2>=H2)),IF(J2="CMRI","Aguardar a CMRI (até a 3ª reunião mensal depois da autuação)","Aguardar decisão do recurso ou da reclamação"),IF(H2="",IF(TODAY()<=G2,"Aguardar resposta do órgão",IF(TODAY()<E2+30,"Prazo vencido: reclamação (modelo E) a partir da próxima data",IF(TODAY()<=E2+40,"Fazer reclamação (modelo E) até a próxima data","Janela de reclamação encerrada: novo pedido ou modelo G"))),IF(I2="Atendido","Concluído: registre a resposta no Log",IF(OR(I2="Negado",I2="Atendido em parte"),"Recorrer (modelo B ou D) até a próxima data","Preencha o resultado da resposta"))))) -> Prazo vencido: reclamação (modelo E) a partir da próxima data | O2: L008 | P2: EXEMPLO — exclua esta linha
A3: 99999.000002/2026-00 | B3: Prefeitura de Cidade Exemplo | C3: Municipal | D3: Processo completo da dispensa 045/2025 | E3: 46254 | F3: Sim | G3: =IF(E3="","",E3+IF(F3="Sim",30,20)) -> 46284 | H3: 46283 | I3: Atendido em parte | J3: Pedido | L3: =IF(E3="","",IF(AND(K3<>"",OR(H3="",K3>=H3)),IF(J3="CMRI","",K3+5),IF(H3="",IF(TODAY()<=G3,G3,IF(TODAY()<E3+30,E3+30,E3+40)),IF(OR(I3="Negado",I3="Atendido em parte"),H3+10,"")))) -> 46293 | M3: =IF(L3="","",L3-TODAY()) -> -2 | N3: =IF(E3="","",IF(AND(K3<>"",OR(H3="",K3>=H3)),IF(J3="CMRI","Aguardar a CMRI (até a 3ª reunião mensal depois da autuação)","Aguardar decisão do recurso ou da reclamação"),IF(H3="",IF(TODAY()<=G3,"Aguardar resposta do órgão",IF(TODAY()<E3+30,"Prazo vencido: reclamação (modelo E) a partir da próxima data",IF(TODAY()<=E3+40,"Fazer reclamação (modelo E) até a próxima data","Janela de reclamação encerrada: novo pedido ou modelo G"))),IF(I3="Atendido","Concluído: registre a resposta no Log",IF(OR(I3="Negado",I3="Atendido em parte"),"Recorrer (modelo B ou D) até a próxima data","Preencha o resultado da resposta"))))) -> Recorrer (modelo B ou D) até a próxima data | O3: L009 | P3: EXEMPLO — faltou a pesquisa de preços (L010)
G4: =IF(E4="","",E4+IF(F4="Sim",30,20)) | L4: =IF(E4="","",IF(AND(K4<>"",OR(H4="",K4>=H4)),IF(J4="CMRI","",K4+5),IF(H4="",IF(TODAY()<=G4,G4,IF(TODAY()<E4+30,E4+30,E4+40)),IF(OR(I4="Negado",I4="Atendido em parte"),H4+10,"")))) | M4: =IF(L4="","",L4-TODAY()) | N4: =IF(E4="","",IF(AND(K4<>"",OR(H4="",K4>=H4)),IF(J4="CMRI","Aguardar a CMRI (até a 3ª reunião mensal depois da autuação)","Aguardar decisão do recurso ou da reclamação"),IF(H4="",IF(TODAY()<=G4,"Aguardar resposta do órgão",IF(TODAY()<E4+30,"Prazo vencido: reclamação (modelo E) a partir da próxima data",IF(TODAY()<=E4+40,"Fazer reclamação (modelo E) até a próxima data","Janela de reclamação encerrada: novo pedido ou modelo G"))),IF(I4="Atendido","Concluído: registre a resposta no Log",IF(OR(I4="Negado",I4="Atendido em parte"),"Recorrer (modelo B ou D) até a próxima data","Preencha o resultado da resposta")))))
G5: =IF(E5="","",E5+IF(F5="Sim",30,20)) | L5: =IF(E5="","",IF(AND(K5<>"",OR(H5="",K5>=H5)),IF(J5="CMRI","",K5+5),IF(H5="",IF(TODAY()<=G5,G5,IF(TODAY()<E5+30,E5+30,E5+40)),IF(OR(I5="Negado",I5="Atendido em parte"),H5+10,"")))) | M5: =IF(L5="","",L5-TODAY()) | N5: =IF(E5="","",IF(AND(K5<>"",OR(H5="",K5>=H5)),IF(J5="CMRI","Aguardar a CMRI (até a 3ª reunião mensal depois da autuação)","Aguardar decisão do recurso ou da reclamação"),IF(H5="",IF(TODAY()<=G5,"Aguardar resposta do órgão",IF(TODAY()<E5+30,"Prazo vencido: reclamação (modelo E) a partir da próxima data",IF(TODAY()<=E5+40,"Fazer reclamação (modelo E) até a próxima data","Janela de reclamação encerrada: novo pedido ou modelo G"))),IF(I5="Atendido","Concluído: registre a resposta no Log",IF(OR(I5="Negado",I5="Atendido em parte"),"Recorrer (modelo B ou D) até a próxima data","Preencha o resultado da resposta")))))
G6: =IF(E6="","",E6+IF(F6="Sim",30,20)) | L6: =IF(E6="","",IF(AND(K6<>"",OR(H6="",K6>=H6)),IF(J6="CMRI","",K6+5),IF(H6="",IF(TODAY()<=G6,G6,IF(TODAY()<E6+30,E6+30,E6+40)),IF(OR(I6="Negado",I6="Atendido em parte"),H6+10,"")))) | M6: =IF(L6="","",L6-TODAY()) | N6: =IF(E6="","",IF(AND(K6<>"",OR(H6="",K6>=H6)),IF(J6="CMRI","Aguardar a CMRI (até a 3ª reunião mensal depois da autuação)","Aguardar decisão do recurso ou da reclamação"),IF(H6="",IF(TODAY()<=G6,"Aguardar resposta do órgão",IF(TODAY()<E6+30,"Prazo vencido: reclamação (modelo E) a partir da próxima data",IF(TODAY()<=E6+40,"Fazer reclamação (modelo E) até a próxima data","Janela de reclamação encerrada: novo pedido ou modelo G"))),IF(I6="Atendido","Concluído: registre a resposta no Log",IF(OR(I6="Negado",I6="Atendido em parte"),"Recorrer (modelo B ou D) até a próxima data","Preencha o resultado da resposta")))))
G7: =IF(E7="","",E7+IF(F7="Sim",30,20)) | L7: =IF(E7="","",IF(AND(K7<>"",OR(H7="",K7>=H7)),IF(J7="CMRI","",K7+5),IF(H7="",IF(TODAY()<=G7,G7,IF(TODAY()<E7+30,E7+30,E7+40)),IF(OR(I7="Negado",I7="Atendido em parte"),H7+10,"")))) | M7: =IF(L7="","",L7-TODAY()) | N7: =IF(E7="","",IF(AND(K7<>"",OR(H7="",K7>=H7)),IF(J7="CMRI","Aguardar a CMRI (até a 3ª reunião mensal depois da autuação)","Aguardar decisão do recurso ou da reclamação"),IF(H7="",IF(TODAY()<=G7,"Aguardar resposta do órgão",IF(TODAY()<E7+30,"Prazo vencido: reclamação (modelo E) a partir da próxima data",IF(TODAY()<=E7+40,"Fazer reclamação (modelo E) até a próxima data","Janela de reclamação encerrada: novo pedido ou modelo G"))),IF(I7="Atendido","Concluído: registre a resposta no Log",IF(OR(I7="Negado",I7="Atendido em parte"),"Recorrer (modelo B ou D) até a próxima data","Preencha o resultado da resposta")))))
G8: =IF(E8="","",E8+IF(F8="Sim",30,20)) | L8: =IF(E8="","",IF(AND(K8<>"",OR(H8="",K8>=H8)),IF(J8="CMRI","",K8+5),IF(H8="",IF(TODAY()<=G8,G8,IF(TODAY()<E8+30,E8+30,E8+40)),IF(OR(I8="Negado",I8="Atendido em parte"),H8+10,"")))) | M8: =IF(L8="","",L8-TODAY()) | N8: =IF(E8="","",IF(AND(K8<>"",OR(H8="",K8>=H8)),IF(J8="CMRI","Aguardar a CMRI (até a 3ª reunião mensal depois da autuação)","Aguardar decisão do recurso ou da reclamação"),IF(H8="",IF(TODAY()<=G8,"Aguardar resposta do órgão",IF(TODAY()<E8+30,"Prazo vencido: reclamação (modelo E) a partir da próxima data",IF(TODAY()<=E8+40,"Fazer reclamação (modelo E) até a próxima data","Janela de reclamação encerrada: novo pedido ou modelo G"))),IF(I8="Atendido","Concluído: registre a resposta no Log",IF(OR(I8="Negado",I8="Atendido em parte"),"Recorrer (modelo B ou D) até a próxima data","Preencha o resultado da resposta")))))
G9: =IF(E9="","",E9+IF(F9="Sim",30,20)) | L9: =IF(E9="","",IF(AND(K9<>"",OR(H9="",K9>=H9)),IF(J9="CMRI","",K9+5),IF(H9="",IF(TODAY()<=G9,G9,IF(TODAY()<E9+30,E9+30,E9+40)),IF(OR(I9="Negado",I9="Atendido em parte"),H9+10,"")))) | M9: =IF(L9="","",L9-TODAY()) | N9: =IF(E9="","",IF(AND(K9<>"",OR(H9="",K9>=H9)),IF(J9="CMRI","Aguardar a CMRI (até a 3ª reunião mensal depois da autuação)","Aguardar decisão do recurso ou da reclamação"),IF(H9="",IF(TODAY()<=G9,"Aguardar resposta do órgão",IF(TODAY()<E9+30,"Prazo vencido: reclamação (modelo E) a partir da próxima data",IF(TODAY()<=E9+40,"Fazer reclamação (modelo E) até a próxima data","Janela de reclamação encerrada: novo pedido ou modelo G"))),IF(I9="Atendido","Concluído: registre a resposta no Log",IF(OR(I9="Negado",I9="Atendido em parte"),"Recorrer (modelo B ou D) até a próxima data","Preencha o resultado da resposta")))))
G10: =IF(E10="","",E10+IF(F10="Sim",30,20)) | L10: =IF(E10="","",IF(AND(K10<>"",OR(H10="",K10>=H10)),IF(J10="CMRI","",K10+5),IF(H10="",IF(TODAY()<=G10,G10,IF(TODAY()<E10+30,E10+30,E10+40)),IF(OR(I10="Negado",I10="Atendido em parte"),H10+10,"")))) | M10: =IF(L10="","",L10-TODAY()) | N10: =IF(E10="","",IF(AND(K10<>"",OR(H10="",K10>=H10)),IF(J10="CMRI","Aguardar a CMRI (até a 3ª reunião mensal depois da autuação)","Aguardar decisão do recurso ou da reclamação"),IF(H10="",IF(TODAY()<=G10,"Aguardar resposta do órgão",IF(TODAY()<E10+30,"Prazo vencido: reclamação (modelo E) a partir da próxima data",IF(TODAY()<=E10+40,"Fazer reclamação (modelo E) até a próxima data","Janela de reclamação encerrada: novo pedido ou modelo G"))),IF(I10="Atendido","Concluído: registre a resposta no Log",IF(OR(I10="Negado",I10="Atendido em parte"),"Recorrer (modelo B ou D) até a próxima data","Preencha o resultado da resposta")))))
G11: =IF(E11="","",E11+IF(F11="Sim",30,20)) | L11: =IF(E11="","",IF(AND(K11<>"",OR(H11="",K11>=H11)),IF(J11="CMRI","",K11+5),IF(H11="",IF(TODAY()<=G11,G11,IF(TODAY()<E11+30,E11+30,E11+40)),IF(OR(I11="Negado",I11="Atendido em parte"),H11+10,"")))) | M11: =IF(L11="","",L11-TODAY()) | N11: =IF(E11="","",IF(AND(K11<>"",OR(H11="",K11>=H11)),IF(J11="CMRI","Aguardar a CMRI (até a 3ª reunião mensal depois da autuação)","Aguardar decisão do recurso ou da reclamação"),IF(H11="",IF(TODAY()<=G11,"Aguardar resposta do órgão",IF(TODAY()<E11+30,"Prazo vencido: reclamação (modelo E) a partir da próxima data",IF(TODAY()<=E11+40,"Fazer reclamação (modelo E) até a próxima data","Janela de reclamação encerrada: novo pedido ou modelo G"))),IF(I11="Atendido","Concluído: registre a resposta no Log",IF(OR(I11="Negado",I11="Atendido em parte"),"Recorrer (modelo B ou D) até a próxima data","Preencha o resultado da resposta")))))
G12: =IF(E12="","",E12+IF(F12="Sim",30,20)) | L12: =IF(E12="","",IF(AND(K12<>"",OR(H12="",K12>=H12)),IF(J12="CMRI","",K12+5),IF(H12="",IF(TODAY()<=G12,G12,IF(TODAY()<E12+30,E12+30,E12+40)),IF(OR(I12="Negado",I12="Atendido em parte"),H12+10,"")))) | M12: =IF(L12="","",L12-TODAY()) | N12: =IF(E12="","",IF(AND(K12<>"",OR(H12="",K12>=H12)),IF(J12="CMRI","Aguardar a CMRI (até a 3ª reunião mensal depois da autuação)","Aguardar decisão do recurso ou da reclamação"),IF(H12="",IF(TODAY()<=G12,"Aguardar resposta do órgão",IF(TODAY()<E12+30,"Prazo vencido: reclamação (modelo E) a partir da próxima data",IF(TODAY()<=E12+40,"Fazer reclamação (modelo E) até a próxima data","Janela de reclamação encerrada: novo pedido ou modelo G"))),IF(I12="Atendido","Concluído: registre a resposta no Log",IF(OR(I12="Negado",I12="Atendido em parte"),"Recorrer (modelo B ou D) até a próxima data","Preencha o resultado da resposta")))))
G13: =IF(E13="","",E13+IF(F13="Sim",30,20)) | L13: =IF(E13="","",IF(AND(K13<>"",OR(H13="",K13>=H13)),IF(J13="CMRI","",K13+5),IF(H13="",IF(TODAY()<=G13,G13,IF(TODAY()<E13+30,E13+30,E13+40)),IF(OR(I13="Negado",I13="Atendido em parte"),H13+10,"")))) | M13: =IF(L13="","",L13-TODAY()) | N13: =IF(E13="","",IF(AND(K13<>"",OR(H13="",K13>=H13)),IF(J13="CMRI","Aguardar a CMRI (até a 3ª reunião mensal depois da autuação)","Aguardar decisão do recurso ou da reclamação"),IF(H13="",IF(TODAY()<=G13,"Aguardar resposta do órgão",IF(TODAY()<E13+30,"Prazo vencido: reclamação (modelo E) a partir da próxima data",IF(TODAY()<=E13+40,"Fazer reclamação (modelo E) até a próxima data","Janela de reclamação encerrada: novo pedido ou modelo G"))),IF(I13="Atendido","Concluído: registre a resposta no Log",IF(OR(I13="Negado",I13="Atendido em parte"),"Recorrer (modelo B ou D) até a próxima data","Preencha o resultado da resposta")))))
G14: =IF(E14="","",E14+IF(F14="Sim",30,20)) | L14: =IF(E14="","",IF(AND(K14<>"",OR(H14="",K14>=H14)),IF(J14="CMRI","",K14+5),IF(H14="",IF(TODAY()<=G14,G14,IF(TODAY()<E14+30,E14+30,E14+40)),IF(OR(I14="Negado",I14="Atendido em parte"),H14+10,"")))) | M14: =IF(L14="","",L14-TODAY()) | N14: =IF(E14="","",IF(AND(K14<>"",OR(H14="",K14>=H14)),IF(J14="CMRI","Aguardar a CMRI (até a 3ª reunião mensal depois da autuação)","Aguardar decisão do recurso ou da reclamação"),IF(H14="",IF(TODAY()<=G14,"Aguardar resposta do órgão",IF(TODAY()<E14+30,"Prazo vencido: reclamação (modelo E) a partir da próxima data",IF(TODAY()<=E14+40,"Fazer reclamação (modelo E) até a próxima data","Janela de reclamação encerrada: novo pedido ou modelo G"))),IF(I14="Atendido","Concluído: registre a resposta no Log",IF(OR(I14="Negado",I14="Atendido em parte"),"Recorrer (modelo B ou D) até a próxima data","Preencha o resultado da resposta")))))
G15: =IF(E15="","",E15+IF(F15="Sim",30,20)) | L15: =IF(E15="","",IF(AND(K15<>"",OR(H15="",K15>=H15)),IF(J15="CMRI","",K15+5),IF(H15="",IF(TODAY()<=G15,G15,IF(TODAY()<E15+30,E15+30,E15+40)),IF(OR(I15="Negado",I15="Atendido em parte"),H15+10,"")))) | M15: =IF(L15="","",L15-TODAY()) | N15: =IF(E15="","",IF(AND(K15<>"",OR(H15="",K15>=H15)),IF(J15="CMRI","Aguardar a CMRI (até a 3ª reunião mensal depois da autuação)","Aguardar decisão do recurso ou da reclamação"),IF(H15="",IF(TODAY()<=G15,"Aguardar resposta do órgão",IF(TODAY()<E15+30,"Prazo vencido: reclamação (modelo E) a partir da próxima data",IF(TODAY()<=E15+40,"Fazer reclamação (modelo E) até a próxima data","Janela de reclamação encerrada: novo pedido ou modelo G"))),IF(I15="Atendido","Concluído: registre a resposta no Log",IF(OR(I15="Negado",I15="Atendido em parte"),"Recorrer (modelo B ou D) até a próxima data","Preencha o resultado da resposta")))))
... G101: =IF(E101="","",E101+IF(F101="Sim",30,20)) | L101: =IF(E101="","",IF(AND(K101<>"",OR(H101="",K101>=H101)),IF(J101="CMRI","",K101+5),IF(H101="",IF(TODAY()<=G101,G101,IF(TODAY()<E101+30,E101+30,E101+40)),IF(OR(I101="Negado",I101="Atendido em parte"),H101+10,"")))) | M101: =IF(L101="","",L101-TODAY()) | N101: =IF(E101="","",IF(AND(K101<>"",OR(H101="",K101>=H101)),IF(J101="CMRI","Aguardar a CMRI (até a 3ª reunião mensal depois da autuação)","Aguardar decisão do recurso ou da reclamação"),IF(H101="",IF(TODAY()<=G101,"Aguardar resposta do órgão",IF(TODAY()<E101+30,"Prazo vencido: reclamação (modelo E) a partir da próxima data",IF(TODAY()<=E101+40,"Fazer reclamação (modelo E) até a próxima data","Janela de reclamação encerrada: novo pedido ou modelo G"))),IF(I101="Atendido","Concluído: registre a resposta no Log",IF(OR(I101="Negado",I101="Atendido em parte"),"Recorrer (modelo B ou D) até a próxima data","Preencha o resultado da resposta")))))

Sheet Pagamentos
A1: CNPJ do credor | B1: Nome | C1: Valor (R$) | D1: Data | E1: Fonte | F1: Fase | G1: Órgão pagador | H1: Nº do documento | I1: Programa, ação ou emenda | J1: CNAE do credor (auto) | K1: Sanção (auto) | L1: Fornecedor de campanha (auto) | M1: Algum sinal? (auto) | N1: Pergunta que o sinal levanta | O1: Ano (auto) | P1: Observações
A2: 11222333000186 | B2: ALIMENTOS MODELO LTDA | C2: 480000 | D2: 45895 | E2: L004 | F2: Empenho | G2: Secretaria Municipal de Educação de Cidade Exemplo | H2: 2025NE000123 | I2: Alimentação escolar | J2: =IF(A2="","",IFERROR(INDEX(Empresas!$D:$D,MATCH(A2,Empresas!$A:$A,0))&"","não consta")) -> 5620-1/01 Fornecimento de alimentos preparados preponderantemente para empresas | K2: =IF(A2="","",IFERROR(INDEX(Sancoes!$B:$B,MATCH(A2,Sancoes!$A:$A,0))&"","não consta")) -> Não consta | L2: =IF(A2="","",IFERROR(INDEX(Eleitoral!$B:$B,MATCH(A2,Eleitoral!$A:$A,0))&"","não consta")) -> não consta | M2: =IF(A2="","",IF(OR(AND(K2<>"",LOWER(K2)<>"não consta"),AND(L2<>"",LOWER(L2)<>"não consta"),IFERROR(INDEX(Empresas!$G:$G,MATCH(A2,Empresas!$A:$A,0))&"","")<>""),"SIM","")) -> SIM | N2: Por que uma empresa aberta em março foi contratada sem licitação em agosto? | O2: =IF(D2="","",YEAR(D2)) -> 2025 | P2: EXEMPLO — exclua esta linha
A3: 11222333000186 | B3: ALIMENTOS MODELO LTDA | C3: 120000 | D3: 45930 | E3: L004 | F3: Pagamento | G3: Secretaria Municipal de Educação de Cidade Exemplo | H3: 2025OB000456 | I3: Alimentação escolar | J3: =IF(A3="","",IFERROR(INDEX(Empresas!$D:$D,MATCH(A3,Empresas!$A:$A,0))&"","não consta")) -> 5620-1/01 Fornecimento de alimentos preparados preponderantemente para empresas | K3: =IF(A3="","",IFERROR(INDEX(Sancoes!$B:$B,MATCH(A3,Sancoes!$A:$A,0))&"","não consta")) -> Não consta | L3: =IF(A3="","",IFERROR(INDEX(Eleitoral!$B:$B,MATCH(A3,Eleitoral!$A:$A,0))&"","não consta")) -> não consta | M3: =IF(A3="","",IF(OR(AND(K3<>"",LOWER(K3)<>"não consta"),AND(L3<>"",LOWER(L3)<>"não consta"),IFERROR(INDEX(Empresas!$G:$G,MATCH(A3,Empresas!$A:$A,0))&"","")<>""),"SIM","")) -> SIM | O3: =IF(D3="","",YEAR(D3)) -> 2025 | P3: EXEMPLO — exclua esta linha
A4: 11222333000186 | B4: ALIMENTOS MODELO LTDA | C4: 120000 | D4: 45961 | E4: L004 | F4: Pagamento | G4: Secretaria Municipal de Educação de Cidade Exemplo | H4: 2025OB000789 | I4: Alimentação escolar | J4: =IF(A4="","",IFERROR(INDEX(Empresas!$D:$D,MATCH(A4,Empresas!$A:$A,0))&"","não consta")) -> 5620-1/01 Fornecimento de alimentos preparados preponderantemente para empresas | K4: =IF(A4="","",IFERROR(INDEX(Sancoes!$B:$B,MATCH(A4,Sancoes!$A:$A,0))&"","não consta")) -> Não consta | L4: =IF(A4="","",IFERROR(INDEX(Eleitoral!$B:$B,MATCH(A4,Eleitoral!$A:$A,0))&"","não consta")) -> não consta | M4: =IF(A4="","",IF(OR(AND(K4<>"",LOWER(K4)<>"não consta"),AND(L4<>"",LOWER(L4)<>"não consta"),IFERROR(INDEX(Empresas!$G:$G,MATCH(A4,Empresas!$A:$A,0))&"","")<>""),"SIM","")) -> SIM | O4: =IF(D4="","",YEAR(D4)) -> 2025 | P4: EXEMPLO — exclua esta linha
A5: 44555666000186 | B5: CONSTRUTORA EXEMPLO LTDA | C5: 460000 | D5: 45107 | E5: L004 | F5: Pagamento | G5: Secretaria Municipal de Obras de Cidade Exemplo | H5: 2023OB000321 | I5: Reforma de escolas | J5: =IF(A5="","",IFERROR(INDEX(Empresas!$D:$D,MATCH(A5,Empresas!$A:$A,0))&"","não consta")) -> 4120-4/00 Construção de edifícios | K5: =IF(A5="","",IFERROR(INDEX(Sancoes!$B:$B,MATCH(A5,Sancoes!$A:$A,0))&"","não consta")) -> Impedimento de licitar e contratar | L5: =IF(A5="","",IFERROR(INDEX(Eleitoral!$B:$B,MATCH(A5,Eleitoral!$A:$A,0))&"","não consta")) -> não consta | M5: =IF(A5="","",IF(OR(AND(K5<>"",LOWER(K5)<>"não consta"),AND(L5<>"",LOWER(L5)<>"não consta"),IFERROR(INDEX(Empresas!$G:$G,MATCH(A5,Empresas!$A:$A,0))&"","")<>""),"SIM","")) -> SIM | N5: A sanção aplicada por outra cidade valia aqui? Leia a abrangência. | O5: =IF(D5="","",YEAR(D5)) -> 2023 | P5: EXEMPLO — exclua esta linha
A6: 77888999000186 | B6: GRÁFICA EXEMPLO LTDA | C6: 38000 | D6: 45762 | E6: L004 | F6: Pagamento | G6: Câmara Municipal de Cidade Exemplo | H6: 2025OB000112 | I6: Divulgação institucional | J6: =IF(A6="","",IFERROR(INDEX(Empresas!$D:$D,MATCH(A6,Empresas!$A:$A,0))&"","não consta")) -> 1813-0/01 Impressão de material para uso publicitário | K6: =IF(A6="","",IFERROR(INDEX(Sancoes!$B:$B,MATCH(A6,Sancoes!$A:$A,0))&"","não consta")) -> Não consta | L6: =IF(A6="","",IFERROR(INDEX(Eleitoral!$B:$B,MATCH(A6,Eleitoral!$A:$A,0))&"","não consta")) -> Sicrano Candidato — vereador, 2024 | M6: =IF(A6="","",IF(OR(AND(K6<>"",LOWER(K6)<>"não consta"),AND(L6<>"",LOWER(L6)<>"não consta"),IFERROR(INDEX(Empresas!$G:$G,MATCH(A6,Empresas!$A:$A,0))&"","")<>""),"SIM","")) -> SIM | N6: Como a Câmara escolheu a gráfica que fez a campanha do vereador? | O6: =IF(D6="","",YEAR(D6)) -> 2025 | P6: EXEMPLO — exclua esta linha
J7: =IF(A7="","",IFERROR(INDEX(Empresas!$D:$D,MATCH(A7,Empresas!$A:$A,0))&"","não consta")) | K7: =IF(A7="","",IFERROR(INDEX(Sancoes!$B:$B,MATCH(A7,Sancoes!$A:$A,0))&"","não consta")) | L7: =IF(A7="","",IFERROR(INDEX(Eleitoral!$B:$B,MATCH(A7,Eleitoral!$A:$A,0))&"","não consta")) | M7: =IF(A7="","",IF(OR(AND(K7<>"",LOWER(K7)<>"não consta"),AND(L7<>"",LOWER(L7)<>"não consta"),IFERROR(INDEX(Empresas!$G:$G,MATCH(A7,Empresas!$A:$A,0))&"","")<>""),"SIM","")) | O7: =IF(D7="","",YEAR(D7))
J8: =IF(A8="","",IFERROR(INDEX(Empresas!$D:$D,MATCH(A8,Empresas!$A:$A,0))&"","não consta")) | K8: =IF(A8="","",IFERROR(INDEX(Sancoes!$B:$B,MATCH(A8,Sancoes!$A:$A,0))&"","não consta")) | L8: =IF(A8="","",IFERROR(INDEX(Eleitoral!$B:$B,MATCH(A8,Eleitoral!$A:$A,0))&"","não consta")) | M8: =IF(A8="","",IF(OR(AND(K8<>"",LOWER(K8)<>"não consta"),AND(L8<>"",LOWER(L8)<>"não consta"),IFERROR(INDEX(Empresas!$G:$G,MATCH(A8,Empresas!$A:$A,0))&"","")<>""),"SIM","")) | O8: =IF(D8="","",YEAR(D8))
J9: =IF(A9="","",IFERROR(INDEX(Empresas!$D:$D,MATCH(A9,Empresas!$A:$A,0))&"","não consta")) | K9: =IF(A9="","",IFERROR(INDEX(Sancoes!$B:$B,MATCH(A9,Sancoes!$A:$A,0))&"","não consta")) | L9: =IF(A9="","",IFERROR(INDEX(Eleitoral!$B:$B,MATCH(A9,Eleitoral!$A:$A,0))&"","não consta")) | M9: =IF(A9="","",IF(OR(AND(K9<>"",LOWER(K9)<>"não consta"),AND(L9<>"",LOWER(L9)<>"não consta"),IFERROR(INDEX(Empresas!$G:$G,MATCH(A9,Empresas!$A:$A,0))&"","")<>""),"SIM","")) | O9: =IF(D9="","",YEAR(D9))
J10: =IF(A10="","",IFERROR(INDEX(Empresas!$D:$D,MATCH(A10,Empresas!$A:$A,0))&"","não consta")) | K10: =IF(A10="","",IFERROR(INDEX(Sancoes!$B:$B,MATCH(A10,Sancoes!$A:$A,0))&"","não consta")) | L10: =IF(A10="","",IFERROR(INDEX(Eleitoral!$B:$B,MATCH(A10,Eleitoral!$A:$A,0))&"","não consta")) | M10: =IF(A10="","",IF(OR(AND(K10<>"",LOWER(K10)<>"não consta"),AND(L10<>"",LOWER(L10)<>"não consta"),IFERROR(INDEX(Empresas!$G:$G,MATCH(A10,Empresas!$A:$A,0))&"","")<>""),"SIM","")) | O10: =IF(D10="","",YEAR(D10))
J11: =IF(A11="","",IFERROR(INDEX(Empresas!$D:$D,MATCH(A11,Empresas!$A:$A,0))&"","não consta")) | K11: =IF(A11="","",IFERROR(INDEX(Sancoes!$B:$B,MATCH(A11,Sancoes!$A:$A,0))&"","não consta")) | L11: =IF(A11="","",IFERROR(INDEX(Eleitoral!$B:$B,MATCH(A11,Eleitoral!$A:$A,0))&"","não consta")) | M11: =IF(A11="","",IF(OR(AND(K11<>"",LOWER(K11)<>"não consta"),AND(L11<>"",LOWER(L11)<>"não consta"),IFERROR(INDEX(Empresas!$G:$G,MATCH(A11,Empresas!$A:$A,0))&"","")<>""),"SIM","")) | O11: =IF(D11="","",YEAR(D11))
J12: =IF(A12="","",IFERROR(INDEX(Empresas!$D:$D,MATCH(A12,Empresas!$A:$A,0))&"","não consta")) | K12: =IF(A12="","",IFERROR(INDEX(Sancoes!$B:$B,MATCH(A12,Sancoes!$A:$A,0))&"","não consta")) | L12: =IF(A12="","",IFERROR(INDEX(Eleitoral!$B:$B,MATCH(A12,Eleitoral!$A:$A,0))&"","não consta")) | M12: =IF(A12="","",IF(OR(AND(K12<>"",LOWER(K12)<>"não consta"),AND(L12<>"",LOWER(L12)<>"não consta"),IFERROR(INDEX(Empresas!$G:$G,MATCH(A12,Empresas!$A:$A,0))&"","")<>""),"SIM","")) | O12: =IF(D12="","",YEAR(D12))
J13: =IF(A13="","",IFERROR(INDEX(Empresas!$D:$D,MATCH(A13,Empresas!$A:$A,0))&"","não consta")) | K13: =IF(A13="","",IFERROR(INDEX(Sancoes!$B:$B,MATCH(A13,Sancoes!$A:$A,0))&"","não consta")) | L13: =IF(A13="","",IFERROR(INDEX(Eleitoral!$B:$B,MATCH(A13,Eleitoral!$A:$A,0))&"","não consta")) | M13: =IF(A13="","",IF(OR(AND(K13<>"",LOWER(K13)<>"não consta"),AND(L13<>"",LOWER(L13)<>"não consta"),IFERROR(INDEX(Empresas!$G:$G,MATCH(A13,Empresas!$A:$A,0))&"","")<>""),"SIM","")) | O13: =IF(D13="","",YEAR(D13))
J14: =IF(A14="","",IFERROR(INDEX(Empresas!$D:$D,MATCH(A14,Empresas!$A:$A,0))&"","não consta")) | K14: =IF(A14="","",IFERROR(INDEX(Sancoes!$B:$B,MATCH(A14,Sancoes!$A:$A,0))&"","não consta")) | L14: =IF(A14="","",IFERROR(INDEX(Eleitoral!$B:$B,MATCH(A14,Eleitoral!$A:$A,0))&"","não consta")) | M14: =IF(A14="","",IF(OR(AND(K14<>"",LOWER(K14)<>"não consta"),AND(L14<>"",LOWER(L14)<>"não consta"),IFERROR(INDEX(Empresas!$G:$G,MATCH(A14,Empresas!$A:$A,0))&"","")<>""),"SIM","")) | O14: =IF(D14="","",YEAR(D14))
J15: =IF(A15="","",IFERROR(INDEX(Empresas!$D:$D,MATCH(A15,Empresas!$A:$A,0))&"","não consta")) | K15: =IF(A15="","",IFERROR(INDEX(Sancoes!$B:$B,MATCH(A15,Sancoes!$A:$A,0))&"","não consta")) | L15: =IF(A15="","",IFERROR(INDEX(Eleitoral!$B:$B,MATCH(A15,Eleitoral!$A:$A,0))&"","não consta")) | M15: =IF(A15="","",IF(OR(AND(K15<>"",LOWER(K15)<>"não consta"),AND(L15<>"",LOWER(L15)<>"não consta"),IFERROR(INDEX(Empresas!$G:$G,MATCH(A15,Empresas!$A:$A,0))&"","")<>""),"SIM","")) | O15: =IF(D15="","",YEAR(D15))
J16: =IF(A16="","",IFERROR(INDEX(Empresas!$D:$D,MATCH(A16,Empresas!$A:$A,0))&"","não consta")) | K16: =IF(A16="","",IFERROR(INDEX(Sancoes!$B:$B,MATCH(A16,Sancoes!$A:$A,0))&"","não consta")) | L16: =IF(A16="","",IFERROR(INDEX(Eleitoral!$B:$B,MATCH(A16,Eleitoral!$A:$A,0))&"","não consta")) | M16: =IF(A16="","",IF(OR(AND(K16<>"",LOWER(K16)<>"não consta"),AND(L16<>"",LOWER(L16)<>"não consta"),IFERROR(INDEX(Empresas!$G:$G,MATCH(A16,Empresas!$A:$A,0))&"","")<>""),"SIM","")) | O16: =IF(D16="","",YEAR(D16))
J17: =IF(A17="","",IFERROR(INDEX(Empresas!$D:$D,MATCH(A17,Empresas!$A:$A,0))&"","não consta")) | K17: =IF(A17="","",IFERROR(INDEX(Sancoes!$B:$B,MATCH(A17,Sancoes!$A:$A,0))&"","não consta")) | L17: =IF(A17="","",IFERROR(INDEX(Eleitoral!$B:$B,MATCH(A17,Eleitoral!$A:$A,0))&"","não consta")) | M17: =IF(A17="","",IF(OR(AND(K17<>"",LOWER(K17)<>"não consta"),AND(L17<>"",LOWER(L17)<>"não consta"),IFERROR(INDEX(Empresas!$G:$G,MATCH(A17,Empresas!$A:$A,0))&"","")<>""),"SIM","")) | O17: =IF(D17="","",YEAR(D17))
J18: =IF(A18="","",IFERROR(INDEX(Empresas!$D:$D,MATCH(A18,Empresas!$A:$A,0))&"","não consta")) | K18: =IF(A18="","",IFERROR(INDEX(Sancoes!$B:$B,MATCH(A18,Sancoes!$A:$A,0))&"","não consta")) | L18: =IF(A18="","",IFERROR(INDEX(Eleitoral!$B:$B,MATCH(A18,Eleitoral!$A:$A,0))&"","não consta")) | M18: =IF(A18="","",IF(OR(AND(K18<>"",LOWER(K18)<>"não consta"),AND(L18<>"",LOWER(L18)<>"não consta"),IFERROR(INDEX(Empresas!$G:$G,MATCH(A18,Empresas!$A:$A,0))&"","")<>""),"SIM","")) | O18: =IF(D18="","",YEAR(D18))
... J2001: =IF(A2001="","",IFERROR(INDEX(Empresas!$D:$D,MATCH(A2001,Empresas!$A:$A,0))&"","não consta")) | K2001: =IF(A2001="","",IFERROR(INDEX(Sancoes!$B:$B,MATCH(A2001,Sancoes!$A:$A,0))&"","não consta")) | L2001: =IF(A2001="","",IFERROR(INDEX(Eleitoral!$B:$B,MATCH(A2001,Eleitoral!$A:$A,0))&"","não consta")) | M2001: =IF(A2001="","",IF(OR(AND(K2001<>"",LOWER(K2001)<>"não consta"),AND(L2001<>"",LOWER(L2001)<>"não consta"),IFERROR(INDEX(Empresas!$G:$G,MATCH(A2001,Empresas!$A:$A,0))&"","")<>""),"SIM","")) | O2001: =IF(D2001="","",YEAR(D2001))

Sheet Contratos
A1: CNPJ do fornecedor | B1: Órgão | C1: Objeto | D1: Valor (R$) | E1: Modalidade | F1: Data do contrato | G1: Data de abertura (fórmula) | H1: Vigência | I1: Aberta menos de 6 meses antes? (auto) | J1: Sanção no cadastro (auto) | K1: Sanção vigente na data (auto) | L1: Fornecedor (auto) | M1: Nº do contrato | N1: Aditivos (R$) | O1: Acréscimo (auto) | P1: Alerta de aditivo (auto) | Q1: Fonte (ID do Log) | R1: Observações
A2: 11222333000186 | B2: Secretaria Municipal de Educação de Cidade Exemplo | C2: Fornecimento de merenda escolar | D2: 480000 | E2: Dispensa | F2: 45889 | G2: =IF(A2="","",IFERROR(IF(INDEX(Empresas!$C:$C,MATCH(A2,Empresas!$A:$A,0))="","",INDEX(Empresas!$C:$C,MATCH(A2,Empresas!$A:$A,0))),"")) -> 45726 | H2: 46253 | I2: =IF(OR(F2="",G2=""),"",IF(F2-G2<0,"CONTRATO ANTERIOR À ABERTURA — conferir datas",IF(F2-G2<180,"ABERTA MENOS DE 6 MESES ANTES",""))) -> ABERTA MENOS DE 6 MESES ANTES | J2: =IF(A2="","",IFERROR(INDEX(Sancoes!$B:$B,MATCH(A2,Sancoes!$A:$A,0))&"","não consta")) -> Não consta | K2: =IF(OR(A2="",F2=""),"",IF(SUMPRODUCT((Sancoes!$A$2:$A$301=A2)*(Sancoes!$B$2:$B$301<>"Não consta")*(Sancoes!$D$2:$D$301<>"")*(Sancoes!$D$2:$D$301<=F2)*(((Sancoes!$E$2:$E$301="")+(Sancoes!$E$2:$E$301>=F2))>0))>0,"SANÇÃO VIGENTE NA DATA — leia o tipo e a abrangência","")) | L2: =IF(A2="","",IFERROR(INDEX(Empresas!$B:$B,MATCH(A2,Empresas!$A:$A,0))&"","cadastre o CNPJ em Empresas")) -> ALIMENTOS MODELO LTDA | M2: 045/2025 | N2: 150000 | O2: =IF(OR(D2="",D2=0,N2=""),"",N2/D2) -> 0.3125 | P2: =IF(O2="","",IF(O2>0.25,"ACRÉSCIMO ACIMA DE 25% — conferir","")) -> ACRÉSCIMO ACIMA DE 25% — conferir | Q2: L003 | R2: EXEMPLO — exclua esta linha
A3: 44555666000186 | B3: Secretaria Municipal de Obras de Cidade Exemplo | C3: Reforma de escola municipal | D3: 2300000 | E3: Concorrência | F3: 45048 | G3: =IF(A3="","",IFERROR(IF(INDEX(Empresas!$C:$C,MATCH(A3,Empresas!$A:$A,0))="","",INDEX(Empresas!$C:$C,MATCH(A3,Empresas!$A:$A,0))),"")) -> 42156 | H3: 45413 | I3: =IF(OR(F3="",G3=""),"",IF(F3-G3<0,"CONTRATO ANTERIOR À ABERTURA — conferir datas",IF(F3-G3<180,"ABERTA MENOS DE 6 MESES ANTES",""))) | J3: =IF(A3="","",IFERROR(INDEX(Sancoes!$B:$B,MATCH(A3,Sancoes!$A:$A,0))&"","não consta")) -> Impedimento de licitar e contratar | K3: =IF(OR(A3="",F3=""),"",IF(SUMPRODUCT((Sancoes!$A$2:$A$301=A3)*(Sancoes!$B$2:$B$301<>"Não consta")*(Sancoes!$D$2:$D$301<>"")*(Sancoes!$D$2:$D$301<=F3)*(((Sancoes!$E$2:$E$301="")+(Sancoes!$E$2:$E$301>=F3))>0))>0,"SANÇÃO VIGENTE NA DATA — leia o tipo e a abrangência","")) -> SANÇÃO VIGENTE NA DATA — leia o tipo e a abrangência | L3: =IF(A3="","",IFERROR(INDEX(Empresas!$B:$B,MATCH(A3,Empresas!$A:$A,0))&"","cadastre o CNPJ em Empresas")) -> CONSTRUTORA EXEMPLO LTDA | M3: 012/2023 | N3: 0 | O3: =IF(OR(D3="",D3=0,N3=""),"",N3/D3) -> 0 | P3: =IF(O3="","",IF(O3>0.25,"ACRÉSCIMO ACIMA DE 25% — conferir","")) | Q3: L013 | R3: EXEMPLO — a sanção é de outra cidade e só vale lá: leia a abrangência antes de concluir
A4: 77888999000186 | B4: Câmara Municipal de Cidade Exemplo | C4: Impressão de material gráfico | D4: 95000 | E4: Pregão | F4: 45719 | G4: =IF(A4="","",IFERROR(IF(INDEX(Empresas!$C:$C,MATCH(A4,Empresas!$A:$A,0))="","",INDEX(Empresas!$C:$C,MATCH(A4,Empresas!$A:$A,0))),"")) -> 41011 | H4: 46083 | I4: =IF(OR(F4="",G4=""),"",IF(F4-G4<0,"CONTRATO ANTERIOR À ABERTURA — conferir datas",IF(F4-G4<180,"ABERTA MENOS DE 6 MESES ANTES",""))) | J4: =IF(A4="","",IFERROR(INDEX(Sancoes!$B:$B,MATCH(A4,Sancoes!$A:$A,0))&"","não consta")) -> Não consta | K4: =IF(OR(A4="",F4=""),"",IF(SUMPRODUCT((Sancoes!$A$2:$A$301=A4)*(Sancoes!$B$2:$B$301<>"Não consta")*(Sancoes!$D$2:$D$301<>"")*(Sancoes!$D$2:$D$301<=F4)*(((Sancoes!$E$2:$E$301="")+(Sancoes!$E$2:$E$301>=F4))>0))>0,"SANÇÃO VIGENTE NA DATA — leia o tipo e a abrangência","")) | L4: =IF(A4="","",IFERROR(INDEX(Empresas!$B:$B,MATCH(A4,Empresas!$A:$A,0))&"","cadastre o CNPJ em Empresas")) -> GRÁFICA EXEMPLO LTDA | M4: 008/2025 | N4: 0 | O4: =IF(OR(D4="",D4=0,N4=""),"",N4/D4) -> 0 | P4: =IF(O4="","",IF(O4>0.25,"ACRÉSCIMO ACIMA DE 25% — conferir","")) | Q4: L003 | R4: EXEMPLO — a gráfica fez a campanha do vereador em 2024 (veja Eleitoral)
G5: =IF(A5="","",IFERROR(IF(INDEX(Empresas!$C:$C,MATCH(A5,Empresas!$A:$A,0))="","",INDEX(Empresas!$C:$C,MATCH(A5,Empresas!$A:$A,0))),"")) | I5: =IF(OR(F5="",G5=""),"",IF(F5-G5<0,"CONTRATO ANTERIOR À ABERTURA — conferir datas",IF(F5-G5<180,"ABERTA MENOS DE 6 MESES ANTES",""))) | J5: =IF(A5="","",IFERROR(INDEX(Sancoes!$B:$B,MATCH(A5,Sancoes!$A:$A,0))&"","não consta")) | K5: =IF(OR(A5="",F5=""),"",IF(SUMPRODUCT((Sancoes!$A$2:$A$301=A5)*(Sancoes!$B$2:$B$301<>"Não consta")*(Sancoes!$D$2:$D$301<>"")*(Sancoes!$D$2:$D$301<=F5)*(((Sancoes!$E$2:$E$301="")+(Sancoes!$E$2:$E$301>=F5))>0))>0,"SANÇÃO VIGENTE NA DATA — leia o tipo e a abrangência","")) | L5: =IF(A5="","",IFERROR(INDEX(Empresas!$B:$B,MATCH(A5,Empresas!$A:$A,0))&"","cadastre o CNPJ em Empresas")) | O5: =IF(OR(D5="",D5=0,N5=""),"",N5/D5) | P5: =IF(O5="","",IF(O5>0.25,"ACRÉSCIMO ACIMA DE 25% — conferir",""))
G6: =IF(A6="","",IFERROR(IF(INDEX(Empresas!$C:$C,MATCH(A6,Empresas!$A:$A,0))="","",INDEX(Empresas!$C:$C,MATCH(A6,Empresas!$A:$A,0))),"")) | I6: =IF(OR(F6="",G6=""),"",IF(F6-G6<0,"CONTRATO ANTERIOR À ABERTURA — conferir datas",IF(F6-G6<180,"ABERTA MENOS DE 6 MESES ANTES",""))) | J6: =IF(A6="","",IFERROR(INDEX(Sancoes!$B:$B,MATCH(A6,Sancoes!$A:$A,0))&"","não consta")) | K6: =IF(OR(A6="",F6=""),"",IF(SUMPRODUCT((Sancoes!$A$2:$A$301=A6)*(Sancoes!$B$2:$B$301<>"Não consta")*(Sancoes!$D$2:$D$301<>"")*(Sancoes!$D$2:$D$301<=F6)*(((Sancoes!$E$2:$E$301="")+(Sancoes!$E$2:$E$301>=F6))>0))>0,"SANÇÃO VIGENTE NA DATA — leia o tipo e a abrangência","")) | L6: =IF(A6="","",IFERROR(INDEX(Empresas!$B:$B,MATCH(A6,Empresas!$A:$A,0))&"","cadastre o CNPJ em Empresas")) | O6: =IF(OR(D6="",D6=0,N6=""),"",N6/D6) | P6: =IF(O6="","",IF(O6>0.25,"ACRÉSCIMO ACIMA DE 25% — conferir",""))
G7: =IF(A7="","",IFERROR(IF(INDEX(Empresas!$C:$C,MATCH(A7,Empresas!$A:$A,0))="","",INDEX(Empresas!$C:$C,MATCH(A7,Empresas!$A:$A,0))),"")) | I7: =IF(OR(F7="",G7=""),"",IF(F7-G7<0,"CONTRATO ANTERIOR À ABERTURA — conferir datas",IF(F7-G7<180,"ABERTA MENOS DE 6 MESES ANTES",""))) | J7: =IF(A7="","",IFERROR(INDEX(Sancoes!$B:$B,MATCH(A7,Sancoes!$A:$A,0))&"","não consta")) | K7: =IF(OR(A7="",F7=""),"",IF(SUMPRODUCT((Sancoes!$A$2:$A$301=A7)*(Sancoes!$B$2:$B$301<>"Não consta")*(Sancoes!$D$2:$D$301<>"")*(Sancoes!$D$2:$D$301<=F7)*(((Sancoes!$E$2:$E$301="")+(Sancoes!$E$2:$E$301>=F7))>0))>0,"SANÇÃO VIGENTE NA DATA — leia o tipo e a abrangência","")) | L7: =IF(A7="","",IFERROR(INDEX(Empresas!$B:$B,MATCH(A7,Empresas!$A:$A,0))&"","cadastre o CNPJ em Empresas")) | O7: =IF(OR(D7="",D7=0,N7=""),"",N7/D7) | P7: =IF(O7="","",IF(O7>0.25,"ACRÉSCIMO ACIMA DE 25% — conferir",""))
G8: =IF(A8="","",IFERROR(IF(INDEX(Empresas!$C:$C,MATCH(A8,Empresas!$A:$A,0))="","",INDEX(Empresas!$C:$C,MATCH(A8,Empresas!$A:$A,0))),"")) | I8: =IF(OR(F8="",G8=""),"",IF(F8-G8<0,"CONTRATO ANTERIOR À ABERTURA — conferir datas",IF(F8-G8<180,"ABERTA MENOS DE 6 MESES ANTES",""))) | J8: =IF(A8="","",IFERROR(INDEX(Sancoes!$B:$B,MATCH(A8,Sancoes!$A:$A,0))&"","não consta")) | K8: =IF(OR(A8="",F8=""),"",IF(SUMPRODUCT((Sancoes!$A$2:$A$301=A8)*(Sancoes!$B$2:$B$301<>"Não consta")*(Sancoes!$D$2:$D$301<>"")*(Sancoes!$D$2:$D$301<=F8)*(((Sancoes!$E$2:$E$301="")+(Sancoes!$E$2:$E$301>=F8))>0))>0,"SANÇÃO VIGENTE NA DATA — leia o tipo e a abrangência","")) | L8: =IF(A8="","",IFERROR(INDEX(Empresas!$B:$B,MATCH(A8,Empresas!$A:$A,0))&"","cadastre o CNPJ em Empresas")) | O8: =IF(OR(D8="",D8=0,N8=""),"",N8/D8) | P8: =IF(O8="","",IF(O8>0.25,"ACRÉSCIMO ACIMA DE 25% — conferir",""))
G9: =IF(A9="","",IFERROR(IF(INDEX(Empresas!$C:$C,MATCH(A9,Empresas!$A:$A,0))="","",INDEX(Empresas!$C:$C,MATCH(A9,Empresas!$A:$A,0))),"")) | I9: =IF(OR(F9="",G9=""),"",IF(F9-G9<0,"CONTRATO ANTERIOR À ABERTURA — conferir datas",IF(F9-G9<180,"ABERTA MENOS DE 6 MESES ANTES",""))) | J9: =IF(A9="","",IFERROR(INDEX(Sancoes!$B:$B,MATCH(A9,Sancoes!$A:$A,0))&"","não consta")) | K9: =IF(OR(A9="",F9=""),"",IF(SUMPRODUCT((Sancoes!$A$2:$A$301=A9)*(Sancoes!$B$2:$B$301<>"Não consta")*(Sancoes!$D$2:$D$301<>"")*(Sancoes!$D$2:$D$301<=F9)*(((Sancoes!$E$2:$E$301="")+(Sancoes!$E$2:$E$301>=F9))>0))>0,"SANÇÃO VIGENTE NA DATA — leia o tipo e a abrangência","")) | L9: =IF(A9="","",IFERROR(INDEX(Empresas!$B:$B,MATCH(A9,Empresas!$A:$A,0))&"","cadastre o CNPJ em Empresas")) | O9: =IF(OR(D9="",D9=0,N9=""),"",N9/D9) | P9: =IF(O9="","",IF(O9>0.25,"ACRÉSCIMO ACIMA DE 25% — conferir",""))
G10: =IF(A10="","",IFERROR(IF(INDEX(Empresas!$C:$C,MATCH(A10,Empresas!$A:$A,0))="","",INDEX(Empresas!$C:$C,MATCH(A10,Empresas!$A:$A,0))),"")) | I10: =IF(OR(F10="",G10=""),"",IF(F10-G10<0,"CONTRATO ANTERIOR À ABERTURA — conferir datas",IF(F10-G10<180,"ABERTA MENOS DE 6 MESES ANTES",""))) | J10: =IF(A10="","",IFERROR(INDEX(Sancoes!$B:$B,MATCH(A10,Sancoes!$A:$A,0))&"","não consta")) | K10: =IF(OR(A10="",F10=""),"",IF(SUMPRODUCT((Sancoes!$A$2:$A$301=A10)*(Sancoes!$B$2:$B$301<>"Não consta")*(Sancoes!$D$2:$D$301<>"")*(Sancoes!$D$2:$D$301<=F10)*(((Sancoes!$E$2:$E$301="")+(Sancoes!$E$2:$E$301>=F10))>0))>0,"SANÇÃO VIGENTE NA DATA — leia o tipo e a abrangência","")) | L10: =IF(A10="","",IFERROR(INDEX(Empresas!$B:$B,MATCH(A10,Empresas!$A:$A,0))&"","cadastre o CNPJ em Empresas")) | O10: =IF(OR(D10="",D10=0,N10=""),"",N10/D10) | P10: =IF(O10="","",IF(O10>0.25,"ACRÉSCIMO ACIMA DE 25% — conferir",""))
G11: =IF(A11="","",IFERROR(IF(INDEX(Empresas!$C:$C,MATCH(A11,Empresas!$A:$A,0))="","",INDEX(Empresas!$C:$C,MATCH(A11,Empresas!$A:$A,0))),"")) | I11: =IF(OR(F11="",G11=""),"",IF(F11-G11<0,"CONTRATO ANTERIOR À ABERTURA — conferir datas",IF(F11-G11<180,"ABERTA MENOS DE 6 MESES ANTES",""))) | J11: =IF(A11="","",IFERROR(INDEX(Sancoes!$B:$B,MATCH(A11,Sancoes!$A:$A,0))&"","não consta")) | K11: =IF(OR(A11="",F11=""),"",IF(SUMPRODUCT((Sancoes!$A$2:$A$301=A11)*(Sancoes!$B$2:$B$301<>"Não consta")*(Sancoes!$D$2:$D$301<>"")*(Sancoes!$D$2:$D$301<=F11)*(((Sancoes!$E$2:$E$301="")+(Sancoes!$E$2:$E$301>=F11))>0))>0,"SANÇÃO VIGENTE NA DATA — leia o tipo e a abrangência","")) | L11: =IF(A11="","",IFERROR(INDEX(Empresas!$B:$B,MATCH(A11,Empresas!$A:$A,0))&"","cadastre o CNPJ em Empresas")) | O11: =IF(OR(D11="",D11=0,N11=""),"",N11/D11) | P11: =IF(O11="","",IF(O11>0.25,"ACRÉSCIMO ACIMA DE 25% — conferir",""))
G12: =IF(A12="","",IFERROR(IF(INDEX(Empresas!$C:$C,MATCH(A12,Empresas!$A:$A,0))="","",INDEX(Empresas!$C:$C,MATCH(A12,Empresas!$A:$A,0))),"")) | I12: =IF(OR(F12="",G12=""),"",IF(F12-G12<0,"CONTRATO ANTERIOR À ABERTURA — conferir datas",IF(F12-G12<180,"ABERTA MENOS DE 6 MESES ANTES",""))) | J12: =IF(A12="","",IFERROR(INDEX(Sancoes!$B:$B,MATCH(A12,Sancoes!$A:$A,0))&"","não consta")) | K12: =IF(OR(A12="",F12=""),"",IF(SUMPRODUCT((Sancoes!$A$2:$A$301=A12)*(Sancoes!$B$2:$B$301<>"Não consta")*(Sancoes!$D$2:$D$301<>"")*(Sancoes!$D$2:$D$301<=F12)*(((Sancoes!$E$2:$E$301="")+(Sancoes!$E$2:$E$301>=F12))>0))>0,"SANÇÃO VIGENTE NA DATA — leia o tipo e a abrangência","")) | L12: =IF(A12="","",IFERROR(INDEX(Empresas!$B:$B,MATCH(A12,Empresas!$A:$A,0))&"","cadastre o CNPJ em Empresas")) | O12: =IF(OR(D12="",D12=0,N12=""),"",N12/D12) | P12: =IF(O12="","",IF(O12>0.25,"ACRÉSCIMO ACIMA DE 25% — conferir",""))
G13: =IF(A13="","",IFERROR(IF(INDEX(Empresas!$C:$C,MATCH(A13,Empresas!$A:$A,0))="","",INDEX(Empresas!$C:$C,MATCH(A13,Empresas!$A:$A,0))),"")) | I13: =IF(OR(F13="",G13=""),"",IF(F13-G13<0,"CONTRATO ANTERIOR À ABERTURA — conferir datas",IF(F13-G13<180,"ABERTA MENOS DE 6 MESES ANTES",""))) | J13: =IF(A13="","",IFERROR(INDEX(Sancoes!$B:$B,MATCH(A13,Sancoes!$A:$A,0))&"","não consta")) | K13: =IF(OR(A13="",F13=""),"",IF(SUMPRODUCT((Sancoes!$A$2:$A$301=A13)*(Sancoes!$B$2:$B$301<>"Não consta")*(Sancoes!$D$2:$D$301<>"")*(Sancoes!$D$2:$D$301<=F13)*(((Sancoes!$E$2:$E$301="")+(Sancoes!$E$2:$E$301>=F13))>0))>0,"SANÇÃO VIGENTE NA DATA — leia o tipo e a abrangência","")) | L13: =IF(A13="","",IFERROR(INDEX(Empresas!$B:$B,MATCH(A13,Empresas!$A:$A,0))&"","cadastre o CNPJ em Empresas")) | O13: =IF(OR(D13="",D13=0,N13=""),"",N13/D13) | P13: =IF(O13="","",IF(O13>0.25,"ACRÉSCIMO ACIMA DE 25% — conferir",""))
G14: =IF(A14="","",IFERROR(IF(INDEX(Empresas!$C:$C,MATCH(A14,Empresas!$A:$A,0))="","",INDEX(Empresas!$C:$C,MATCH(A14,Empresas!$A:$A,0))),"")) | I14: =IF(OR(F14="",G14=""),"",IF(F14-G14<0,"CONTRATO ANTERIOR À ABERTURA — conferir datas",IF(F14-G14<180,"ABERTA MENOS DE 6 MESES ANTES",""))) | J14: =IF(A14="","",IFERROR(INDEX(Sancoes!$B:$B,MATCH(A14,Sancoes!$A:$A,0))&"","não consta")) | K14: =IF(OR(A14="",F14=""),"",IF(SUMPRODUCT((Sancoes!$A$2:$A$301=A14)*(Sancoes!$B$2:$B$301<>"Não consta")*(Sancoes!$D$2:$D$301<>"")*(Sancoes!$D$2:$D$301<=F14)*(((Sancoes!$E$2:$E$301="")+(Sancoes!$E$2:$E$301>=F14))>0))>0,"SANÇÃO VIGENTE NA DATA — leia o tipo e a abrangência","")) | L14: =IF(A14="","",IFERROR(INDEX(Empresas!$B:$B,MATCH(A14,Empresas!$A:$A,0))&"","cadastre o CNPJ em Empresas")) | O14: =IF(OR(D14="",D14=0,N14=""),"",N14/D14) | P14: =IF(O14="","",IF(O14>0.25,"ACRÉSCIMO ACIMA DE 25% — conferir",""))
G15: =IF(A15="","",IFERROR(IF(INDEX(Empresas!$C:$C,MATCH(A15,Empresas!$A:$A,0))="","",INDEX(Empresas!$C:$C,MATCH(A15,Empresas!$A:$A,0))),"")) | I15: =IF(OR(F15="",G15=""),"",IF(F15-G15<0,"CONTRATO ANTERIOR À ABERTURA — conferir datas",IF(F15-G15<180,"ABERTA MENOS DE 6 MESES ANTES",""))) | J15: =IF(A15="","",IFERROR(INDEX(Sancoes!$B:$B,MATCH(A15,Sancoes!$A:$A,0))&"","não consta")) | K15: =IF(OR(A15="",F15=""),"",IF(SUMPRODUCT((Sancoes!$A$2:$A$301=A15)*(Sancoes!$B$2:$B$301<>"Não consta")*(Sancoes!$D$2:$D$301<>"")*(Sancoes!$D$2:$D$301<=F15)*(((Sancoes!$E$2:$E$301="")+(Sancoes!$E$2:$E$301>=F15))>0))>0,"SANÇÃO VIGENTE NA DATA — leia o tipo e a abrangência","")) | L15: =IF(A15="","",IFERROR(INDEX(Empresas!$B:$B,MATCH(A15,Empresas!$A:$A,0))&"","cadastre o CNPJ em Empresas")) | O15: =IF(OR(D15="",D15=0,N15=""),"",N15/D15) | P15: =IF(O15="","",IF(O15>0.25,"ACRÉSCIMO ACIMA DE 25% — conferir",""))
G16: =IF(A16="","",IFERROR(IF(INDEX(Empresas!$C:$C,MATCH(A16,Empresas!$A:$A,0))="","",INDEX(Empresas!$C:$C,MATCH(A16,Empresas!$A:$A,0))),"")) | I16: =IF(OR(F16="",G16=""),"",IF(F16-G16<0,"CONTRATO ANTERIOR À ABERTURA — conferir datas",IF(F16-G16<180,"ABERTA MENOS DE 6 MESES ANTES",""))) | J16: =IF(A16="","",IFERROR(INDEX(Sancoes!$B:$B,MATCH(A16,Sancoes!$A:$A,0))&"","não consta")) | K16: =IF(OR(A16="",F16=""),"",IF(SUMPRODUCT((Sancoes!$A$2:$A$301=A16)*(Sancoes!$B$2:$B$301<>"Não consta")*(Sancoes!$D$2:$D$301<>"")*(Sancoes!$D$2:$D$301<=F16)*(((Sancoes!$E$2:$E$301="")+(Sancoes!$E$2:$E$301>=F16))>0))>0,"SANÇÃO VIGENTE NA DATA — leia o tipo e a abrangência","")) | L16: =IF(A16="","",IFERROR(INDEX(Empresas!$B:$B,MATCH(A16,Empresas!$A:$A,0))&"","cadastre o CNPJ em Empresas")) | O16: =IF(OR(D16="",D16=0,N16=""),"",N16/D16) | P16: =IF(O16="","",IF(O16>0.25,"ACRÉSCIMO ACIMA DE 25% — conferir",""))
... G1001: =IF(A1001="","",IFERROR(IF(INDEX(Empresas!$C:$C,MATCH(A1001,Empresas!$A:$A,0))="","",INDEX(Empresas!$C:$C,MATCH(A1001,Empresas!$A:$A,0))),"")) | I1001: =IF(OR(F1001="",G1001=""),"",IF(F1001-G1001<0,"CONTRATO ANTERIOR À ABERTURA — conferir datas",IF(F1001-G1001<180,"ABERTA MENOS DE 6 MESES ANTES",""))) | J1001: =IF(A1001="","",IFERROR(INDEX(Sancoes!$B:$B,MATCH(A1001,Sancoes!$A:$A,0))&"","não consta")) | K1001: =IF(OR(A1001="",F1001=""),"",IF(SUMPRODUCT((Sancoes!$A$2:$A$301=A1001)*(Sancoes!$B$2:$B$301<>"Não consta")*(Sancoes!$D$2:$D$301<>"")*(Sancoes!$D$2:$D$301<=F1001)*(((Sancoes!$E$2:$E$301="")+(Sancoes!$E$2:$E$301>=F1001))>0))>0,"SANÇÃO VIGENTE NA DATA — leia o tipo e a abrangência","")) | L1001: =IF(A1001="","",IFERROR(INDEX(Empresas!$B:$B,MATCH(A1001,Empresas!$A:$A,0))&"","cadastre o CNPJ em Empresas")) | O1001: =IF(OR(D1001="",D1001=0,N1001=""),"",N1001/D1001) | P1001: =IF(O1001="","",IF(O1001>0.25,"ACRÉSCIMO ACIMA DE 25% — conferir",""))

Sheet Sancoes
A1: CNPJ | B1: Tipo de sanção | C1: Abrangência | D1: Período: início | E1: Período: fim | F1: Cadastro | G1: Nome no cadastro | H1: Órgão que puniu | I1: Vigente hoje? (auto) | J1: Fonte (ID do Log) | K1: Observações
A2: 44555666000186 | B2: Impedimento de licitar e contratar | C2: Só no ente que puniu | D2: 44936 | E2: 45301 | F2: CEIS | G2: CONSTRUTORA EXEMPLO LTDA | H2: Prefeitura de Outra Cidade | I2: =IF(OR(A2="",D2=""),"",IF(AND(D2<=TODAY(),OR(E2="",E2>=TODAY())),"VIGENTE","encerrada")) -> encerrada | J2: L005 | K2: EXEMPLO — exclua esta linha
A3: 11222333000186 | B3: Não consta | G3: ALIMENTOS MODELO LTDA | I3: =IF(OR(A3="",D3=""),"",IF(AND(D3<=TODAY(),OR(E3="",E3>=TODAY())),"VIGENTE","encerrada")) | J3: L005 | K3: EXEMPLO — CEIS, CNEP e CEPIM consultados em 02/09/2026
A4: 77888999000186 | B4: Não consta | G4: GRÁFICA EXEMPLO LTDA | I4: =IF(OR(A4="",D4=""),"",IF(AND(D4<=TODAY(),OR(E4="",E4>=TODAY())),"VIGENTE","encerrada")) | J4: L005 | K4: EXEMPLO — CEIS, CNEP e CEPIM consultados em 02/09/2026
I5: =IF(OR(A5="",D5=""),"",IF(AND(D5<=TODAY(),OR(E5="",E5>=TODAY())),"VIGENTE","encerrada"))
I6: =IF(OR(A6="",D6=""),"",IF(AND(D6<=TODAY(),OR(E6="",E6>=TODAY())),"VIGENTE","encerrada"))
I7: =IF(OR(A7="",D7=""),"",IF(AND(D7<=TODAY(),OR(E7="",E7>=TODAY())),"VIGENTE","encerrada"))
I8: =IF(OR(A8="",D8=""),"",IF(AND(D8<=TODAY(),OR(E8="",E8>=TODAY())),"VIGENTE","encerrada"))
I9: =IF(OR(A9="",D9=""),"",IF(AND(D9<=TODAY(),OR(E9="",E9>=TODAY())),"VIGENTE","encerrada"))
I10: =IF(OR(A10="",D10=""),"",IF(AND(D10<=TODAY(),OR(E10="",E10>=TODAY())),"VIGENTE","encerrada"))
I11: =IF(OR(A11="",D11=""),"",IF(AND(D11<=TODAY(),OR(E11="",E11>=TODAY())),"VIGENTE","encerrada"))
I12: =IF(OR(A12="",D12=""),"",IF(AND(D12<=TODAY(),OR(E12="",E12>=TODAY())),"VIGENTE","encerrada"))
I13: =IF(OR(A13="",D13=""),"",IF(AND(D13<=TODAY(),OR(E13="",E13>=TODAY())),"VIGENTE","encerrada"))
I14: =IF(OR(A14="",D14=""),"",IF(AND(D14<=TODAY(),OR(E14="",E14>=TODAY())),"VIGENTE","encerrada"))
I15: =IF(OR(A15="",D15=""),"",IF(AND(D15<=TODAY(),OR(E15="",E15>=TODAY())),"VIGENTE","encerrada"))
I16: =IF(OR(A16="",D16=""),"",IF(AND(D16<=TODAY(),OR(E16="",E16>=TODAY())),"VIGENTE","encerrada"))
... I301: =IF(OR(A301="",D301=""),"",IF(AND(D301<=TODAY(),OR(E301="",E301>=TODAY())),"VIGENTE","encerrada"))

Sheet Empresas
A1: CNPJ | B1: Razão social | C1: Data de abertura | D1: CNAE | E1: Capital social (R$) | F1: Endereço | G1: Sinal | H1: Nome fantasia | I1: Situação cadastral | J1: Município/UF | K1: Contratos (auto) | L1: Valor contratado com aditivos (R$) (auto) | M1: Empenhado (R$) (auto) | N1: Pago (R$) (auto) | O1: Capital ÷ contratado (auto) | P1: Sanções registradas (auto) | Q1: Sócios (auto) | R1: Sócios que estão em Pessoas (auto) | S1: Fonte (ID do Log) | T1: Observações
A2: 11222333000186 | B2: ALIMENTOS MODELO LTDA | C2: 45726 | D2: 5620-1/01 Fornecimento de alimentos preparados preponderantemente para empresas | E2: 10000 | F2: Rua Exemplo, 100, sala 2 | G2: Aberta cinco meses antes do contrato; capital de R$ 10 mil para contrato de R$ 480 mil | H2: Modelo Alimentos | I2: Ativa | J2: Cidade Exemplo/UF | K2: =IF(A2="","",COUNTIF(Contratos!$A:$A,A2)) -> 1 | L2: =IF(A2="","",SUMIFS(Contratos!$D:$D,Contratos!$A:$A,A2)+SUMIFS(Contratos!$N:$N,Contratos!$A:$A,A2)) -> 630000 | M2: =IF(A2="","",SUMIFS(Pagamentos!$C:$C,Pagamentos!$A:$A,A2,Pagamentos!$F:$F,"Empenho")) -> 480000 | N2: =IF(A2="","",SUMIFS(Pagamentos!$C:$C,Pagamentos!$A:$A,A2,Pagamentos!$F:$F,"Pagamento")) -> 240000 | O2: =IF(OR(A2="",E2="",L2="",L2=0),"",E2/L2) -> 0.015873016 | P2: =IF(A2="","",COUNTIFS(Sancoes!$A:$A,A2,Sancoes!$B:$B,"<>Não consta")) -> 0 | Q2: =IF(A2="","",COUNTIF(Socios!$A:$A,A2)) -> 1 | R2: =IF(A2="","",COUNTIFS(Socios!$A:$A,A2,Socios!$K:$K,"SIM")) -> 1 | S2: L001 | T2: EXEMPLO — CNPJ fictício; exclua esta linha
A3: 44555666000186 | B3: CONSTRUTORA EXEMPLO LTDA | C3: 42156 | D3: 4120-4/00 Construção de edifícios | E3: 2000000 | F3: Avenida Modelo, 500 | G3: Sanção no CEIS aplicada por outra cidade | H3: Construtora Exemplo | I3: Ativa | J3: Cidade Exemplo/UF | K3: =IF(A3="","",COUNTIF(Contratos!$A:$A,A3)) -> 1 | L3: =IF(A3="","",SUMIFS(Contratos!$D:$D,Contratos!$A:$A,A3)+SUMIFS(Contratos!$N:$N,Contratos!$A:$A,A3)) -> 2300000 | M3: =IF(A3="","",SUMIFS(Pagamentos!$C:$C,Pagamentos!$A:$A,A3,Pagamentos!$F:$F,"Empenho")) -> 0 | N3: =IF(A3="","",SUMIFS(Pagamentos!$C:$C,Pagamentos!$A:$A,A3,Pagamentos!$F:$F,"Pagamento")) -> 460000 | O3: =IF(OR(A3="",E3="",L3="",L3=0),"",E3/L3) -> 0.86956522 | P3: =IF(A3="","",COUNTIFS(Sancoes!$A:$A,A3,Sancoes!$B:$B,"<>Não consta")) -> 1 | Q3: =IF(A3="","",COUNTIF(Socios!$A:$A,A3)) -> 1 | R3: =IF(A3="","",COUNTIFS(Socios!$A:$A,A3,Socios!$K:$K,"SIM")) -> 0 | S3: L001 | T3: EXEMPLO — CNPJ fictício; exclua esta linha
A4: 77888999000186 | B4: GRÁFICA EXEMPLO LTDA | C4: 41011 | D4: 1813-0/01 Impressão de material para uso publicitário | E4: 50000 | F4: Rua da Impressão, 20 | G4: Fornecedora da campanha de 2024 do vereador | H4: Gráfica Exemplo | I4: Ativa | J4: Cidade Exemplo/UF | K4: =IF(A4="","",COUNTIF(Contratos!$A:$A,A4)) -> 1 | L4: =IF(A4="","",SUMIFS(Contratos!$D:$D,Contratos!$A:$A,A4)+SUMIFS(Contratos!$N:$N,Contratos!$A:$A,A4)) -> 95000 | M4: =IF(A4="","",SUMIFS(Pagamentos!$C:$C,Pagamentos!$A:$A,A4,Pagamentos!$F:$F,"Empenho")) -> 0 | N4: =IF(A4="","",SUMIFS(Pagamentos!$C:$C,Pagamentos!$A:$A,A4,Pagamentos!$F:$F,"Pagamento")) -> 38000 | O4: =IF(OR(A4="",E4="",L4="",L4=0),"",E4/L4) -> 0.52631579 | P4: =IF(A4="","",COUNTIFS(Sancoes!$A:$A,A4,Sancoes!$B:$B,"<>Não consta")) -> 0 | Q4: =IF(A4="","",COUNTIF(Socios!$A:$A,A4)) -> 1 | R4: =IF(A4="","",COUNTIFS(Socios!$A:$A,A4,Socios!$K:$K,"SIM")) -> 0 | S4: L001 | T4: EXEMPLO — CNPJ fictício; exclua esta linha
K5: =IF(A5="","",COUNTIF(Contratos!$A:$A,A5)) | L5: =IF(A5="","",SUMIFS(Contratos!$D:$D,Contratos!$A:$A,A5)+SUMIFS(Contratos!$N:$N,Contratos!$A:$A,A5)) | M5: =IF(A5="","",SUMIFS(Pagamentos!$C:$C,Pagamentos!$A:$A,A5,Pagamentos!$F:$F,"Empenho")) | N5: =IF(A5="","",SUMIFS(Pagamentos!$C:$C,Pagamentos!$A:$A,A5,Pagamentos!$F:$F,"Pagamento")) | O5: =IF(OR(A5="",E5="",L5="",L5=0),"",E5/L5) | P5: =IF(A5="","",COUNTIFS(Sancoes!$A:$A,A5,Sancoes!$B:$B,"<>Não consta")) | Q5: =IF(A5="","",COUNTIF(Socios!$A:$A,A5)) | R5: =IF(A5="","",COUNTIFS(Socios!$A:$A,A5,Socios!$K:$K,"SIM"))
K6: =IF(A6="","",COUNTIF(Contratos!$A:$A,A6)) | L6: =IF(A6="","",SUMIFS(Contratos!$D:$D,Contratos!$A:$A,A6)+SUMIFS(Contratos!$N:$N,Contratos!$A:$A,A6)) | M6: =IF(A6="","",SUMIFS(Pagamentos!$C:$C,Pagamentos!$A:$A,A6,Pagamentos!$F:$F,"Empenho")) | N6: =IF(A6="","",SUMIFS(Pagamentos!$C:$C,Pagamentos!$A:$A,A6,Pagamentos!$F:$F,"Pagamento")) | O6: =IF(OR(A6="",E6="",L6="",L6=0),"",E6/L6) | P6: =IF(A6="","",COUNTIFS(Sancoes!$A:$A,A6,Sancoes!$B:$B,"<>Não consta")) | Q6: =IF(A6="","",COUNTIF(Socios!$A:$A,A6)) | R6: =IF(A6="","",COUNTIFS(Socios!$A:$A,A6,Socios!$K:$K,"SIM"))
K7: =IF(A7="","",COUNTIF(Contratos!$A:$A,A7)) | L7: =IF(A7="","",SUMIFS(Contratos!$D:$D,Contratos!$A:$A,A7)+SUMIFS(Contratos!$N:$N,Contratos!$A:$A,A7)) | M7: =IF(A7="","",SUMIFS(Pagamentos!$C:$C,Pagamentos!$A:$A,A7,Pagamentos!$F:$F,"Empenho")) | N7: =IF(A7="","",SUMIFS(Pagamentos!$C:$C,Pagamentos!$A:$A,A7,Pagamentos!$F:$F,"Pagamento")) | O7: =IF(OR(A7="",E7="",L7="",L7=0),"",E7/L7) | P7: =IF(A7="","",COUNTIFS(Sancoes!$A:$A,A7,Sancoes!$B:$B,"<>Não consta")) | Q7: =IF(A7="","",COUNTIF(Socios!$A:$A,A7)) | R7: =IF(A7="","",COUNTIFS(Socios!$A:$A,A7,Socios!$K:$K,"SIM"))
K8: =IF(A8="","",COUNTIF(Contratos!$A:$A,A8)) | L8: =IF(A8="","",SUMIFS(Contratos!$D:$D,Contratos!$A:$A,A8)+SUMIFS(Contratos!$N:$N,Contratos!$A:$A,A8)) | M8: =IF(A8="","",SUMIFS(Pagamentos!$C:$C,Pagamentos!$A:$A,A8,Pagamentos!$F:$F,"Empenho")) | N8: =IF(A8="","",SUMIFS(Pagamentos!$C:$C,Pagamentos!$A:$A,A8,Pagamentos!$F:$F,"Pagamento")) | O8: =IF(OR(A8="",E8="",L8="",L8=0),"",E8/L8) | P8: =IF(A8="","",COUNTIFS(Sancoes!$A:$A,A8,Sancoes!$B:$B,"<>Não consta")) | Q8: =IF(A8="","",COUNTIF(Socios!$A:$A,A8)) | R8: =IF(A8="","",COUNTIFS(Socios!$A:$A,A8,Socios!$K:$K,"SIM"))
K9: =IF(A9="","",COUNTIF(Contratos!$A:$A,A9)) | L9: =IF(A9="","",SUMIFS(Contratos!$D:$D,Contratos!$A:$A,A9)+SUMIFS(Contratos!$N:$N,Contratos!$A:$A,A9)) | M9: =IF(A9="","",SUMIFS(Pagamentos!$C:$C,Pagamentos!$A:$A,A9,Pagamentos!$F:$F,"Empenho")) | N9: =IF(A9="","",SUMIFS(Pagamentos!$C:$C,Pagamentos!$A:$A,A9,Pagamentos!$F:$F,"Pagamento")) | O9: =IF(OR(A9="",E9="",L9="",L9=0),"",E9/L9) | P9: =IF(A9="","",COUNTIFS(Sancoes!$A:$A,A9,Sancoes!$B:$B,"<>Não consta")) | Q9: =IF(A9="","",COUNTIF(Socios!$A:$A,A9)) | R9: =IF(A9="","",COUNTIFS(Socios!$A:$A,A9,Socios!$K:$K,"SIM"))
K10: =IF(A10="","",COUNTIF(Contratos!$A:$A,A10)) | L10: =IF(A10="","",SUMIFS(Contratos!$D:$D,Contratos!$A:$A,A10)+SUMIFS(Contratos!$N:$N,Contratos!$A:$A,A10)) | M10: =IF(A10="","",SUMIFS(Pagamentos!$C:$C,Pagamentos!$A:$A,A10,Pagamentos!$F:$F,"Empenho")) | N10: =IF(A10="","",SUMIFS(Pagamentos!$C:$C,Pagamentos!$A:$A,A10,Pagamentos!$F:$F,"Pagamento")) | O10: =IF(OR(A10="",E10="",L10="",L10=0),"",E10/L10) | P10: =IF(A10="","",COUNTIFS(Sancoes!$A:$A,A10,Sancoes!$B:$B,"<>Não consta")) | Q10: =IF(A10="","",COUNTIF(Socios!$A:$A,A10)) | R10: =IF(A10="","",COUNTIFS(Socios!$A:$A,A10,Socios!$K:$K,"SIM"))
K11: =IF(A11="","",COUNTIF(Contratos!$A:$A,A11)) | L11: =IF(A11="","",SUMIFS(Contratos!$D:$D,Contratos!$A:$A,A11)+SUMIFS(Contratos!$N:$N,Contratos!$A:$A,A11)) | M11: =IF(A11="","",SUMIFS(Pagamentos!$C:$C,Pagamentos!$A:$A,A11,Pagamentos!$F:$F,"Empenho")) | N11: =IF(A11="","",SUMIFS(Pagamentos!$C:$C,Pagamentos!$A:$A,A11,Pagamentos!$F:$F,"Pagamento")) | O11: =IF(OR(A11="",E11="",L11="",L11=0),"",E11/L11) | P11: =IF(A11="","",COUNTIFS(Sancoes!$A:$A,A11,Sancoes!$B:$B,"<>Não consta")) | Q11: =IF(A11="","",COUNTIF(Socios!$A:$A,A11)) | R11: =IF(A11="","",COUNTIFS(Socios!$A:$A,A11,Socios!$K:$K,"SIM"))
K12: =IF(A12="","",COUNTIF(Contratos!$A:$A,A12)) | L12: =IF(A12="","",SUMIFS(Contratos!$D:$D,Contratos!$A:$A,A12)+SUMIFS(Contratos!$N:$N,Contratos!$A:$A,A12)) | M12: =IF(A12="","",SUMIFS(Pagamentos!$C:$C,Pagamentos!$A:$A,A12,Pagamentos!$F:$F,"Empenho")) | N12: =IF(A12="","",SUMIFS(Pagamentos!$C:$C,Pagamentos!$A:$A,A12,Pagamentos!$F:$F,"Pagamento")) | O12: =IF(OR(A12="",E12="",L12="",L12=0),"",E12/L12) | P12: =IF(A12="","",COUNTIFS(Sancoes!$A:$A,A12,Sancoes!$B:$B,"<>Não consta")) | Q12: =IF(A12="","",COUNTIF(Socios!$A:$A,A12)) | R12: =IF(A12="","",COUNTIFS(Socios!$A:$A,A12,Socios!$K:$K,"SIM"))
K13: =IF(A13="","",COUNTIF(Contratos!$A:$A,A13)) | L13: =IF(A13="","",SUMIFS(Contratos!$D:$D,Contratos!$A:$A,A13)+SUMIFS(Contratos!$N:$N,Contratos!$A:$A,A13)) | M13: =IF(A13="","",SUMIFS(Pagamentos!$C:$C,Pagamentos!$A:$A,A13,Pagamentos!$F:$F,"Empenho")) | N13: =IF(A13="","",SUMIFS(Pagamentos!$C:$C,Pagamentos!$A:$A,A13,Pagamentos!$F:$F,"Pagamento")) | O13: =IF(OR(A13="",E13="",L13="",L13=0),"",E13/L13) | P13: =IF(A13="","",COUNTIFS(Sancoes!$A:$A,A13,Sancoes!$B:$B,"<>Não consta")) | Q13: =IF(A13="","",COUNTIF(Socios!$A:$A,A13)) | R13: =IF(A13="","",COUNTIFS(Socios!$A:$A,A13,Socios!$K:$K,"SIM"))
K14: =IF(A14="","",COUNTIF(Contratos!$A:$A,A14)) | L14: =IF(A14="","",SUMIFS(Contratos!$D:$D,Contratos!$A:$A,A14)+SUMIFS(Contratos!$N:$N,Contratos!$A:$A,A14)) | M14: =IF(A14="","",SUMIFS(Pagamentos!$C:$C,Pagamentos!$A:$A,A14,Pagamentos!$F:$F,"Empenho")) | N14: =IF(A14="","",SUMIFS(Pagamentos!$C:$C,Pagamentos!$A:$A,A14,Pagamentos!$F:$F,"Pagamento")) | O14: =IF(OR(A14="",E14="",L14="",L14=0),"",E14/L14) | P14: =IF(A14="","",COUNTIFS(Sancoes!$A:$A,A14,Sancoes!$B:$B,"<>Não consta")) | Q14: =IF(A14="","",COUNTIF(Socios!$A:$A,A14)) | R14: =IF(A14="","",COUNTIFS(Socios!$A:$A,A14,Socios!$K:$K,"SIM"))
K15: =IF(A15="","",COUNTIF(Contratos!$A:$A,A15)) | L15: =IF(A15="","",SUMIFS(Contratos!$D:$D,Contratos!$A:$A,A15)+SUMIFS(Contratos!$N:$N,Contratos!$A:$A,A15)) | M15: =IF(A15="","",SUMIFS(Pagamentos!$C:$C,Pagamentos!$A:$A,A15,Pagamentos!$F:$F,"Empenho")) | N15: =IF(A15="","",SUMIFS(Pagamentos!$C:$C,Pagamentos!$A:$A,A15,Pagamentos!$F:$F,"Pagamento")) | O15: =IF(OR(A15="",E15="",L15="",L15=0),"",E15/L15) | P15: =IF(A15="","",COUNTIFS(Sancoes!$A:$A,A15,Sancoes!$B:$B,"<>Não consta")) | Q15: =IF(A15="","",COUNTIF(Socios!$A:$A,A15)) | R15: =IF(A15="","",COUNTIFS(Socios!$A:$A,A15,Socios!$K:$K,"SIM"))
K16: =IF(A16="","",COUNTIF(Contratos!$A:$A,A16)) | L16: =IF(A16="","",SUMIFS(Contratos!$D:$D,Contratos!$A:$A,A16)+SUMIFS(Contratos!$N:$N,Contratos!$A:$A,A16)) | M16: =IF(A16="","",SUMIFS(Pagamentos!$C:$C,Pagamentos!$A:$A,A16,Pagamentos!$F:$F,"Empenho")) | N16: =IF(A16="","",SUMIFS(Pagamentos!$C:$C,Pagamentos!$A:$A,A16,Pagamentos!$F:$F,"Pagamento")) | O16: =IF(OR(A16="",E16="",L16="",L16=0),"",E16/L16) | P16: =IF(A16="","",COUNTIFS(Sancoes!$A:$A,A16,Sancoes!$B:$B,"<>Não consta")) | Q16: =IF(A16="","",COUNTIF(Socios!$A:$A,A16)) | R16: =IF(A16="","",COUNTIFS(Socios!$A:$A,A16,Socios!$K:$K,"SIM"))
... K501: =IF(A501="","",COUNTIF(Contratos!$A:$A,A501)) | L501: =IF(A501="","",SUMIFS(Contratos!$D:$D,Contratos!$A:$A,A501)+SUMIFS(Contratos!$N:$N,Contratos!$A:$A,A501)) | M501: =IF(A501="","",SUMIFS(Pagamentos!$C:$C,Pagamentos!$A:$A,A501,Pagamentos!$F:$F,"Empenho")) | N501: =IF(A501="","",SUMIFS(Pagamentos!$C:$C,Pagamentos!$A:$A,A501,Pagamentos!$F:$F,"Pagamento")) | O501: =IF(OR(A501="",E501="",L501="",L501=0),"",E501/L501) | P501: =IF(A501="","",COUNTIFS(Sancoes!$A:$A,A501,Sancoes!$B:$B,"<>Não consta")) | Q501: =IF(A501="","",COUNTIF(Socios!$A:$A,A501)) | R501: =IF(A501="","",COUNTIFS(Socios!$A:$A,A501,Socios!$K:$K,"SIM"))

Sheet Socios
A1: CNPJ | B1: Nome do sócio | C1: Dígitos visíveis do CPF | D1: Data de entrada | E1: Qualificação | F1: Saída da sociedade | G1: Empresa (auto) | H1: Nome normalizado (auto) | I1: CPF, 6 dígitos (auto) | J1: Chave (auto) | K1: Está em Pessoas? (auto) | L1: Fonte (ID do Log) | M1: Observações
A2: 11222333000186 | B2: Fulano de Tal | C2: ***123456** | D2: 45726 | E2: Sócio-administrador | G2: =IF(A2="","",IFERROR(INDEX(Empresas!$B:$B,MATCH(A2,Empresas!$A:$A,0))&"","cadastre o CNPJ em Empresas")) -> ALIMENTOS MODELO LTDA | H2: =IF(B2="","",SUBSTITUTE(SUBSTITUTE(SUBSTITUTE(SUBSTITUTE(SUBSTITUTE(SUBSTITUTE(SUBSTITUTE(SUBSTITUTE(SUBSTITUTE(SUBSTITUTE(SUBSTITUTE(SUBSTITUTE(SUBSTITUTE(UPPER(TRIM(B2)),"Á","A"),"À","A"),"Â","A"),"Ã","A"),"É","E"),"Ê","E"),"Í","I"),"Ó","O"),"Ô","O"),"Õ","O"),"Ú","U"),"Ü","U"),"Ç","C")) -> FULANO DE TAL | I2: =IF(C2="","",IF(LEN(SUBSTITUTE(SUBSTITUTE(SUBSTITUTE(SUBSTITUTE(TRIM(C2),"*",""),".",""),"-","")," ",""))=11,MID(SUBSTITUTE(SUBSTITUTE(SUBSTITUTE(SUBSTITUTE(TRIM(C2),"*",""),".",""),"-","")," ",""),4,6),SUBSTITUTE(SUBSTITUTE(SUBSTITUTE(SUBSTITUTE(TRIM(C2),"*",""),".",""),"-","")," ",""))) -> 123456 | J2: =IF(OR(H2="",I2=""),"",H2&"|"&I2) -> FULANO DE TAL|123456 | K2: =IF(H2="","",IF(AND(J2<>"",COUNTIF(Pessoas!$J:$J,J2)>0),"SIM",IF(COUNTIF(Pessoas!$H:$H,H2)>0,"nome igual em Pessoas: confira o CPF",""))) -> SIM | L2: L001 | M2: EXEMPLO — exclua esta linha
A3: 44555666000186 | B3: Maria Exemplo | C3: ***654321** | D3: 42156 | E3: Sócia-administradora | G3: =IF(A3="","",IFERROR(INDEX(Empresas!$B:$B,MATCH(A3,Empresas!$A:$A,0))&"","cadastre o CNPJ em Empresas")) -> CONSTRUTORA EXEMPLO LTDA | H3: =IF(B3="","",SUBSTITUTE(SUBSTITUTE(SUBSTITUTE(SUBSTITUTE(SUBSTITUTE(SUBSTITUTE(SUBSTITUTE(SUBSTITUTE(SUBSTITUTE(SUBSTITUTE(SUBSTITUTE(SUBSTITUTE(SUBSTITUTE(UPPER(TRIM(B3)),"Á","A"),"À","A"),"Â","A"),"Ã","A"),"É","E"),"Ê","E"),"Í","I"),"Ó","O"),"Ô","O"),"Õ","O"),"Ú","U"),"Ü","U"),"Ç","C")) -> MARIA EXEMPLO | I3: =IF(C3="","",IF(LEN(SUBSTITUTE(SUBSTITUTE(SUBSTITUTE(SUBSTITUTE(TRIM(C3),"*",""),".",""),"-","")," ",""))=11,MID(SUBSTITUTE(SUBSTITUTE(SUBSTITUTE(SUBSTITUTE(TRIM(C3),"*",""),".",""),"-","")," ",""),4,6),SUBSTITUTE(SUBSTITUTE(SUBSTITUTE(SUBSTITUTE(TRIM(C3),"*",""),".",""),"-","")," ",""))) -> 654321 | J3: =IF(OR(H3="",I3=""),"",H3&"|"&I3) -> MARIA EXEMPLO|654321 | K3: =IF(H3="","",IF(AND(J3<>"",COUNTIF(Pessoas!$J:$J,J3)>0),"SIM",IF(COUNTIF(Pessoas!$H:$H,H3)>0,"nome igual em Pessoas: confira o CPF",""))) | L3: L001 | M3: EXEMPLO — exclua esta linha
A4: 77888999000186 | B4: Beltrano Exemplo | C4: ***777888** | D4: 41011 | E4: Sócio-administrador | G4: =IF(A4="","",IFERROR(INDEX(Empresas!$B:$B,MATCH(A4,Empresas!$A:$A,0))&"","cadastre o CNPJ em Empresas")) -> GRÁFICA EXEMPLO LTDA | H4: =IF(B4="","",SUBSTITUTE(SUBSTITUTE(SUBSTITUTE(SUBSTITUTE(SUBSTITUTE(SUBSTITUTE(SUBSTITUTE(SUBSTITUTE(SUBSTITUTE(SUBSTITUTE(SUBSTITUTE(SUBSTITUTE(SUBSTITUTE(UPPER(TRIM(B4)),"Á","A"),"À","A"),"Â","A"),"Ã","A"),"É","E"),"Ê","E"),"Í","I"),"Ó","O"),"Ô","O"),"Õ","O"),"Ú","U"),"Ü","U"),"Ç","C")) -> BELTRANO EXEMPLO | I4: =IF(C4="","",IF(LEN(SUBSTITUTE(SUBSTITUTE(SUBSTITUTE(SUBSTITUTE(TRIM(C4),"*",""),".",""),"-","")," ",""))=11,MID(SUBSTITUTE(SUBSTITUTE(SUBSTITUTE(SUBSTITUTE(TRIM(C4),"*",""),".",""),"-","")," ",""),4,6),SUBSTITUTE(SUBSTITUTE(SUBSTITUTE(SUBSTITUTE(TRIM(C4),"*",""),".",""),"-","")," ",""))) -> 777888 | J4: =IF(OR(H4="",I4=""),"",H4&"|"&I4) -> BELTRANO EXEMPLO|777888 | K4: =IF(H4="","",IF(AND(J4<>"",COUNTIF(Pessoas!$J:$J,J4)>0),"SIM",IF(COUNTIF(Pessoas!$H:$H,H4)>0,"nome igual em Pessoas: confira o CPF",""))) | L4: L001 | M4: EXEMPLO — exclua esta linha
G5: =IF(A5="","",IFERROR(INDEX(Empresas!$B:$B,MATCH(A5,Empresas!$A:$A,0))&"","cadastre o CNPJ em Empresas")) | H5: =IF(B5="","",SUBSTITUTE(SUBSTITUTE(SUBSTITUTE(SUBSTITUTE(SUBSTITUTE(SUBSTITUTE(SUBSTITUTE(SUBSTITUTE(SUBSTITUTE(SUBSTITUTE(SUBSTITUTE(SUBSTITUTE(SUBSTITUTE(UPPER(TRIM(B5)),"Á","A"),"À","A"),"Â","A"),"Ã","A"),"É","E"),"Ê","E"),"Í","I"),"Ó","O"),"Ô","O"),"Õ","O"),"Ú","U"),"Ü","U"),"Ç","C")) | I5: =IF(C5="","",IF(LEN(SUBSTITUTE(SUBSTITUTE(SUBSTITUTE(SUBSTITUTE(TRIM(C5),"*",""),".",""),"-","")," ",""))=11,MID(SUBSTITUTE(SUBSTITUTE(SUBSTITUTE(SUBSTITUTE(TRIM(C5),"*",""),".",""),"-","")," ",""),4,6),SUBSTITUTE(SUBSTITUTE(SUBSTITUTE(SUBSTITUTE(TRIM(C5),"*",""),".",""),"-","")," ",""))) | J5: =IF(OR(H5="",I5=""),"",H5&"|"&I5) | K5: =IF(H5="","",IF(AND(J5<>"",COUNTIF(Pessoas!$J:$J,J5)>0),"SIM",IF(COUNTIF(Pessoas!$H:$H,H5)>0,"nome igual em Pessoas: confira o CPF","")))
G6: =IF(A6="","",IFERROR(INDEX(Empresas!$B:$B,MATCH(A6,Empresas!$A:$A,0))&"","cadastre o CNPJ em Empresas")) | H6: =IF(B6="","",SUBSTITUTE(SUBSTITUTE(SUBSTITUTE(SUBSTITUTE(SUBSTITUTE(SUBSTITUTE(SUBSTITUTE(SUBSTITUTE(SUBSTITUTE(SUBSTITUTE(SUBSTITUTE(SUBSTITUTE(SUBSTITUTE(UPPER(TRIM(B6)),"Á","A"),"À","A"),"Â","A"),"Ã","A"),"É","E"),"Ê","E"),"Í","I"),"Ó","O"),"Ô","O"),"Õ","O"),"Ú","U"),"Ü","U"),"Ç","C")) | I6: =IF(C6="","",IF(LEN(SUBSTITUTE(SUBSTITUTE(SUBSTITUTE(SUBSTITUTE(TRIM(C6),"*",""),".",""),"-","")," ",""))=11,MID(SUBSTITUTE(SUBSTITUTE(SUBSTITUTE(SUBSTITUTE(TRIM(C6),"*",""),".",""),"-","")," ",""),4,6),SUBSTITUTE(SUBSTITUTE(SUBSTITUTE(SUBSTITUTE(TRIM(C6),"*",""),".",""),"-","")," ",""))) | J6: =IF(OR(H6="",I6=""),"",H6&"|"&I6) | K6: =IF(H6="","",IF(AND(J6<>"",COUNTIF(Pessoas!$J:$J,J6)>0),"SIM",IF(COUNTIF(Pessoas!$H:$H,H6)>0,"nome igual em Pessoas: confira o CPF","")))
G7: =IF(A7="","",IFERROR(INDEX(Empresas!$B:$B,MATCH(A7,Empresas!$A:$A,0))&"","cadastre o CNPJ em Empresas")) | H7: =IF(B7="","",SUBSTITUTE(SUBSTITUTE(SUBSTITUTE(SUBSTITUTE(SUBSTITUTE(SUBSTITUTE(SUBSTITUTE(SUBSTITUTE(SUBSTITUTE(SUBSTITUTE(SUBSTITUTE(SUBSTITUTE(SUBSTITUTE(UPPER(TRIM(B7)),"Á","A"),"À","A"),"Â","A"),"Ã","A"),"É","E"),"Ê","E"),"Í","I"),"Ó","O"),"Ô","O"),"Õ","O"),"Ú","U"),"Ü","U"),"Ç","C")) | I7: =IF(C7="","",IF(LEN(SUBSTITUTE(SUBSTITUTE(SUBSTITUTE(SUBSTITUTE(TRIM(C7),"*",""),".",""),"-","")," ",""))=11,MID(SUBSTITUTE(SUBSTITUTE(SUBSTITUTE(SUBSTITUTE(TRIM(C7),"*",""),".",""),"-","")," ",""),4,6),SUBSTITUTE(SUBSTITUTE(SUBSTITUTE(SUBSTITUTE(TRIM(C7),"*",""),".",""),"-","")," ",""))) | J7: =IF(OR(H7="",I7=""),"",H7&"|"&I7) | K7: =IF(H7="","",IF(AND(J7<>"",COUNTIF(Pessoas!$J:$J,J7)>0),"SIM",IF(COUNTIF(Pessoas!$H:$H,H7)>0,"nome igual em Pessoas: confira o CPF","")))
G8: =IF(A8="","",IFERROR(INDEX(Empresas!$B:$B,MATCH(A8,Empresas!$A:$A,0))&"","cadastre o CNPJ em Empresas")) | H8: =IF(B8="","",SUBSTITUTE(SUBSTITUTE(SUBSTITUTE(SUBSTITUTE(SUBSTITUTE(SUBSTITUTE(SUBSTITUTE(SUBSTITUTE(SUBSTITUTE(SUBSTITUTE(SUBSTITUTE(SUBSTITUTE(SUBSTITUTE(UPPER(TRIM(B8)),"Á","A"),"À","A"),"Â","A"),"Ã","A"),"É","E"),"Ê","E"),"Í","I"),"Ó","O"),"Ô","O"),"Õ","O"),"Ú","U"),"Ü","U"),"Ç","C")) | I8: =IF(C8="","",IF(LEN(SUBSTITUTE(SUBSTITUTE(SUBSTITUTE(SUBSTITUTE(TRIM(C8),"*",""),".",""),"-","")," ",""))=11,MID(SUBSTITUTE(SUBSTITUTE(SUBSTITUTE(SUBSTITUTE(TRIM(C8),"*",""),".",""),"-","")," ",""),4,6),SUBSTITUTE(SUBSTITUTE(SUBSTITUTE(SUBSTITUTE(TRIM(C8),"*",""),".",""),"-","")," ",""))) | J8: =IF(OR(H8="",I8=""),"",H8&"|"&I8) | K8: =IF(H8="","",IF(AND(J8<>"",COUNTIF(Pessoas!$J:$J,J8)>0),"SIM",IF(COUNTIF(Pessoas!$H:$H,H8)>0,"nome igual em Pessoas: confira o CPF","")))
G9: =IF(A9="","",IFERROR(INDEX(Empresas!$B:$B,MATCH(A9,Empresas!$A:$A,0))&"","cadastre o CNPJ em Empresas")) | H9: =IF(B9="","",SUBSTITUTE(SUBSTITUTE(SUBSTITUTE(SUBSTITUTE(SUBSTITUTE(SUBSTITUTE(SUBSTITUTE(SUBSTITUTE(SUBSTITUTE(SUBSTITUTE(SUBSTITUTE(SUBSTITUTE(SUBSTITUTE(UPPER(TRIM(B9)),"Á","A"),"À","A"),"Â","A"),"Ã","A"),"É","E"),"Ê","E"),"Í","I"),"Ó","O"),"Ô","O"),"Õ","O"),"Ú","U"),"Ü","U"),"Ç","C")) | I9: =IF(C9="","",IF(LEN(SUBSTITUTE(SUBSTITUTE(SUBSTITUTE(SUBSTITUTE(TRIM(C9),"*",""),".",""),"-","")," ",""))=11,MID(SUBSTITUTE(SUBSTITUTE(SUBSTITUTE(SUBSTITUTE(TRIM(C9),"*",""),".",""),"-","")," ",""),4,6),SUBSTITUTE(SUBSTITUTE(SUBSTITUTE(SUBSTITUTE(TRIM(C9),"*",""),".",""),"-","")," ",""))) | J9: =IF(OR(H9="",I9=""),"",H9&"|"&I9) | K9: =IF(H9="","",IF(AND(J9<>"",COUNTIF(Pessoas!$J:$J,J9)>0),"SIM",IF(COUNTIF(Pessoas!$H:$H,H9)>0,"nome igual em Pessoas: confira o CPF","")))
G10: =IF(A10="","",IFERROR(INDEX(Empresas!$B:$B,MATCH(A10,Empresas!$A:$A,0))&"","cadastre o CNPJ em Empresas")) | H10: =IF(B10="","",SUBSTITUTE(SUBSTITUTE(SUBSTITUTE(SUBSTITUTE(SUBSTITUTE(SUBSTITUTE(SUBSTITUTE(SUBSTITUTE(SUBSTITUTE(SUBSTITUTE(SUBSTITUTE(SUBSTITUTE(SUBSTITUTE(UPPER(TRIM(B10)),"Á","A"),"À","A"),"Â","A"),"Ã","A"),"É","E"),"Ê","E"),"Í","I"),"Ó","O"),"Ô","O"),"Õ","O"),"Ú","U"),"Ü","U"),"Ç","C")) | I10: =IF(C10="","",IF(LEN(SUBSTITUTE(SUBSTITUTE(SUBSTITUTE(SUBSTITUTE(TRIM(C10),"*",""),".",""),"-","")," ",""))=11,MID(SUBSTITUTE(SUBSTITUTE(SUBSTITUTE(SUBSTITUTE(TRIM(C10),"*",""),".",""),"-","")," ",""),4,6),SUBSTITUTE(SUBSTITUTE(SUBSTITUTE(SUBSTITUTE(TRIM(C10),"*",""),".",""),"-","")," ",""))) | J10: =IF(OR(H10="",I10=""),"",H10&"|"&I10) | K10: =IF(H10="","",IF(AND(J10<>"",COUNTIF(Pessoas!$J:$J,J10)>0),"SIM",IF(COUNTIF(Pessoas!$H:$H,H10)>0,"nome igual em Pessoas: confira o CPF","")))
G11: =IF(A11="","",IFERROR(INDEX(Empresas!$B:$B,MATCH(A11,Empresas!$A:$A,0))&"","cadastre o CNPJ em Empresas")) | H11: =IF(B11="","",SUBSTITUTE(SUBSTITUTE(SUBSTITUTE(SUBSTITUTE(SUBSTITUTE(SUBSTITUTE(SUBSTITUTE(SUBSTITUTE(SUBSTITUTE(SUBSTITUTE(SUBSTITUTE(SUBSTITUTE(SUBSTITUTE(UPPER(TRIM(B11)),"Á","A"),"À","A"),"Â","A"),"Ã","A"),"É","E"),"Ê","E"),"Í","I"),"Ó","O"),"Ô","O"),"Õ","O"),"Ú","U"),"Ü","U"),"Ç","C")) | I11: =IF(C11="","",IF(LEN(SUBSTITUTE(SUBSTITUTE(SUBSTITUTE(SUBSTITUTE(TRIM(C11),"*",""),".",""),"-","")," ",""))=11,MID(SUBSTITUTE(SUBSTITUTE(SUBSTITUTE(SUBSTITUTE(TRIM(C11),"*",""),".",""),"-","")," ",""),4,6),SUBSTITUTE(SUBSTITUTE(SUBSTITUTE(SUBSTITUTE(TRIM(C11),"*",""),".",""),"-","")," ",""))) | J11: =IF(OR(H11="",I11=""),"",H11&"|"&I11) | K11: =IF(H11="","",IF(AND(J11<>"",COUNTIF(Pessoas!$J:$J,J11)>0),"SIM",IF(COUNTIF(Pessoas!$H:$H,H11)>0,"nome igual em Pessoas: confira o CPF","")))
G12: =IF(A12="","",IFERROR(INDEX(Empresas!$B:$B,MATCH(A12,Empresas!$A:$A,0))&"","cadastre o CNPJ em Empresas")) | H12: =IF(B12="","",SUBSTITUTE(SUBSTITUTE(SUBSTITUTE(SUBSTITUTE(SUBSTITUTE(SUBSTITUTE(SUBSTITUTE(SUBSTITUTE(SUBSTITUTE(SUBSTITUTE(SUBSTITUTE(SUBSTITUTE(SUBSTITUTE(UPPER(TRIM(B12)),"Á","A"),"À","A"),"Â","A"),"Ã","A"),"É","E"),"Ê","E"),"Í","I"),"Ó","O"),"Ô","O"),"Õ","O"),"Ú","U"),"Ü","U"),"Ç","C")) | I12: =IF(C12="","",IF(LEN(SUBSTITUTE(SUBSTITUTE(SUBSTITUTE(SUBSTITUTE(TRIM(C12),"*",""),".",""),"-","")," ",""))=11,MID(SUBSTITUTE(SUBSTITUTE(SUBSTITUTE(SUBSTITUTE(TRIM(C12),"*",""),".",""),"-","")," ",""),4,6),SUBSTITUTE(SUBSTITUTE(SUBSTITUTE(SUBSTITUTE(TRIM(C12),"*",""),".",""),"-","")," ",""))) | J12: =IF(OR(H12="",I12=""),"",H12&"|"&I12) | K12: =IF(H12="","",IF(AND(J12<>"",COUNTIF(Pessoas!$J:$J,J12)>0),"SIM",IF(COUNTIF(Pessoas!$H:$H,H12)>0,"nome igual em Pessoas: confira o CPF","")))
G13: =IF(A13="","",IFERROR(INDEX(Empresas!$B:$B,MATCH(A13,Empresas!$A:$A,0))&"","cadastre o CNPJ em Empresas")) | H13: =IF(B13="","",SUBSTITUTE(SUBSTITUTE(SUBSTITUTE(SUBSTITUTE(SUBSTITUTE(SUBSTITUTE(SUBSTITUTE(SUBSTITUTE(SUBSTITUTE(SUBSTITUTE(SUBSTITUTE(SUBSTITUTE(SUBSTITUTE(UPPER(TRIM(B13)),"Á","A"),"À","A"),"Â","A"),"Ã","A"),"É","E"),"Ê","E"),"Í","I"),"Ó","O"),"Ô","O"),"Õ","O"),"Ú","U"),"Ü","U"),"Ç","C")) | I13: =IF(C13="","",IF(LEN(SUBSTITUTE(SUBSTITUTE(SUBSTITUTE(SUBSTITUTE(TRIM(C13),"*",""),".",""),"-","")," ",""))=11,MID(SUBSTITUTE(SUBSTITUTE(SUBSTITUTE(SUBSTITUTE(TRIM(C13),"*",""),".",""),"-","")," ",""),4,6),SUBSTITUTE(SUBSTITUTE(SUBSTITUTE(SUBSTITUTE(TRIM(C13),"*",""),".",""),"-","")," ",""))) | J13: =IF(OR(H13="",I13=""),"",H13&"|"&I13) | K13: =IF(H13="","",IF(AND(J13<>"",COUNTIF(Pessoas!$J:$J,J13)>0),"SIM",IF(COUNTIF(Pessoas!$H:$H,H13)>0,"nome igual em Pessoas: confira o CPF","")))
G14: =IF(A14="","",IFERROR(INDEX(Empresas!$B:$B,MATCH(A14,Empresas!$A:$A,0))&"","cadastre o CNPJ em Empresas")) | H14: =IF(B14="","",SUBSTITUTE(SUBSTITUTE(SUBSTITUTE(SUBSTITUTE(SUBSTITUTE(SUBSTITUTE(SUBSTITUTE(SUBSTITUTE(SUBSTITUTE(SUBSTITUTE(SUBSTITUTE(SUBSTITUTE(SUBSTITUTE(UPPER(TRIM(B14)),"Á","A"),"À","A"),"Â","A"),"Ã","A"),"É","E"),"Ê","E"),"Í","I"),"Ó","O"),"Ô","O"),"Õ","O"),"Ú","U"),"Ü","U"),"Ç","C")) | I14: =IF(C14="","",IF(LEN(SUBSTITUTE(SUBSTITUTE(SUBSTITUTE(SUBSTITUTE(TRIM(C14),"*",""),".",""),"-","")," ",""))=11,MID(SUBSTITUTE(SUBSTITUTE(SUBSTITUTE(SUBSTITUTE(TRIM(C14),"*",""),".",""),"-","")," ",""),4,6),SUBSTITUTE(SUBSTITUTE(SUBSTITUTE(SUBSTITUTE(TRIM(C14),"*",""),".",""),"-","")," ",""))) | J14: =IF(OR(H14="",I14=""),"",H14&"|"&I14) | K14: =IF(H14="","",IF(AND(J14<>"",COUNTIF(Pessoas!$J:$J,J14)>0),"SIM",IF(COUNTIF(Pessoas!$H:$H,H14)>0,"nome igual em Pessoas: confira o CPF","")))
G15: =IF(A15="","",IFERROR(INDEX(Empresas!$B:$B,MATCH(A15,Empresas!$A:$A,0))&"","cadastre o CNPJ em Empresas")) | H15: =IF(B15="","",SUBSTITUTE(SUBSTITUTE(SUBSTITUTE(SUBSTITUTE(SUBSTITUTE(SUBSTITUTE(SUBSTITUTE(SUBSTITUTE(SUBSTITUTE(SUBSTITUTE(SUBSTITUTE(SUBSTITUTE(SUBSTITUTE(UPPER(TRIM(B15)),"Á","A"),"À","A"),"Â","A"),"Ã","A"),"É","E"),"Ê","E"),"Í","I"),"Ó","O"),"Ô","O"),"Õ","O"),"Ú","U"),"Ü","U"),"Ç","C")) | I15: =IF(C15="","",IF(LEN(SUBSTITUTE(SUBSTITUTE(SUBSTITUTE(SUBSTITUTE(TRIM(C15),"*",""),".",""),"-","")," ",""))=11,MID(SUBSTITUTE(SUBSTITUTE(SUBSTITUTE(SUBSTITUTE(TRIM(C15),"*",""),".",""),"-","")," ",""),4,6),SUBSTITUTE(SUBSTITUTE(SUBSTITUTE(SUBSTITUTE(TRIM(C15),"*",""),".",""),"-","")," ",""))) | J15: =IF(OR(H15="",I15=""),"",H15&"|"&I15) | K15: =IF(H15="","",IF(AND(J15<>"",COUNTIF(Pessoas!$J:$J,J15)>0),"SIM",IF(COUNTIF(Pessoas!$H:$H,H15)>0,"nome igual em Pessoas: confira o CPF","")))
G16: =IF(A16="","",IFERROR(INDEX(Empresas!$B:$B,MATCH(A16,Empresas!$A:$A,0))&"","cadastre o CNPJ em Empresas")) | H16: =IF(B16="","",SUBSTITUTE(SUBSTITUTE(SUBSTITUTE(SUBSTITUTE(SUBSTITUTE(SUBSTITUTE(SUBSTITUTE(SUBSTITUTE(SUBSTITUTE(SUBSTITUTE(SUBSTITUTE(SUBSTITUTE(SUBSTITUTE(UPPER(TRIM(B16)),"Á","A"),"À","A"),"Â","A"),"Ã","A"),"É","E"),"Ê","E"),"Í","I"),"Ó","O"),"Ô","O"),"Õ","O"),"Ú","U"),"Ü","U"),"Ç","C")) | I16: =IF(C16="","",IF(LEN(SUBSTITUTE(SUBSTITUTE(SUBSTITUTE(SUBSTITUTE(TRIM(C16),"*",""),".",""),"-","")," ",""))=11,MID(SUBSTITUTE(SUBSTITUTE(SUBSTITUTE(SUBSTITUTE(TRIM(C16),"*",""),".",""),"-","")," ",""),4,6),SUBSTITUTE(SUBSTITUTE(SUBSTITUTE(SUBSTITUTE(TRIM(C16),"*",""),".",""),"-","")," ",""))) | J16: =IF(OR(H16="",I16=""),"",H16&"|"&I16) | K16: =IF(H16="","",IF(AND(J16<>"",COUNTIF(Pessoas!$J:$J,J16)>0),"SIM",IF(COUNTIF(Pessoas!$H:$H,H16)>0,"nome igual em Pessoas: confira o CPF","")))
... G1001: =IF(A1001="","",IFERROR(INDEX(Empresas!$B:$B,MATCH(A1001,Empresas!$A:$A,0))&"","cadastre o CNPJ em Empresas")) | H1001: =IF(B1001="","",SUBSTITUTE(SUBSTITUTE(SUBSTITUTE(SUBSTITUTE(SUBSTITUTE(SUBSTITUTE(SUBSTITUTE(SUBSTITUTE(SUBSTITUTE(SUBSTITUTE(SUBSTITUTE(SUBSTITUTE(SUBSTITUTE(UPPER(TRIM(B1001)),"Á","A"),"À","A"),"Â","A"),"Ã","A"),"É","E"),"Ê","E"),"Í","I"),"Ó","O"),"Ô","O"),"Õ","O"),"Ú","U"),"Ü","U"),"Ç","C")) | I1001: =IF(C1001="","",IF(LEN(SUBSTITUTE(SUBSTITUTE(SUBSTITUTE(SUBSTITUTE(TRIM(C1001),"*",""),".",""),"-","")," ",""))=11,MID(SUBSTITUTE(SUBSTITUTE(SUBSTITUTE(SUBSTITUTE(TRIM(C1001),"*",""),".",""),"-","")," ",""),4,6),SUBSTITUTE(SUBSTITUTE(SUBSTITUTE(SUBSTITUTE(TRIM(C1001),"*",""),".",""),"-","")," ",""))) | J1001: =IF(OR(H1001="",I1001=""),"",H1001&"|"&I1001) | K1001: =IF(H1001="","",IF(AND(J1001<>"",COUNTIF(Pessoas!$J:$J,J1001)>0),"SIM",IF(COUNTIF(Pessoas!$H:$H,H1001)>0,"nome igual em Pessoas: confira o CPF","")))

Sheet Pessoas
A1: Nome | B1: CPF (dígitos visíveis) | C1: Cargo ou função | D1: Órgão | E1: Nomeação ou posse | F1: Partido | G1: Vínculo com a pauta | H1: Nome normalizado (auto) | I1: CPF, 6 dígitos (auto) | J1: Chave (auto) | K1: Sócio de empresas (auto) | L1: Fonte (ID do Log) | M1: Observações
A2: Fulano de Tal | B2: ***123456** | C2: Assessor parlamentar | D2: Câmara Municipal de Cidade Exemplo | E2: 45672 | G2: Nomeado para o gabinete do vereador Sicrano Candidato; doou R$ 20 mil à campanha dele em 2024 | H2: =IF(A2="","",SUBSTITUTE(SUBSTITUTE(SUBSTITUTE(SUBSTITUTE(SUBSTITUTE(SUBSTITUTE(SUBSTITUTE(SUBSTITUTE(SUBSTITUTE(SUBSTITUTE(SUBSTITUTE(SUBSTITUTE(SUBSTITUTE(UPPER(TRIM(A2)),"Á","A"),"À","A"),"Â","A"),"Ã","A"),"É","E"),"Ê","E"),"Í","I"),"Ó","O"),"Ô","O"),"Õ","O"),"Ú","U"),"Ü","U"),"Ç","C")) -> FULANO DE TAL | I2: =IF(B2="","",IF(LEN(SUBSTITUTE(SUBSTITUTE(SUBSTITUTE(SUBSTITUTE(TRIM(B2),"*",""),".",""),"-","")," ",""))=11,MID(SUBSTITUTE(SUBSTITUTE(SUBSTITUTE(SUBSTITUTE(TRIM(B2),"*",""),".",""),"-","")," ",""),4,6),SUBSTITUTE(SUBSTITUTE(SUBSTITUTE(SUBSTITUTE(TRIM(B2),"*",""),".",""),"-","")," ",""))) -> 123456 | J2: =IF(OR(H2="",I2=""),"",H2&"|"&I2) -> FULANO DE TAL|123456 | K2: =IF(H2="","",IF(J2<>"",COUNTIF(Socios!$J:$J,J2),IF(COUNTIF(Socios!$H:$H,H2)>0,"nome igual em Socios: confira o CPF","sem CPF: não cruzado"))) -> 1 | L2: L002 | M2: EXEMPLO — exclua esta linha
A3: Sicrano Candidato | C3: Vereador | D3: Câmara Municipal de Cidade Exemplo | E3: 45658 | F3: Partido Exemplo | G3: Vereador; candidato a deputado estadual em 2026 | H3: =IF(A3="","",SUBSTITUTE(SUBSTITUTE(SUBSTITUTE(SUBSTITUTE(SUBSTITUTE(SUBSTITUTE(SUBSTITUTE(SUBSTITUTE(SUBSTITUTE(SUBSTITUTE(SUBSTITUTE(SUBSTITUTE(SUBSTITUTE(UPPER(TRIM(A3)),"Á","A"),"À","A"),"Â","A"),"Ã","A"),"É","E"),"Ê","E"),"Í","I"),"Ó","O"),"Ô","O"),"Õ","O"),"Ú","U"),"Ü","U"),"Ç","C")) -> SICRANO CANDIDATO | I3: =IF(B3="","",IF(LEN(SUBSTITUTE(SUBSTITUTE(SUBSTITUTE(SUBSTITUTE(TRIM(B3),"*",""),".",""),"-","")," ",""))=11,MID(SUBSTITUTE(SUBSTITUTE(SUBSTITUTE(SUBSTITUTE(TRIM(B3),"*",""),".",""),"-","")," ",""),4,6),SUBSTITUTE(SUBSTITUTE(SUBSTITUTE(SUBSTITUTE(TRIM(B3),"*",""),".",""),"-","")," ",""))) | J3: =IF(OR(H3="",I3=""),"",H3&"|"&I3) | K3: =IF(H3="","",IF(J3<>"",COUNTIF(Socios!$J:$J,J3),IF(COUNTIF(Socios!$H:$H,H3)>0,"nome igual em Socios: confira o CPF","sem CPF: não cruzado"))) -> sem CPF: não cruzado | L3: L006 | M3: EXEMPLO — sem CPF, não é cruzado
H4: =IF(A4="","",SUBSTITUTE(SUBSTITUTE(SUBSTITUTE(SUBSTITUTE(SUBSTITUTE(SUBSTITUTE(SUBSTITUTE(SUBSTITUTE(SUBSTITUTE(SUBSTITUTE(SUBSTITUTE(SUBSTITUTE(SUBSTITUTE(UPPER(TRIM(A4)),"Á","A"),"À","A"),"Â","A"),"Ã","A"),"É","E"),"Ê","E"),"Í","I"),"Ó","O"),"Ô","O"),"Õ","O"),"Ú","U"),"Ü","U"),"Ç","C")) | I4: =IF(B4="","",IF(LEN(SUBSTITUTE(SUBSTITUTE(SUBSTITUTE(SUBSTITUTE(TRIM(B4),"*",""),".",""),"-","")," ",""))=11,MID(SUBSTITUTE(SUBSTITUTE(SUBSTITUTE(SUBSTITUTE(TRIM(B4),"*",""),".",""),"-","")," ",""),4,6),SUBSTITUTE(SUBSTITUTE(SUBSTITUTE(SUBSTITUTE(TRIM(B4),"*",""),".",""),"-","")," ",""))) | J4: =IF(OR(H4="",I4=""),"",H4&"|"&I4) | K4: =IF(H4="","",IF(J4<>"",COUNTIF(Socios!$J:$J,J4),IF(COUNTIF(Socios!$H:$H,H4)>0,"nome igual em Socios: confira o CPF","sem CPF: não cruzado")))
H5: =IF(A5="","",SUBSTITUTE(SUBSTITUTE(SUBSTITUTE(SUBSTITUTE(SUBSTITUTE(SUBSTITUTE(SUBSTITUTE(SUBSTITUTE(SUBSTITUTE(SUBSTITUTE(SUBSTITUTE(SUBSTITUTE(SUBSTITUTE(UPPER(TRIM(A5)),"Á","A"),"À","A"),"Â","A"),"Ã","A"),"É","E"),"Ê","E"),"Í","I"),"Ó","O"),"Ô","O"),"Õ","O"),"Ú","U"),"Ü","U"),"Ç","C")) | I5: =IF(B5="","",IF(LEN(SUBSTITUTE(SUBSTITUTE(SUBSTITUTE(SUBSTITUTE(TRIM(B5),"*",""),".",""),"-","")," ",""))=11,MID(SUBSTITUTE(SUBSTITUTE(SUBSTITUTE(SUBSTITUTE(TRIM(B5),"*",""),".",""),"-","")," ",""),4,6),SUBSTITUTE(SUBSTITUTE(SUBSTITUTE(SUBSTITUTE(TRIM(B5),"*",""),".",""),"-","")," ",""))) | J5: =IF(OR(H5="",I5=""),"",H5&"|"&I5) | K5: =IF(H5="","",IF(J5<>"",COUNTIF(Socios!$J:$J,J5),IF(COUNTIF(Socios!$H:$H,H5)>0,"nome igual em Socios: confira o CPF","sem CPF: não cruzado")))
H6: =IF(A6="","",SUBSTITUTE(SUBSTITUTE(SUBSTITUTE(SUBSTITUTE(SUBSTITUTE(SUBSTITUTE(SUBSTITUTE(SUBSTITUTE(SUBSTITUTE(SUBSTITUTE(SUBSTITUTE(SUBSTITUTE(SUBSTITUTE(UPPER(TRIM(A6)),"Á","A"),"À","A"),"Â","A"),"Ã","A"),"É","E"),"Ê","E"),"Í","I"),"Ó","O"),"Ô","O"),"Õ","O"),"Ú","U"),"Ü","U"),"Ç","C")) | I6: =IF(B6="","",IF(LEN(SUBSTITUTE(SUBSTITUTE(SUBSTITUTE(SUBSTITUTE(TRIM(B6),"*",""),".",""),"-","")," ",""))=11,MID(SUBSTITUTE(SUBSTITUTE(SUBSTITUTE(SUBSTITUTE(TRIM(B6),"*",""),".",""),"-","")," ",""),4,6),SUBSTITUTE(SUBSTITUTE(SUBSTITUTE(SUBSTITUTE(TRIM(B6),"*",""),".",""),"-","")," ",""))) | J6: =IF(OR(H6="",I6=""),"",H6&"|"&I6) | K6: =IF(H6="","",IF(J6<>"",COUNTIF(Socios!$J:$J,J6),IF(COUNTIF(Socios!$H:$H,H6)>0,"nome igual em Socios: confira o CPF","sem CPF: não cruzado")))
H7: =IF(A7="","",SUBSTITUTE(SUBSTITUTE(SUBSTITUTE(SUBSTITUTE(SUBSTITUTE(SUBSTITUTE(SUBSTITUTE(SUBSTITUTE(SUBSTITUTE(SUBSTITUTE(SUBSTITUTE(SUBSTITUTE(SUBSTITUTE(UPPER(TRIM(A7)),"Á","A"),"À","A"),"Â","A"),"Ã","A"),"É","E"),"Ê","E"),"Í","I"),"Ó","O"),"Ô","O"),"Õ","O"),"Ú","U"),"Ü","U"),"Ç","C")) | I7: =IF(B7="","",IF(LEN(SUBSTITUTE(SUBSTITUTE(SUBSTITUTE(SUBSTITUTE(TRIM(B7),"*",""),".",""),"-","")," ",""))=11,MID(SUBSTITUTE(SUBSTITUTE(SUBSTITUTE(SUBSTITUTE(TRIM(B7),"*",""),".",""),"-","")," ",""),4,6),SUBSTITUTE(SUBSTITUTE(SUBSTITUTE(SUBSTITUTE(TRIM(B7),"*",""),".",""),"-","")," ",""))) | J7: =IF(OR(H7="",I7=""),"",H7&"|"&I7) | K7: =IF(H7="","",IF(J7<>"",COUNTIF(Socios!$J:$J,J7),IF(COUNTIF(Socios!$H:$H,H7)>0,"nome igual em Socios: confira o CPF","sem CPF: não cruzado")))
H8: =IF(A8="","",SUBSTITUTE(SUBSTITUTE(SUBSTITUTE(SUBSTITUTE(SUBSTITUTE(SUBSTITUTE(SUBSTITUTE(SUBSTITUTE(SUBSTITUTE(SUBSTITUTE(SUBSTITUTE(SUBSTITUTE(SUBSTITUTE(UPPER(TRIM(A8)),"Á","A"),"À","A"),"Â","A"),"Ã","A"),"É","E"),"Ê","E"),"Í","I"),"Ó","O"),"Ô","O"),"Õ","O"),"Ú","U"),"Ü","U"),"Ç","C")) | I8: =IF(B8="","",IF(LEN(SUBSTITUTE(SUBSTITUTE(SUBSTITUTE(SUBSTITUTE(TRIM(B8),"*",""),".",""),"-","")," ",""))=11,MID(SUBSTITUTE(SUBSTITUTE(SUBSTITUTE(SUBSTITUTE(TRIM(B8),"*",""),".",""),"-","")," ",""),4,6),SUBSTITUTE(SUBSTITUTE(SUBSTITUTE(SUBSTITUTE(TRIM(B8),"*",""),".",""),"-","")," ",""))) | J8: =IF(OR(H8="",I8=""),"",H8&"|"&I8) | K8: =IF(H8="","",IF(J8<>"",COUNTIF(Socios!$J:$J,J8),IF(COUNTIF(Socios!$H:$H,H8)>0,"nome igual em Socios: confira o CPF","sem CPF: não cruzado")))
H9: =IF(A9="","",SUBSTITUTE(SUBSTITUTE(SUBSTITUTE(SUBSTITUTE(SUBSTITUTE(SUBSTITUTE(SUBSTITUTE(SUBSTITUTE(SUBSTITUTE(SUBSTITUTE(SUBSTITUTE(SUBSTITUTE(SUBSTITUTE(UPPER(TRIM(A9)),"Á","A"),"À","A"),"Â","A"),"Ã","A"),"É","E"),"Ê","E"),"Í","I"),"Ó","O"),"Ô","O"),"Õ","O"),"Ú","U"),"Ü","U"),"Ç","C")) | I9: =IF(B9="","",IF(LEN(SUBSTITUTE(SUBSTITUTE(SUBSTITUTE(SUBSTITUTE(TRIM(B9),"*",""),".",""),"-","")," ",""))=11,MID(SUBSTITUTE(SUBSTITUTE(SUBSTITUTE(SUBSTITUTE(TRIM(B9),"*",""),".",""),"-","")," ",""),4,6),SUBSTITUTE(SUBSTITUTE(SUBSTITUTE(SUBSTITUTE(TRIM(B9),"*",""),".",""),"-","")," ",""))) | J9: =IF(OR(H9="",I9=""),"",H9&"|"&I9) | K9: =IF(H9="","",IF(J9<>"",COUNTIF(Socios!$J:$J,J9),IF(COUNTIF(Socios!$H:$H,H9)>0,"nome igual em Socios: confira o CPF","sem CPF: não cruzado")))
H10: =IF(A10="","",SUBSTITUTE(SUBSTITUTE(SUBSTITUTE(SUBSTITUTE(SUBSTITUTE(SUBSTITUTE(SUBSTITUTE(SUBSTITUTE(SUBSTITUTE(SUBSTITUTE(SUBSTITUTE(SUBSTITUTE(SUBSTITUTE(UPPER(TRIM(A10)),"Á","A"),"À","A"),"Â","A"),"Ã","A"),"É","E"),"Ê","E"),"Í","I"),"Ó","O"),"Ô","O"),"Õ","O"),"Ú","U"),"Ü","U"),"Ç","C")) | I10: =IF(B10="","",IF(LEN(SUBSTITUTE(SUBSTITUTE(SUBSTITUTE(SUBSTITUTE(TRIM(B10),"*",""),".",""),"-","")," ",""))=11,MID(SUBSTITUTE(SUBSTITUTE(SUBSTITUTE(SUBSTITUTE(TRIM(B10),"*",""),".",""),"-","")," ",""),4,6),SUBSTITUTE(SUBSTITUTE(SUBSTITUTE(SUBSTITUTE(TRIM(B10),"*",""),".",""),"-","")," ",""))) | J10: =IF(OR(H10="",I10=""),"",H10&"|"&I10) | K10: =IF(H10="","",IF(J10<>"",COUNTIF(Socios!$J:$J,J10),IF(COUNTIF(Socios!$H:$H,H10)>0,"nome igual em Socios: confira o CPF","sem CPF: não cruzado")))
H11: =IF(A11="","",SUBSTITUTE(SUBSTITUTE(SUBSTITUTE(SUBSTITUTE(SUBSTITUTE(SUBSTITUTE(SUBSTITUTE(SUBSTITUTE(SUBSTITUTE(SUBSTITUTE(SUBSTITUTE(SUBSTITUTE(SUBSTITUTE(UPPER(TRIM(A11)),"Á","A"),"À","A"),"Â","A"),"Ã","A"),"É","E"),"Ê","E"),"Í","I"),"Ó","O"),"Ô","O"),"Õ","O"),"Ú","U"),"Ü","U"),"Ç","C")) | I11: =IF(B11="","",IF(LEN(SUBSTITUTE(SUBSTITUTE(SUBSTITUTE(SUBSTITUTE(TRIM(B11),"*",""),".",""),"-","")," ",""))=11,MID(SUBSTITUTE(SUBSTITUTE(SUBSTITUTE(SUBSTITUTE(TRIM(B11),"*",""),".",""),"-","")," ",""),4,6),SUBSTITUTE(SUBSTITUTE(SUBSTITUTE(SUBSTITUTE(TRIM(B11),"*",""),".",""),"-","")," ",""))) | J11: =IF(OR(H11="",I11=""),"",H11&"|"&I11) | K11: =IF(H11="","",IF(J11<>"",COUNTIF(Socios!$J:$J,J11),IF(COUNTIF(Socios!$H:$H,H11)>0,"nome igual em Socios: confira o CPF","sem CPF: não cruzado")))
H12: =IF(A12="","",SUBSTITUTE(SUBSTITUTE(SUBSTITUTE(SUBSTITUTE(SUBSTITUTE(SUBSTITUTE(SUBSTITUTE(SUBSTITUTE(SUBSTITUTE(SUBSTITUTE(SUBSTITUTE(SUBSTITUTE(SUBSTITUTE(UPPER(TRIM(A12)),"Á","A"),"À","A"),"Â","A"),"Ã","A"),"É","E"),"Ê","E"),"Í","I"),"Ó","O"),"Ô","O"),"Õ","O"),"Ú","U"),"Ü","U"),"Ç","C")) | I12: =IF(B12="","",IF(LEN(SUBSTITUTE(SUBSTITUTE(SUBSTITUTE(SUBSTITUTE(TRIM(B12),"*",""),".",""),"-","")," ",""))=11,MID(SUBSTITUTE(SUBSTITUTE(SUBSTITUTE(SUBSTITUTE(TRIM(B12),"*",""),".",""),"-","")," ",""),4,6),SUBSTITUTE(SUBSTITUTE(SUBSTITUTE(SUBSTITUTE(TRIM(B12),"*",""),".",""),"-","")," ",""))) | J12: =IF(OR(H12="",I12=""),"",H12&"|"&I12) | K12: =IF(H12="","",IF(J12<>"",COUNTIF(Socios!$J:$J,J12),IF(COUNTIF(Socios!$H:$H,H12)>0,"nome igual em Socios: confira o CPF","sem CPF: não cruzado")))
H13: =IF(A13="","",SUBSTITUTE(SUBSTITUTE(SUBSTITUTE(SUBSTITUTE(SUBSTITUTE(SUBSTITUTE(SUBSTITUTE(SUBSTITUTE(SUBSTITUTE(SUBSTITUTE(SUBSTITUTE(SUBSTITUTE(SUBSTITUTE(UPPER(TRIM(A13)),"Á","A"),"À","A"),"Â","A"),"Ã","A"),"É","E"),"Ê","E"),"Í","I"),"Ó","O"),"Ô","O"),"Õ","O"),"Ú","U"),"Ü","U"),"Ç","C")) | I13: =IF(B13="","",IF(LEN(SUBSTITUTE(SUBSTITUTE(SUBSTITUTE(SUBSTITUTE(TRIM(B13),"*",""),".",""),"-","")," ",""))=11,MID(SUBSTITUTE(SUBSTITUTE(SUBSTITUTE(SUBSTITUTE(TRIM(B13),"*",""),".",""),"-","")," ",""),4,6),SUBSTITUTE(SUBSTITUTE(SUBSTITUTE(SUBSTITUTE(TRIM(B13),"*",""),".",""),"-","")," ",""))) | J13: =IF(OR(H13="",I13=""),"",H13&"|"&I13) | K13: =IF(H13="","",IF(J13<>"",COUNTIF(Socios!$J:$J,J13),IF(COUNTIF(Socios!$H:$H,H13)>0,"nome igual em Socios: confira o CPF","sem CPF: não cruzado")))
H14: =IF(A14="","",SUBSTITUTE(SUBSTITUTE(SUBSTITUTE(SUBSTITUTE(SUBSTITUTE(SUBSTITUTE(SUBSTITUTE(SUBSTITUTE(SUBSTITUTE(SUBSTITUTE(SUBSTITUTE(SUBSTITUTE(SUBSTITUTE(UPPER(TRIM(A14)),"Á","A"),"À","A"),"Â","A"),"Ã","A"),"É","E"),"Ê","E"),"Í","I"),"Ó","O"),"Ô","O"),"Õ","O"),"Ú","U"),"Ü","U"),"Ç","C")) | I14: =IF(B14="","",IF(LEN(SUBSTITUTE(SUBSTITUTE(SUBSTITUTE(SUBSTITUTE(TRIM(B14),"*",""),".",""),"-","")," ",""))=11,MID(SUBSTITUTE(SUBSTITUTE(SUBSTITUTE(SUBSTITUTE(TRIM(B14),"*",""),".",""),"-","")," ",""),4,6),SUBSTITUTE(SUBSTITUTE(SUBSTITUTE(SUBSTITUTE(TRIM(B14),"*",""),".",""),"-","")," ",""))) | J14: =IF(OR(H14="",I14=""),"",H14&"|"&I14) | K14: =IF(H14="","",IF(J14<>"",COUNTIF(Socios!$J:$J,J14),IF(COUNTIF(Socios!$H:$H,H14)>0,"nome igual em Socios: confira o CPF","sem CPF: não cruzado")))
H15: =IF(A15="","",SUBSTITUTE(SUBSTITUTE(SUBSTITUTE(SUBSTITUTE(SUBSTITUTE(SUBSTITUTE(SUBSTITUTE(SUBSTITUTE(SUBSTITUTE(SUBSTITUTE(SUBSTITUTE(SUBSTITUTE(SUBSTITUTE(UPPER(TRIM(A15)),"Á","A"),"À","A"),"Â","A"),"Ã","A"),"É","E"),"Ê","E"),"Í","I"),"Ó","O"),"Ô","O"),"Õ","O"),"Ú","U"),"Ü","U"),"Ç","C")) | I15: =IF(B15="","",IF(LEN(SUBSTITUTE(SUBSTITUTE(SUBSTITUTE(SUBSTITUTE(TRIM(B15),"*",""),".",""),"-","")," ",""))=11,MID(SUBSTITUTE(SUBSTITUTE(SUBSTITUTE(SUBSTITUTE(TRIM(B15),"*",""),".",""),"-","")," ",""),4,6),SUBSTITUTE(SUBSTITUTE(SUBSTITUTE(SUBSTITUTE(TRIM(B15),"*",""),".",""),"-","")," ",""))) | J15: =IF(OR(H15="",I15=""),"",H15&"|"&I15) | K15: =IF(H15="","",IF(J15<>"",COUNTIF(Socios!$J:$J,J15),IF(COUNTIF(Socios!$H:$H,H15)>0,"nome igual em Socios: confira o CPF","sem CPF: não cruzado")))
... H301: =IF(A301="","",SUBSTITUTE(SUBSTITUTE(SUBSTITUTE(SUBSTITUTE(SUBSTITUTE(SUBSTITUTE(SUBSTITUTE(SUBSTITUTE(SUBSTITUTE(SUBSTITUTE(SUBSTITUTE(SUBSTITUTE(SUBSTITUTE(UPPER(TRIM(A301)),"Á","A"),"À","A"),"Â","A"),"Ã","A"),"É","E"),"Ê","E"),"Í","I"),"Ó","O"),"Ô","O"),"Õ","O"),"Ú","U"),"Ü","U"),"Ç","C")) | I301: =IF(B301="","",IF(LEN(SUBSTITUTE(SUBSTITUTE(SUBSTITUTE(SUBSTITUTE(TRIM(B301),"*",""),".",""),"-","")," ",""))=11,MID(SUBSTITUTE(SUBSTITUTE(SUBSTITUTE(SUBSTITUTE(TRIM(B301),"*",""),".",""),"-","")," ",""),4,6),SUBSTITUTE(SUBSTITUTE(SUBSTITUTE(SUBSTITUTE(TRIM(B301),"*",""),".",""),"-","")," ",""))) | J301: =IF(OR(H301="",I301=""),"",H301&"|"&I301) | K301: =IF(H301="","",IF(J301<>"",COUNTIF(Socios!$J:$J,J301),IF(COUNTIF(Socios!$H:$H,H301)>0,"nome igual em Socios: confira o CPF","sem CPF: não cruzado")))

Sheet Eleitoral
A1: CNPJ do fornecedor de campanha | B1: Candidato e eleição | C1: Valor (R$) | D1: Fornecedor | E1: O que forneceu | F1: Virou fornecedor do poder público? (auto) | G1: Fonte (ID do Log) | H1: Observações | J1: Bens: candidato | K1: Eleição (ano) | L1: Cargo disputado | M1: Bem declarado | N1: Valor declarado (R$) | O1: Fonte (ID do Log) | P1: Total nesta eleição (auto) | Q1: Eleição anterior (auto) | R1: Total na eleição anterior (auto) | S1: Variação (auto)
A2: 77888999000186 | B2: Sicrano Candidato — vereador, 2024 | C2: 15000 | D2: GRÁFICA EXEMPLO LTDA | E2: Santinhos e adesivos | F2: =IF(A2="","",IF(COUNTIF(Contratos!$A:$A,A2)+COUNTIF(Pagamentos!$A:$A,A2)=0,"não consta","SIM — contratos: "&COUNTIF(Contratos!$A:$A,A2)&"; pagamentos: "&COUNTIF(Pagamentos!$A:$A,A2))) -> SIM — contratos: 1; pagamentos: 1 | G2: L006 | H2: EXEMPLO — exclua esta linha | J2: Sicrano Candidato | K2: 2024 | L2: Vereador | M2: Casa em Cidade Exemplo | N2: 350000 | O2: L006 | P2: =IF(OR(J2="",K2=""),"",SUMIFS($N:$N,$J:$J,J2,$K:$K,K2)) -> 350000 | Q2: =IF(OR(J2="",K2=""),"",IF(COUNTIFS($J:$J,J2,$K:$K,"<"&K2)=0,"",_xlfn.MAXIFS($K:$K,$J:$J,J2,$K:$K,"<"&K2))) | R2: =IF(Q2="","",SUMIFS($N:$N,$J:$J,J2,$K:$K,Q2)) | S2: =IF(OR(R2="",R2=0,P2=""),"",P2/R2-1)
A3: 55666777000186 | B3: Sicrano Candidato — vereador, 2024 | C3: 8000 | D3: SOM E EVENTOS EXEMPLO LTDA | E3: Carro de som | F3: =IF(A3="","",IF(COUNTIF(Contratos!$A:$A,A3)+COUNTIF(Pagamentos!$A:$A,A3)=0,"não consta","SIM — contratos: "&COUNTIF(Contratos!$A:$A,A3)&"; pagamentos: "&COUNTIF(Pagamentos!$A:$A,A3))) -> não consta | G3: L006 | H3: EXEMPLO — exclua esta linha | J3: Sicrano Candidato | K3: 2026 | L3: Deputado estadual | M3: Casa em Cidade Exemplo | N3: 350000 | O3: L006 | P3: =IF(OR(J3="",K3=""),"",SUMIFS($N:$N,$J:$J,J3,$K:$K,K3)) -> 1550000 | Q3: =IF(OR(J3="",K3=""),"",IF(COUNTIFS($J:$J,J3,$K:$K,"<"&K3)=0,"",_xlfn.MAXIFS($K:$K,$J:$J,J3,$K:$K,"<"&K3))) -> 2024 | R3: =IF(Q3="","",SUMIFS($N:$N,$J:$J,J3,$K:$K,Q3)) -> 350000 | S3: =IF(OR(R3="",R3=0,P3=""),"",P3/R3-1) -> 3.4285714
A4: 77888999000186 | B4: Sicrano Candidato — deputado estadual, 2026 | C4: 22000 | D4: GRÁFICA EXEMPLO LTDA | E4: Santinhos | F4: =IF(A4="","",IF(COUNTIF(Contratos!$A:$A,A4)+COUNTIF(Pagamentos!$A:$A,A4)=0,"não consta","SIM — contratos: "&COUNTIF(Contratos!$A:$A,A4)&"; pagamentos: "&COUNTIF(Pagamentos!$A:$A,A4))) -> SIM — contratos: 1; pagamentos: 1 | G4: L006 | H4: EXEMPLO — exclua esta linha | J4: Sicrano Candidato | K4: 2026 | L4: Deputado estadual | M4: Fazenda em Outra Cidade | N4: 1200000 | O4: L006 | P4: =IF(OR(J4="",K4=""),"",SUMIFS($N:$N,$J:$J,J4,$K:$K,K4)) -> 1550000 | Q4: =IF(OR(J4="",K4=""),"",IF(COUNTIFS($J:$J,J4,$K:$K,"<"&K4)=0,"",_xlfn.MAXIFS($K:$K,$J:$J,J4,$K:$K,"<"&K4))) -> 2024 | R4: =IF(Q4="","",SUMIFS($N:$N,$J:$J,J4,$K:$K,Q4)) -> 350000 | S4: =IF(OR(R4="",R4=0,P4=""),"",P4/R4-1) -> 3.4285714
F5: =IF(A5="","",IF(COUNTIF(Contratos!$A:$A,A5)+COUNTIF(Pagamentos!$A:$A,A5)=0,"não consta","SIM — contratos: "&COUNTIF(Contratos!$A:$A,A5)&"; pagamentos: "&COUNTIF(Pagamentos!$A:$A,A5))) | P5: =IF(OR(J5="",K5=""),"",SUMIFS($N:$N,$J:$J,J5,$K:$K,K5)) | Q5: =IF(OR(J5="",K5=""),"",IF(COUNTIFS($J:$J,J5,$K:$K,"<"&K5)=0,"",_xlfn.MAXIFS($K:$K,$J:$J,J5,$K:$K,"<"&K5))) | R5: =IF(Q5="","",SUMIFS($N:$N,$J:$J,J5,$K:$K,Q5)) | S5: =IF(OR(R5="",R5=0,P5=""),"",P5/R5-1)
F6: =IF(A6="","",IF(COUNTIF(Contratos!$A:$A,A6)+COUNTIF(Pagamentos!$A:$A,A6)=0,"não consta","SIM — contratos: "&COUNTIF(Contratos!$A:$A,A6)&"; pagamentos: "&COUNTIF(Pagamentos!$A:$A,A6))) | P6: =IF(OR(J6="",K6=""),"",SUMIFS($N:$N,$J:$J,J6,$K:$K,K6)) | Q6: =IF(OR(J6="",K6=""),"",IF(COUNTIFS($J:$J,J6,$K:$K,"<"&K6)=0,"",_xlfn.MAXIFS($K:$K,$J:$J,J6,$K:$K,"<"&K6))) | R6: =IF(Q6="","",SUMIFS($N:$N,$J:$J,J6,$K:$K,Q6)) | S6: =IF(OR(R6="",R6=0,P6=""),"",P6/R6-1)
F7: =IF(A7="","",IF(COUNTIF(Contratos!$A:$A,A7)+COUNTIF(Pagamentos!$A:$A,A7)=0,"não consta","SIM — contratos: "&COUNTIF(Contratos!$A:$A,A7)&"; pagamentos: "&COUNTIF(Pagamentos!$A:$A,A7))) | P7: =IF(OR(J7="",K7=""),"",SUMIFS($N:$N,$J:$J,J7,$K:$K,K7)) | Q7: =IF(OR(J7="",K7=""),"",IF(COUNTIFS($J:$J,J7,$K:$K,"<"&K7)=0,"",_xlfn.MAXIFS($K:$K,$J:$J,J7,$K:$K,"<"&K7))) | R7: =IF(Q7="","",SUMIFS($N:$N,$J:$J,J7,$K:$K,Q7)) | S7: =IF(OR(R7="",R7=0,P7=""),"",P7/R7-1)
F8: =IF(A8="","",IF(COUNTIF(Contratos!$A:$A,A8)+COUNTIF(Pagamentos!$A:$A,A8)=0,"não consta","SIM — contratos: "&COUNTIF(Contratos!$A:$A,A8)&"; pagamentos: "&COUNTIF(Pagamentos!$A:$A,A8))) | P8: =IF(OR(J8="",K8=""),"",SUMIFS($N:$N,$J:$J,J8,$K:$K,K8)) | Q8: =IF(OR(J8="",K8=""),"",IF(COUNTIFS($J:$J,J8,$K:$K,"<"&K8)=0,"",_xlfn.MAXIFS($K:$K,$J:$J,J8,$K:$K,"<"&K8))) | R8: =IF(Q8="","",SUMIFS($N:$N,$J:$J,J8,$K:$K,Q8)) | S8: =IF(OR(R8="",R8=0,P8=""),"",P8/R8-1)
F9: =IF(A9="","",IF(COUNTIF(Contratos!$A:$A,A9)+COUNTIF(Pagamentos!$A:$A,A9)=0,"não consta","SIM — contratos: "&COUNTIF(Contratos!$A:$A,A9)&"; pagamentos: "&COUNTIF(Pagamentos!$A:$A,A9))) | P9: =IF(OR(J9="",K9=""),"",SUMIFS($N:$N,$J:$J,J9,$K:$K,K9)) | Q9: =IF(OR(J9="",K9=""),"",IF(COUNTIFS($J:$J,J9,$K:$K,"<"&K9)=0,"",_xlfn.MAXIFS($K:$K,$J:$J,J9,$K:$K,"<"&K9))) | R9: =IF(Q9="","",SUMIFS($N:$N,$J:$J,J9,$K:$K,Q9)) | S9: =IF(OR(R9="",R9=0,P9=""),"",P9/R9-1)
F10: =IF(A10="","",IF(COUNTIF(Contratos!$A:$A,A10)+COUNTIF(Pagamentos!$A:$A,A10)=0,"não consta","SIM — contratos: "&COUNTIF(Contratos!$A:$A,A10)&"; pagamentos: "&COUNTIF(Pagamentos!$A:$A,A10))) | P10: =IF(OR(J10="",K10=""),"",SUMIFS($N:$N,$J:$J,J10,$K:$K,K10)) | Q10: =IF(OR(J10="",K10=""),"",IF(COUNTIFS($J:$J,J10,$K:$K,"<"&K10)=0,"",_xlfn.MAXIFS($K:$K,$J:$J,J10,$K:$K,"<"&K10))) | R10: =IF(Q10="","",SUMIFS($N:$N,$J:$J,J10,$K:$K,Q10)) | S10: =IF(OR(R10="",R10=0,P10=""),"",P10/R10-1)
F11: =IF(A11="","",IF(COUNTIF(Contratos!$A:$A,A11)+COUNTIF(Pagamentos!$A:$A,A11)=0,"não consta","SIM — contratos: "&COUNTIF(Contratos!$A:$A,A11)&"; pagamentos: "&COUNTIF(Pagamentos!$A:$A,A11))) | P11: =IF(OR(J11="",K11=""),"",SUMIFS($N:$N,$J:$J,J11,$K:$K,K11)) | Q11: =IF(OR(J11="",K11=""),"",IF(COUNTIFS($J:$J,J11,$K:$K,"<"&K11)=0,"",_xlfn.MAXIFS($K:$K,$J:$J,J11,$K:$K,"<"&K11))) | R11: =IF(Q11="","",SUMIFS($N:$N,$J:$J,J11,$K:$K,Q11)) | S11: =IF(OR(R11="",R11=0,P11=""),"",P11/R11-1)
F12: =IF(A12="","",IF(COUNTIF(Contratos!$A:$A,A12)+COUNTIF(Pagamentos!$A:$A,A12)=0,"não consta","SIM — contratos: "&COUNTIF(Contratos!$A:$A,A12)&"; pagamentos: "&COUNTIF(Pagamentos!$A:$A,A12))) | P12: =IF(OR(J12="",K12=""),"",SUMIFS($N:$N,$J:$J,J12,$K:$K,K12)) | Q12: =IF(OR(J12="",K12=""),"",IF(COUNTIFS($J:$J,J12,$K:$K,"<"&K12)=0,"",_xlfn.MAXIFS($K:$K,$J:$J,J12,$K:$K,"<"&K12))) | R12: =IF(Q12="","",SUMIFS($N:$N,$J:$J,J12,$K:$K,Q12)) | S12: =IF(OR(R12="",R12=0,P12=""),"",P12/R12-1)
F13: =IF(A13="","",IF(COUNTIF(Contratos!$A:$A,A13)+COUNTIF(Pagamentos!$A:$A,A13)=0,"não consta","SIM — contratos: "&COUNTIF(Contratos!$A:$A,A13)&"; pagamentos: "&COUNTIF(Pagamentos!$A:$A,A13))) | P13: =IF(OR(J13="",K13=""),"",SUMIFS($N:$N,$J:$J,J13,$K:$K,K13)) | Q13: =IF(OR(J13="",K13=""),"",IF(COUNTIFS($J:$J,J13,$K:$K,"<"&K13)=0,"",_xlfn.MAXIFS($K:$K,$J:$J,J13,$K:$K,"<"&K13))) | R13: =IF(Q13="","",SUMIFS($N:$N,$J:$J,J13,$K:$K,Q13)) | S13: =IF(OR(R13="",R13=0,P13=""),"",P13/R13-1)
F14: =IF(A14="","",IF(COUNTIF(Contratos!$A:$A,A14)+COUNTIF(Pagamentos!$A:$A,A14)=0,"não consta","SIM — contratos: "&COUNTIF(Contratos!$A:$A,A14)&"; pagamentos: "&COUNTIF(Pagamentos!$A:$A,A14))) | P14: =IF(OR(J14="",K14=""),"",SUMIFS($N:$N,$J:$J,J14,$K:$K,K14)) | Q14: =IF(OR(J14="",K14=""),"",IF(COUNTIFS($J:$J,J14,$K:$K,"<"&K14)=0,"",_xlfn.MAXIFS($K:$K,$J:$J,J14,$K:$K,"<"&K14))) | R14: =IF(Q14="","",SUMIFS($N:$N,$J:$J,J14,$K:$K,Q14)) | S14: =IF(OR(R14="",R14=0,P14=""),"",P14/R14-1)
F15: =IF(A15="","",IF(COUNTIF(Contratos!$A:$A,A15)+COUNTIF(Pagamentos!$A:$A,A15)=0,"não consta","SIM — contratos: "&COUNTIF(Contratos!$A:$A,A15)&"; pagamentos: "&COUNTIF(Pagamentos!$A:$A,A15))) | P15: =IF(OR(J15="",K15=""),"",SUMIFS($N:$N,$J:$J,J15,$K:$K,K15)) | Q15: =IF(OR(J15="",K15=""),"",IF(COUNTIFS($J:$J,J15,$K:$K,"<"&K15)=0,"",_xlfn.MAXIFS($K:$K,$J:$J,J15,$K:$K,"<"&K15))) | R15: =IF(Q15="","",SUMIFS($N:$N,$J:$J,J15,$K:$K,Q15)) | S15: =IF(OR(R15="",R15=0,P15=""),"",P15/R15-1)
F16: =IF(A16="","",IF(COUNTIF(Contratos!$A:$A,A16)+COUNTIF(Pagamentos!$A:$A,A16)=0,"não consta","SIM — contratos: "&COUNTIF(Contratos!$A:$A,A16)&"; pagamentos: "&COUNTIF(Pagamentos!$A:$A,A16))) | P16: =IF(OR(J16="",K16=""),"",SUMIFS($N:$N,$J:$J,J16,$K:$K,K16)) | Q16: =IF(OR(J16="",K16=""),"",IF(COUNTIFS($J:$J,J16,$K:$K,"<"&K16)=0,"",_xlfn.MAXIFS($K:$K,$J:$J,J16,$K:$K,"<"&K16))) | R16: =IF(Q16="","",SUMIFS($N:$N,$J:$J,J16,$K:$K,Q16)) | S16: =IF(OR(R16="",R16=0,P16=""),"",P16/R16-1)
... F501: =IF(A501="","",IF(COUNTIF(Contratos!$A:$A,A501)+COUNTIF(Pagamentos!$A:$A,A501)=0,"não consta","SIM — contratos: "&COUNTIF(Contratos!$A:$A,A501)&"; pagamentos: "&COUNTIF(Pagamentos!$A:$A,A501))) | P501: =IF(OR(J501="",K501=""),"",SUMIFS($N:$N,$J:$J,J501,$K:$K,K501)) | Q501: =IF(OR(J501="",K501=""),"",IF(COUNTIFS($J:$J,J501,$K:$K,"<"&K501)=0,"",_xlfn.MAXIFS($K:$K,$J:$J,J501,$K:$K,"<"&K501))) | R501: =IF(Q501="","",SUMIFS($N:$N,$J:$J,J501,$K:$K,Q501)) | S501: =IF(OR(R501="",R501=0,P501=""),"",P501/R501-1)

Sheet Processos
A1: Número | B1: Classe | C1: Fase | D1: Última decisão | E1: Como escrever (auto) | F1: Tribunal ou órgão | G1: Assunto | H1: Parte ligada à pauta | I1: Data da última decisão | J1: Link | K1: Fonte (ID do Log) | L1: Observações
A2: 0000001-00.2026.8.99.0001 | B2: Ação civil de improbidade administrativa | C2: Réu em ação de improbidade (cível) | D2: Recebida a petição inicial; réus citados para contestar | E2: =IF(C2="","",IFERROR(INDEX(Listas!$S:$S,MATCH(C2,Listas!$R:$R,0)),"")) -> é réu em ação de improbidade administrativa, que é cível, não criminal | F2: Tribunal de Justiça | G2: Contratação direta de merenda escolar | H2: Alimentos Modelo Ltda | I2: 46154 | K2: L007 | L2: EXEMPLO — número fictício; exclua esta linha
A3: TC-0000/2026 | B3: Representação | C3: Auditoria de tribunal de contas com apontamento | D3: Área técnica apontou falta de pesquisa de preços na dispensa 045/2025 | E3: =IF(C3="","",IFERROR(INDEX(Listas!$S:$S,MATCH(C3,Listas!$R:$R,0)),"")) -> o [TCU ou TCE] apontou [achado] em auditoria, no processo [número]; é apontamento de controle, não condenação | F3: Tribunal de Contas do Estado | G3: Dispensa 045/2025 | H3: Secretaria Municipal de Educação | I3: 46266 | K3: L015 | L3: EXEMPLO — número fictício; exclua esta linha
E4: =IF(C4="","",IFERROR(INDEX(Listas!$S:$S,MATCH(C4,Listas!$R:$R,0)),""))
E5: =IF(C5="","",IFERROR(INDEX(Listas!$S:$S,MATCH(C5,Listas!$R:$R,0)),""))
E6: =IF(C6="","",IFERROR(INDEX(Listas!$S:$S,MATCH(C6,Listas!$R:$R,0)),""))
E7: =IF(C7="","",IFERROR(INDEX(Listas!$S:$S,MATCH(C7,Listas!$R:$R,0)),""))
E8: =IF(C8="","",IFERROR(INDEX(Listas!$S:$S,MATCH(C8,Listas!$R:$R,0)),""))
E9: =IF(C9="","",IFERROR(INDEX(Listas!$S:$S,MATCH(C9,Listas!$R:$R,0)),""))
E10: =IF(C10="","",IFERROR(INDEX(Listas!$S:$S,MATCH(C10,Listas!$R:$R,0)),""))
E11: =IF(C11="","",IFERROR(INDEX(Listas!$S:$S,MATCH(C11,Listas!$R:$R,0)),""))
E12: =IF(C12="","",IFERROR(INDEX(Listas!$S:$S,MATCH(C12,Listas!$R:$R,0)),""))
E13: =IF(C13="","",IFERROR(INDEX(Listas!$S:$S,MATCH(C13,Listas!$R:$R,0)),""))
E14: =IF(C14="","",IFERROR(INDEX(Listas!$S:$S,MATCH(C14,Listas!$R:$R,0)),""))
E15: =IF(C15="","",IFERROR(INDEX(Listas!$S:$S,MATCH(C15,Listas!$R:$R,0)),""))
... E201: =IF(C201="","",IFERROR(INDEX(Listas!$S:$S,MATCH(C201,Listas!$R:$R,0)),""))

Sheet Sites
A1: Site | B1: Empresa responsável | C1: Códigos | D1: Anúncios | E1: CNPJ da empresa responsável | F1: Contrato com o órgão | G1: Outros sites com o mesmo código | H1: Pergunta que a ligação levanta | I1: Fonte (ID do Log) | J1: Observações
A2: https://transparencia.cidadeexemplo.gov.br | B2: Sistemas Exemplo Ltda | C2: G-EXEMPLO01 | D2: Nenhum anúncio da prefeitura sobre merenda | E2: 88999000000186 | F2: Contrato 010/2024, no PNCP | G2: Nove prefeituras da região | H2: Por que as despesas de 2025 sumiram do portal? | I2: L014 | J2: EXEMPLO — exclua esta linha
A3: https://sicranocandidato.exemplo | B3: Agência Exemplo | C3: GTM-EXEMPLO2 | D3: Dois anúncios em 2025 sobre “merenda nas escolas”, pagos pelo gabinete | G3: Site da Câmara Municipal | H3: A agência da campanha também atende a Câmara? | I3: L016 | J3: EXEMPLO — exclua esta linha

Sheet Perfis
A1: Nome | B1: Rede | C1: Link | D1: Data de criação | E1: Cópia arquivada | F1: Tipo de perfil | G1: Pode monitorar? (auto) | H1: Operado de (país) | I1: Mudanças de nome | J1: Posts relevantes | K1: Fonte (ID do Log) | L1: Observações
A2: Sicrano Candidato (perfil do mandato) | B2: Instagram | C2: https://www.instagram.com/perfil-exemplo | D2: 42430 | E2: https://web.archive.org/web/2026/https://www.instagram.com/perfil-exemplo | F2: Pessoa pública, sobre o cargo | G2: =IF(F2="","",IF(F2="Cidadão comum","NÃO — monitorar a vida de cidadão comum não é apuração (OSINT 6.7)",IF(F2="Empresa","Só o que for público e ligado à pauta","Sim: perfil público, sobre o cargo ou a pauta"))) -> Sim: perfil público, sobre o cargo ou a pauta | H2: Brasil | I2: Nenhuma | J2: Post de 20/08/2025 sobre a merenda, arquivado | K2: L016 | L2: EXEMPLO — exclua esta linha
A3: Prefeitura de Cidade Exemplo | B3: Facebook | C3: https://www.facebook.com/pagina-exemplo | D3: 41031 | F3: Oficial (órgão ou mandato) | G3: =IF(F3="","",IF(F3="Cidadão comum","NÃO — monitorar a vida de cidadão comum não é apuração (OSINT 6.7)",IF(F3="Empresa","Só o que for público e ligado à pauta","Sim: perfil público, sobre o cargo ou a pauta"))) -> Sim: perfil público, sobre o cargo ou a pauta | H3: Brasil | I3: Mudou de nome em janeiro de 2025, com a nova gestão | K3: L016 | L3: EXEMPLO — exclua esta linha
A4: Maria Exemplo (perfil pessoal) | B4: Instagram | F4: Cidadão comum | G4: =IF(F4="","",IF(F4="Cidadão comum","NÃO — monitorar a vida de cidadão comum não é apuração (OSINT 6.7)",IF(F4="Empresa","Só o que for público e ligado à pauta","Sim: perfil público, sobre o cargo ou a pauta"))) -> NÃO — monitorar a vida de cidadão comum não é apuração (OSINT 6.7) | L4: EXEMPLO — isso não se faz: a linha mostra o alerta
G5: =IF(F5="","",IF(F5="Cidadão comum","NÃO — monitorar a vida de cidadão comum não é apuração (OSINT 6.7)",IF(F5="Empresa","Só o que for público e ligado à pauta","Sim: perfil público, sobre o cargo ou a pauta"))) | N5: Regra de observação | O5: Nesta pauta
G6: =IF(F6="","",IF(F6="Cidadão comum","NÃO — monitorar a vida de cidadão comum não é apuração (OSINT 6.7)",IF(F6="Empresa","Só o que for público e ligado à pauta","Sim: perfil público, sobre o cargo ou a pauta"))) | N6: Conta usada | O6: De pesquisa, identificada com o nome do canal
G7: =IF(F7="","",IF(F7="Cidadão comum","NÃO — monitorar a vida de cidadão comum não é apuração (OSINT 6.7)",IF(F7="Empresa","Só o que for público e ligado à pauta","Sim: perfil público, sobre o cargo ou a pauta"))) | N7: Não faço | O7: Curtir, seguir perfis pessoais, entrar em grupo fechado
G8: =IF(F8="","",IF(F8="Cidadão comum","NÃO — monitorar a vida de cidadão comum não é apuração (OSINT 6.7)",IF(F8="Empresa","Só o que for público e ligado à pauta","Sim: perfil público, sobre o cargo ou a pauta"))) | N8: Quem decide mudança | O8: Eu, por escrito, antes de mudar
G9: =IF(F9="","",IF(F9="Cidadão comum","NÃO — monitorar a vida de cidadão comum não é apuração (OSINT 6.7)",IF(F9="Empresa","Só o que for público e ligado à pauta","Sim: perfil público, sobre o cargo ou a pauta")))
G10: =IF(F10="","",IF(F10="Cidadão comum","NÃO — monitorar a vida de cidadão comum não é apuração (OSINT 6.7)",IF(F10="Empresa","Só o que for público e ligado à pauta","Sim: perfil público, sobre o cargo ou a pauta")))
G11: =IF(F11="","",IF(F11="Cidadão comum","NÃO — monitorar a vida de cidadão comum não é apuração (OSINT 6.7)",IF(F11="Empresa","Só o que for público e ligado à pauta","Sim: perfil público, sobre o cargo ou a pauta")))
G12: =IF(F12="","",IF(F12="Cidadão comum","NÃO — monitorar a vida de cidadão comum não é apuração (OSINT 6.7)",IF(F12="Empresa","Só o que for público e ligado à pauta","Sim: perfil público, sobre o cargo ou a pauta")))
G13: =IF(F13="","",IF(F13="Cidadão comum","NÃO — monitorar a vida de cidadão comum não é apuração (OSINT 6.7)",IF(F13="Empresa","Só o que for público e ligado à pauta","Sim: perfil público, sobre o cargo ou a pauta")))
G14: =IF(F14="","",IF(F14="Cidadão comum","NÃO — monitorar a vida de cidadão comum não é apuração (OSINT 6.7)",IF(F14="Empresa","Só o que for público e ligado à pauta","Sim: perfil público, sobre o cargo ou a pauta")))
G15: =IF(F15="","",IF(F15="Cidadão comum","NÃO — monitorar a vida de cidadão comum não é apuração (OSINT 6.7)",IF(F15="Empresa","Só o que for público e ligado à pauta","Sim: perfil público, sobre o cargo ou a pauta")))
G16: =IF(F16="","",IF(F16="Cidadão comum","NÃO — monitorar a vida de cidadão comum não é apuração (OSINT 6.7)",IF(F16="Empresa","Só o que for público e ligado à pauta","Sim: perfil público, sobre o cargo ou a pauta")))
G17: =IF(F17="","",IF(F17="Cidadão comum","NÃO — monitorar a vida de cidadão comum não é apuração (OSINT 6.7)",IF(F17="Empresa","Só o que for público e ligado à pauta","Sim: perfil público, sobre o cargo ou a pauta")))
G18: =IF(F18="","",IF(F18="Cidadão comum","NÃO — monitorar a vida de cidadão comum não é apuração (OSINT 6.7)",IF(F18="Empresa","Só o que for público e ligado à pauta","Sim: perfil público, sobre o cargo ou a pauta")))
G19: =IF(F19="","",IF(F19="Cidadão comum","NÃO — monitorar a vida de cidadão comum não é apuração (OSINT 6.7)",IF(F19="Empresa","Só o que for público e ligado à pauta","Sim: perfil público, sobre o cargo ou a pauta")))
G20: =IF(F20="","",IF(F20="Cidadão comum","NÃO — monitorar a vida de cidadão comum não é apuração (OSINT 6.7)",IF(F20="Empresa","Só o que for público e ligado à pauta","Sim: perfil público, sobre o cargo ou a pauta")))
... G201: =IF(F201="","",IF(F201="Cidadão comum","NÃO — monitorar a vida de cidadão comum não é apuração (OSINT 6.7)",IF(F201="Empresa","Só o que for público e ligado à pauta","Sim: perfil público, sobre o cargo ou a pauta")))

Sheet Listas
A1: Tipo de registro (Log) | B1: Tipo de evento (Linha do tempo) | C1: Fato, indício ou versão | D1: Esfera | E1: Sim ou não | F1: Resultado (LAI) | G1: Instância | H1: Modalidade | I1: Fase do gasto | J1: Cadastro de sanção | K1: Abrangência da sanção | L1: Tipo de sanção | M1: Já está publicado? | N1: Probabilidade (e risco para a fonte) | O1: Impacto | P1: Combinado com a fonte | Q1: Tipo de perfil | R1: Fase processual | S1: Como escrever (aula 5.2)
A2: Documento público baixado | B2: Emenda ou transferência | C2: Fato | D2: Federal | E2: Sim | F2: Atendido | G2: Pedido | H2: Pregão | I2: Empenho | J2: CEIS | K2: Só no ente que puniu | L2: Impedimento de licitar e contratar | M2: Sim | N2: baixa | O2: baixo | P2: On | Q2: Oficial (órgão ou mandato) | R2: Enviado para apuração (PGR, MP ou PF) | S2: o caso foi enviado [à PGR, ao Ministério Público ou à Polícia Federal] para apuração, o que ainda não é inquérito
A3: Documento recebido | B3: Empresa | C3: Indício | D3: Estadual | E3: Não | F3: Atendido em parte | G3: 1ª instância | H3: Concorrência | I3: Liquidação | J3: CNEP | K3: Todos os entes | L3: Declaração de inidoneidade | M3: Não | N3: média | O3: médio | P3: Off | Q3: Pessoa pública, sobre o cargo | R3: Investigação (inquérito ou procedimento) | S3: é investigado em [inquérito ou procedimento] no [órgão]
A4: Base de dados | B4: Contrato ou aditivo | C4: Versão | D4: Municipal | F4: Negado | G4: 2ª instância | H4: Concurso | I4: Pagamento | J4: CEPIM | K4: Não informada | L4: Suspensão | M4: Em parte | N4: alta | O4: alto | P4: Background | Q4: Empresa | R4: Indiciado | S4: foi indiciado pela [Polícia Civil ou Federal] em [data]
A5: Pedido LAI | B5: Pagamento | G5: CGU | H5: Leilão | J5: Outro | L5: Multa | M5: Talvez | P5: Ainda não combinado | Q5: Cidadão comum | R5: Denunciado (denúncia ainda não recebida) | S5: foi denunciado pelo Ministério Público por [crime]
A6: Resposta de órgão | B6: Ato no diário oficial | G6: CMRI | H6: Diálogo competitivo | L6: Outra | R6: Réu em ação penal (denúncia recebida) | S6: é réu em ação penal por [crime]
A7: Recurso ou reclamação LAI | B7: Nomeação ou exoneração | G7: Reclamação | H7: Dispensa | L7: Não consta | R7: Prisão preventiva ou temporária | S7: está preso [preventiva ou temporariamente], o que não é condenação
A8: Página arquivada | B8: Campanha ou eleição | H8: Inexigibilidade | R8: Condenado em 1ª instância | S8: foi condenado em primeira instância e pode recorrer
A9: Monitoramento de página | B9: Auditoria ou controle | H9: Adesão a ata | R9: Condenado em 2ª instância | S9: foi condenado em segunda instância e ainda pode recorrer
A10: Transcrição ou OCR | B10: Processo judicial | H10: Tomada de preços (lei antiga) | R10: Condenação definitiva (trânsito em julgado) | S10: foi condenado em decisão definitiva, da qual não cabe mais recurso
A11: Pedido de posicionamento | B11: Sanção | H11: Convite (lei antiga) | R11: Absolvido | S11: foi absolvido [em primeira instância ou em decisão definitiva]
A12: Resposta do citado | B12: Reportagem | H12: Outra | R12: Arquivado | S12: a investigação foi arquivada
A13: Pedido de resposta | B13: Nota ou declaração | R13: Acordo de não persecução penal | S13: fez acordo com o Ministério Público, no qual admitiu os fatos, para não ser processado
A14: Entrevista ou conversa | B14: Imagem de satélite ou foto | R14: Réu em ação de improbidade (cível) | S14: é réu em ação de improbidade administrativa, que é cível, não criminal
A15: Manifesto de hashes | B15: Pedido LAI | R15: Réu em outra ação cível | S15: é réu em ação cível, não criminal
A16: Frase de método | B16: Pedido de posicionamento | R16: Auditoria de tribunal de contas com apontamento | S16: o [TCU ou TCE] apontou [achado] em auditoria, no processo [número]; é apontamento de controle, não condenação
A17: Outro | B17: Publicação | R17: Tomada de contas especial | S17: é alvo de tomada de contas especial no [TCU ou TCE], processo administrativo que calcula o prejuízo e cobra de quem responde; não é processo criminal
B18: Outro | R18: Contas julgadas irregulares (tribunal de contas) | S18: teve as contas julgadas irregulares pelo [TCU ou TCE], em decisão administrativa [da qual ainda cabe recurso ou definitiva]
R19: Ação sobre a regra no STF (ADI ou ADPF) | S19: o tema é discutido no STF na [ADI ou ADPF] [número], ação sobre a regra, em que ninguém é réu
